Workbook
Name AD21AF348: #REF!
Name AD21AF348: #REF!

Sheet ICSE
A1: Paper ID | B1: Paper Title | C1: Year | D1: Successfully passed AE | E1: Artifacts Available badge | F1: Functional - Artifacts Evaluated badge | G1: Reusable - Artifacts Evaluated badge | H1: Results Replicated - Results Validated badge | I1: Results Reproduced - Results Validated badge | J1: Other badge | K1: Artifact link | L1: Footnote | M1: References | N1: Introduction | O1: Conclusion | P1: Highlight | Q1: Specific section or subsection | R1: Other Place | S1: Where is talking about the link? | T1: Artifact link(s) | U1: ="All artifact links whitout repetition - column "&SUBSTITUTE(ADDRESS(ROW(T1),COLUMN(T1),4),1,"")&" for artifact sharing (without real link)" -> All artifact links whitout repetition - column T for artifact sharing (without real link) | V1: Publicly available | W1: Not available | X1: Restrict access | Y1: No links | Z1: ="Status of the links in 02/24/2024 - "&SUBSTITUTE(ADDRESS(ROW(U1),COLUMN(U1),4),1,"") -> Status of the links in 02/24/2024 - U | AA1: # of different links | AB1: University domain | AC1: unique identifier | AD1: Is there a statement? | AE1: Statements for non-disclosure or partial disclosure of the research artifacts | AF1: Statements 1 | AG1: Statements 2 | AH1: Statements 3 | AI1: ="All statement labels "&SUBSTITUTE(ADDRESS(ROW(AF1),COLUMN(AF1),4),1,"")&" + "&SUBSTITUTE(ADDRESS(ROW(AG1),COLUMN(AG1),4),1,"")&" + "&SUBSTITUTE(ADDRESS(ROW(AH1),COLUMN(AH1),4),1,"") -> All statement labels AF + AG + AH | AJ1: ="Link and statement analysis "&SUBSTITUTE(ADDRESS(ROW(K1),COLUMN(K1),4),1,"")&" and "&SUBSTITUTE(ADDRESS(ROW(AD1),COLUMN(AD1),4),1,"") -> Link and statement analysis K and AD | AK1: Paper download | AL1: Track | AM1: Paper ID
A2: 1844 | B2: Cowboys, ankle sprains, and keepers of quality: how is video game development different from software development? | C2: 2014 | D2: No | E2: - | F2: - | G2: - | H2: - | I2: - | J2: - | K2: Yes | L2: Yes | M2: Yes | N2: No | O2: No | P2: No | Q2: No | R2: Yes | S2: - FN 1 - 3. METHODOLOGY - [38] 4. RESULTS | T2: http://people.engr.ncsu.edu/ermurph3/experiments/Games.pdf > Microsoft Research (MSR-TR-2014-24) - real link: https://www.microsoft.com/en-us/research/wp-content/uploads/2016/02/MSR-TR-2014-24.pdf | U2: http://people.engr.ncsu.edu/ermurph3/experiments/Games.pdf Microsoft Research (MSR-TR-2014-24) - real link: https://www.microsoft.com/en-us/research/wp-content/uploads/2016/02/MSR-TR-2014-24.pdf | V2: =IF(lenb(SUBSTITUTE($Z2,V$1&" (1)",""))<lenb($Z2),1,IF(lenb(SUBSTITUTE($Z2,V$1&" (2)",""))<lenb($Z2),2,IF(lenb(SUBSTITUTE($Z2,V$1&" (3)",""))<lenb($Z2),3,IF(lenb(SUBSTITUTE($Z2,V$1&" (4)",""))<lenb($Z2),4,IF(lenb(SUBSTITUTE($Z2,V$1&" (5)",""))<lenb($Z2),5,IF(lenb(SUBSTITUTE($Z2,V$1&" (6)",""))<lenb($Z2),6,IF(lenb(SUBSTITUTE($Z2,V$1&" (7)",""))<lenb($Z2),1,IF(lenb(SUBSTITUTE($Z2,V$1&" (8)",""))<lenb($Z2),8,IF(lenb(SUBSTITUTE($Z2,V$1&" (9)",""))<lenb($Z2),9,IF(lenb(SUBSTITUTE($Z2,V$1&" (10)",""))<lenb($Z2),10,IF(lenb(SUBSTITUTE($Z2,V$1,""))<lenb($Z2),"ERROR",IF($Z2=$Y$1,"-",0)))))))))))) -> 1 | W2: =IF(lenb(SUBSTITUTE($Z2,W$1&" (1)",""))<lenb($Z2),1,IF(lenb(SUBSTITUTE($Z2,W$1&" (2)",""))<lenb($Z2),2,IF(lenb(SUBSTITUTE($Z2,W$1&" (3)",""))<lenb($Z2),3,IF(lenb(SUBSTITUTE($Z2,W$1&" (4)",""))<lenb($Z2),4,IF(lenb(SUBSTITUTE($Z2,W$1&" (5)",""))<lenb($Z2),5,IF(lenb(SUBSTITUTE($Z2,W$1&" (6)",""))<lenb($Z2),6,IF(lenb(SUBSTITUTE($Z2,W$1&" (7)",""))<lenb($Z2),1,IF(lenb(SUBSTITUTE($Z2,W$1&" (8)",""))<lenb($Z2),8,IF(lenb(SUBSTITUTE($Z2,W$1&" (9)",""))<lenb($Z2),9,IF(lenb(SUBSTITUTE($Z2,W$1&" (10)",""))<lenb($Z2),10,IF(lenb(SUBSTITUTE($Z2,W$1,""))<lenb($Z2),"ERROR",IF($Z2=$Y$1,"-",0)))))))))))) -> 1 | X2: =IF(lenb(SUBSTITUTE($Z2,X$1&" (1)",""))<lenb($Z2),1,IF(lenb(SUBSTITUTE($Z2,X$1&" (2)",""))<lenb($Z2),2,IF(lenb(SUBSTITUTE($Z2,X$1&" (3)",""))<lenb($Z2),3,IF(lenb(SUBSTITUTE($Z2,X$1&" (4)",""))<lenb($Z2),4,IF(lenb(SUBSTITUTE($Z2,X$1&" (5)",""))<lenb($Z2),5,IF(lenb(SUBSTITUTE($Z2,X$1&" (6)",""))<lenb($Z2),6,IF(lenb(SUBSTITUTE($Z2,X$1&" (7)",""))<lenb($Z2),1,IF(lenb(SUBSTITUTE($Z2,X$1&" (8)",""))<lenb($Z2),8,IF(lenb(SUBSTITUTE($Z2,X$1&" (9)",""))<lenb($Z2),9,IF(lenb(SUBSTITUTE($Z2,X$1&" (10)",""))<lenb($Z2),10,IF(lenb(SUBSTITUTE($Z2,X$1,""))<lenb($Z2),"ERROR",IF($Z2=$Y$1,"-",0)))))))))))) -> 0 | Y2: =IF(Z2=Y$1,1,"-") -> - | Z2: Not available (1) - Broken link. Publicly available (1) | AA2: =ifs(U2="","",U2="-",0,U2="Erro",0,U2<>"",LEN(U2)-LEN(SUBSTITUTE(U2,CHAR(10),""))+1) -> 2 | AB2: =COUNTIFS(Links!B:B,"ICSE",Links!C:C,A2,Links!AD:AD,1) -> 1 | AC2: No | AD2: =ifs(AE2="None.","No",AE2="-","No",AND(AE2<>"None.",AE2<>"-"),"Yes") -> No | AE2: - | AF2: ---- | AG2: ---- | AH2: ---- | AI2: =IF(AH2="----",IF(AG2="----",IF(AF2="----","----",AF2),AF2&CHAR(10)&AG2),AF2&CHAR(10)&AG2&CHAR(10)&AH2) -> ---- | AJ2: =IFERROR( if(and(K2="Yes",AD2="No"),"Paper has link but no statement", if(and(K2="No",AD2="No"),"Paper has no link and no statement", if(and(K2="Yes",AD2="Yes"),"Paper has link and statement", if(and(K2="No",AD2="Yes"),"Paper has no link but has statement","")))),"") -> Paper has link but no statement | AK2: 45035 | AL2: Technical | AM2: ="[IP"&TEXT(A2,"0000")&"]" -> [IP1844]
A3: 1845 | B3: Analyze this! 145 questions for data scientists in software engineering | C3: 2014 | D3: Yes | E3: No | F3: No | G3: No | H3: Yes | I3: No | J3: - | K3: Yes | L3: No | M3: Yes | N3: Yes | O3: Yes | P3: No | Q3: No | R3: Yes | S3: [11] - 1. INTRODUCTION - 3. METHODOLOGY * (4x) - 6. CONCLUSION | T3: http://aka.ms/145Questions | U3: http://aka.ms/145Questions | V3: =IF(lenb(SUBSTITUTE($Z3,V$1&" (1)",""))<lenb($Z3),1,IF(lenb(SUBSTITUTE($Z3,V$1&" (2)",""))<lenb($Z3),2,IF(lenb(SUBSTITUTE($Z3,V$1&" (3)",""))<lenb($Z3),3,IF(lenb(SUBSTITUTE($Z3,V$1&" (4)",""))<lenb($Z3),4,IF(lenb(SUBSTITUTE($Z3,V$1&" (5)",""))<lenb($Z3),5,IF(lenb(SUBSTITUTE($Z3,V$1&" (6)",""))<lenb($Z3),6,IF(lenb(SUBSTITUTE($Z3,V$1&" (7)",""))<lenb($Z3),1,IF(lenb(SUBSTITUTE($Z3,V$1&" (8)",""))<lenb($Z3),8,IF(lenb(SUBSTITUTE($Z3,V$1&" (9)",""))<lenb($Z3),9,IF(lenb(SUBSTITUTE($Z3,V$1&" (10)",""))<lenb($Z3),10,IF(lenb(SUBSTITUTE($Z3,V$1,""))<lenb($Z3),"ERROR",IF($Z3=$Y$1,"-",0)))))))))))) -> 0 | W3: =IF(lenb(SUBSTITUTE($Z3,W$1&" (1)",""))<lenb($Z3),1,IF(lenb(SUBSTITUTE($Z3,W$1&" (2)",""))<lenb($Z3),2,IF(lenb(SUBSTITUTE($Z3,W$1&" (3)",""))<lenb($Z3),3,IF(lenb(SUBSTITUTE($Z3,W$1&" (4)",""))<lenb($Z3),4,IF(lenb(SUBSTITUTE($Z3,W$1&" (5)",""))<lenb($Z3),5,IF(lenb(SUBSTITUTE($Z3,W$1&" (6)",""))<lenb($Z3),6,IF(lenb(SUBSTITUTE($Z3,W$1&" (7)",""))<lenb($Z3),1,IF(lenb(SUBSTITUTE($Z3,W$1&" (8)",""))<lenb($Z3),8,IF(lenb(SUBSTITUTE($Z3,W$1&" (9)",""))<lenb($Z3),9,IF(lenb(SUBSTITUTE($Z3,W$1&" (10)",""))<lenb($Z3),10,IF(lenb(SUBSTITUTE($Z3,W$1,""))<lenb($Z3),"ERROR",IF($Z3=$Y$1,"-",0)))))))))))) -> 1 | X3: =IF(lenb(SUBSTITUTE($Z3,X$1&" (1)",""))<lenb($Z3),1,IF(lenb(SUBSTITUTE($Z3,X$1&" (2)",""))<lenb($Z3),2,IF(lenb(SUBSTITUTE($Z3,X$1&" (3)",""))<lenb($Z3),3,IF(lenb(SUBSTITUTE($Z3,X$1&" (4)",""))<lenb($Z3),4,IF(lenb(SUBSTITUTE($Z3,X$1&" (5)",""))<lenb($Z3),5,IF(lenb(SUBSTITUTE($Z3,X$1&" (6)",""))<lenb($Z3),6,IF(lenb(SUBSTITUTE($Z3,X$1&" (7)",""))<lenb($Z3),1,IF(lenb(SUBSTITUTE($Z3,X$1&" (8)",""))<lenb($Z3),8,IF(lenb(SUBSTITUTE($Z3,X$1&" (9)",""))<lenb($Z3),9,IF(lenb(SUBSTITUTE($Z3,X$1&" (10)",""))<lenb($Z3),10,IF(lenb(SUBSTITUTE($Z3,X$1,""))<lenb($Z3),"ERROR",IF($Z3=$Y$1,"-",0)))))))))))) -> 0 | Y3: =IF(Z3=Y$1,1,"-") -> - | Z3: Not available (1) - Broken link. | AA3: =ifs(U3="","",U3="-",0,U3="Erro",0,U3<>"",LEN(U3)-LEN(SUBSTITUTE(U3,CHAR(10),""))+1) -> 1 | AB3: =COUNTIFS(Links!B:B,"ICSE",Links!C:C,A3,Links!AD:AD,1) -> 0 | AC3: No | AD3: =ifs(AE3="None.","No",AE3="-","No",AND(AE3<>"None.",AE3<>"-"),"Yes") -> No | AE3: - | AF3: ---- | AG3: ---- | AH3: ---- | AI3: =IF(AH3="----",IF(AG3="----",IF(AF3="----","----",AF3),AF3&CHAR(10)&AG3),AF3&CHAR(10)&AG3&CHAR(10)&AH3) -> ---- | AJ3: =IFERROR( if(and(K3="Yes",AD3="No"),"Paper has link but no statement", if(and(K3="No",AD3="No"),"Paper has no link and no statement", if(and(K3="Yes",AD3="Yes"),"Paper has link and statement", if(and(K3="No",AD3="Yes"),"Paper has no link but has statement","")))),"") -> Paper has link but no statement | AK3: 45035 | AL3: Technical | AM3: ="[IP"&TEXT(A3,"0000")&"]" -> [IP1845]
A4: 1846 | B4: The dimensions of software engineering success | C4: 2014 | D4: No | E4: - | F4: - | G4: - | H4: - | I4: - | J4: - | K4: No | L4: - | M4: - | N4: - | O4: - | P4: - | Q4: - | R4: - | S4: - | T4: - | U4: - | V4: =IF(lenb(SUBSTITUTE($Z4,V$1&" (1)",""))<lenb($Z4),1,IF(lenb(SUBSTITUTE($Z4,V$1&" (2)",""))<lenb($Z4),2,IF(lenb(SUBSTITUTE($Z4,V$1&" (3)",""))<lenb($Z4),3,IF(lenb(SUBSTITUTE($Z4,V$1&" (4)",""))<lenb($Z4),4,IF(lenb(SUBSTITUTE($Z4,V$1&" (5)",""))<lenb($Z4),5,IF(lenb(SUBSTITUTE($Z4,V$1&" (6)",""))<lenb($Z4),6,IF(lenb(SUBSTITUTE($Z4,V$1&" (7)",""))<lenb($Z4),1,IF(lenb(SUBSTITUTE($Z4,V$1&" (8)",""))<lenb($Z4),8,IF(lenb(SUBSTITUTE($Z4,V$1&" (9)",""))<lenb($Z4),9,IF(lenb(SUBSTITUTE($Z4,V$1&" (10)",""))<lenb($Z4),10,IF(lenb(SUBSTITUTE($Z4,V$1,""))<lenb($Z4),"ERROR",IF($Z4=$Y$1,"-",0)))))))))))) -> - | W4: =IF(lenb(SUBSTITUTE($Z4,W$1&" (1)",""))<lenb($Z4),1,IF(lenb(SUBSTITUTE($Z4,W$1&" (2)",""))<lenb($Z4),2,IF(lenb(SUBSTITUTE($Z4,W$1&" (3)",""))<lenb($Z4),3,IF(lenb(SUBSTITUTE($Z4,W$1&" (4)",""))<lenb($Z4),4,IF(lenb(SUBSTITUTE($Z4,W$1&" (5)",""))<lenb($Z4),5,IF(lenb(SUBSTITUTE($Z4,W$1&" (6)",""))<lenb($Z4),6,IF(lenb(SUBSTITUTE($Z4,W$1&" (7)",""))<lenb($Z4),1,IF(lenb(SUBSTITUTE($Z4,W$1&" (8)",""))<lenb($Z4),8,IF(lenb(SUBSTITUTE($Z4,W$1&" (9)",""))<lenb($Z4),9,IF(lenb(SUBSTITUTE($Z4,W$1&" (10)",""))<lenb($Z4),10,IF(lenb(SUBSTITUTE($Z4,W$1,""))<lenb($Z4),"ERROR",IF($Z4=$Y$1,"-",0)))))))))))) -> - | X4: =IF(lenb(SUBSTITUTE($Z4,X$1&" (1)",""))<lenb($Z4),1,IF(lenb(SUBSTITUTE($Z4,X$1&" (2)",""))<lenb($Z4),2,IF(lenb(SUBSTITUTE($Z4,X$1&" (3)",""))<lenb($Z4),3,IF(lenb(SUBSTITUTE($Z4,X$1&" (4)",""))<lenb($Z4),4,IF(lenb(SUBSTITUTE($Z4,X$1&" (5)",""))<lenb($Z4),5,IF(lenb(SUBSTITUTE($Z4,X$1&" (6)",""))<lenb($Z4),6,IF(lenb(SUBSTITUTE($Z4,X$1&" (7)",""))<lenb($Z4),1,IF(lenb(SUBSTITUTE($Z4,X$1&" (8)",""))<lenb($Z4),8,IF(lenb(SUBSTITUTE($Z4,X$1&" (9)",""))<lenb($Z4),9,IF(lenb(SUBSTITUTE($Z4,X$1&" (10)",""))<lenb($Z4),10,IF(lenb(SUBSTITUTE($Z4,X$1,""))<lenb($Z4),"ERROR",IF($Z4=$Y$1,"-",0)))))))))))) -> - | Y4: =IF(Z4=Y$1,1,"-") -> 1 | Z4: No links | AA4: =ifs(U4="","",U4="-",0,U4="Erro",0,U4<>"",LEN(U4)-LEN(SUBSTITUTE(U4,CHAR(10),""))+1) -> 0 | AB4: =COUNTIFS(Links!B:B,"ICSE",Links!C:C,A4,Links!AD:AD,1) -> 0 | AC4: - | AD4: =ifs(AE4="None.","No",AE4="-","No",AND(AE4<>"None.",AE4<>"-"),"Yes") -> No | AE4: - | AF4: ---- | AG4: ---- | AH4: ---- | AI4: =IF(AH4="----",IF(AG4="----",IF(AF4="----","----",AF4),AF4&CHAR(10)&AG4),AF4&CHAR(10)&AG4&CHAR(10)&AH4) -> ---- | AJ4: =IFERROR( if(and(K4="Yes",AD4="No"),"Paper has link but no statement", if(and(K4="No",AD4="No"),"Paper has no link and no statement", if(and(K4="Yes",AD4="Yes"),"Paper has link and statement", if(and(K4="No",AD4="Yes"),"Paper has no link but has statement","")))),"") -> Paper has no link and no statement | AK4: 45035 | AL4: Technical | AM4: ="[IP"&TEXT(A4,"0000")&"]" -> [IP1846]
A5: 1847 | B5: How do professionals perceive legacy systems and software modernization? | C5: 2014 | D5: No | E5: - | F5: - | G5: - | H5: - | I5: - | J5: - | K5: Yes | L5: Yes | M5: Yes | N5: No | O5: No | P5: No | Q5: No | R5: Yes | S5: - FN 2 - 2. STUDY DESIGN - FN 3 - 4. DISCUSSION - [6] 2. STUDY DESIGN | T5: http://www.servicifi.org > TR UU-CS-2014-004 - real link: https://www.cs.uu.nl/research/techreps/UU-CS-2014-004.html | U5: http://www.servicifi.org TR UU-CS-2014-004 - real link: https://www.cs.uu.nl/research/techreps/UU-CS-2014-004.html | V5: =IF(lenb(SUBSTITUTE($Z5,V$1&" (1)",""))<lenb($Z5),1,IF(lenb(SUBSTITUTE($Z5,V$1&" (2)",""))<lenb($Z5),2,IF(lenb(SUBSTITUTE($Z5,V$1&" (3)",""))<lenb($Z5),3,IF(lenb(SUBSTITUTE($Z5,V$1&" (4)",""))<lenb($Z5),4,IF(lenb(SUBSTITUTE($Z5,V$1&" (5)",""))<lenb($Z5),5,IF(lenb(SUBSTITUTE($Z5,V$1&" (6)",""))<lenb($Z5),6,IF(lenb(SUBSTITUTE($Z5,V$1&" (7)",""))<lenb($Z5),1,IF(lenb(SUBSTITUTE($Z5,V$1&" (8)",""))<lenb($Z5),8,IF(lenb(SUBSTITUTE($Z5,V$1&" (9)",""))<lenb($Z5),9,IF(lenb(SUBSTITUTE($Z5,V$1&" (10)",""))<lenb($Z5),10,IF(lenb(SUBSTITUTE($Z5,V$1,""))<lenb($Z5),"ERROR",IF($Z5=$Y$1,"-",0)))))))))))) -> 1 | W5: =IF(lenb(SUBSTITUTE($Z5,W$1&" (1)",""))<lenb($Z5),1,IF(lenb(SUBSTITUTE($Z5,W$1&" (2)",""))<lenb($Z5),2,IF(lenb(SUBSTITUTE($Z5,W$1&" (3)",""))<lenb($Z5),3,IF(lenb(SUBSTITUTE($Z5,W$1&" (4)",""))<lenb($Z5),4,IF(lenb(SUBSTITUTE($Z5,W$1&" (5)",""))<lenb($Z5),5,IF(lenb(SUBSTITUTE($Z5,W$1&" (6)",""))<lenb($Z5),6,IF(lenb(SUBSTITUTE($Z5,W$1&" (7)",""))<lenb($Z5),1,IF(lenb(SUBSTITUTE($Z5,W$1&" (8)",""))<lenb($Z5),8,IF(lenb(SUBSTITUTE($Z5,W$1&" (9)",""))<lenb($Z5),9,IF(lenb(SUBSTITUTE($Z5,W$1&" (10)",""))<lenb($Z5),10,IF(lenb(SUBSTITUTE($Z5,W$1,""))<lenb($Z5),"ERROR",IF($Z5=$Y$1,"-",0)))))))))))) -> 1 | X5: =IF(lenb(SUBSTITUTE($Z5,X$1&" (1)",""))<lenb($Z5),1,IF(lenb(SUBSTITUTE($Z5,X$1&" (2)",""))<lenb($Z5),2,IF(lenb(SUBSTITUTE($Z5,X$1&" (3)",""))<lenb($Z5),3,IF(lenb(SUBSTITUTE($Z5,X$1&" (4)",""))<lenb($Z5),4,IF(lenb(SUBSTITUTE($Z5,X$1&" (5)",""))<lenb($Z5),5,IF(lenb(SUBSTITUTE($Z5,X$1&" (6)",""))<lenb($Z5),6,IF(lenb(SUBSTITUTE($Z5,X$1&" (7)",""))<lenb($Z5),1,IF(lenb(SUBSTITUTE($Z5,X$1&" (8)",""))<lenb($Z5),8,IF(lenb(SUBSTITUTE($Z5,X$1&" (9)",""))<lenb($Z5),9,IF(lenb(SUBSTITUTE($Z5,X$1&" (10)",""))<lenb($Z5),10,IF(lenb(SUBSTITUTE($Z5,X$1,""))<lenb($Z5),"ERROR",IF($Z5=$Y$1,"-",0)))))))))))) -> 0 | Y5: =IF(Z5=Y$1,1,"-") -> - | Z5: Not available (1) - Broken link. Publicly available (1) | AA5: =ifs(U5="","",U5="-",0,U5="Erro",0,U5<>"",LEN(U5)-LEN(SUBSTITUTE(U5,CHAR(10),""))+1) -> 2 | AB5: =COUNTIFS(Links!B:B,"ICSE",Links!C:C,A5,Links!AD:AD,1) -> 1 | AC5: No | AD5: =ifs(AE5="None.","No",AE5="-","No",AND(AE5<>"None.",AE5<>"-"),"Yes") -> No | AE5: - | AF5: ---- | AG5: ---- | AH5: ---- | AI5: =IF(AH5="----",IF(AG5="----",IF(AF5="----","----",AF5),AF5&CHAR(10)&AG5),AF5&CHAR(10)&AG5&CHAR(10)&AH5) -> ---- | AJ5: =IFERROR( if(and(K5="Yes",AD5="No"),"Paper has link but no statement", if(and(K5="No",AD5="No"),"Paper has no link and no statement", if(and(K5="Yes",AD5="Yes"),"Paper has link and statement", if(and(K5="No",AD5="Yes"),"Paper has no link but has statement","")))),"") -> Paper has link but no statement | AK5: 45035 | AL5: Technical | AM5: ="[IP"&TEXT(A5,"0000")&"]" -> [IP1847]
A6: 1848 | B6: SimRT: an automated framework to support regression testing for data races | C6: 2014 | D6: No | E6: - | F6: - | G6: - | H6: - | I6: - | J6: - | K6: No | L6: - | M6: - | N6: - | O6: - | P6: - | Q6: - | R6: - | S6: - | T6: - | U6: - | V6: =IF(lenb(SUBSTITUTE($Z6,V$1&" (1)",""))<lenb($Z6),1,IF(lenb(SUBSTITUTE($Z6,V$1&" (2)",""))<lenb($Z6),2,IF(lenb(SUBSTITUTE($Z6,V$1&" (3)",""))<lenb($Z6),3,IF(lenb(SUBSTITUTE($Z6,V$1&" (4)",""))<lenb($Z6),4,IF(lenb(SUBSTITUTE($Z6,V$1&" (5)",""))<lenb($Z6),5,IF(lenb(SUBSTITUTE($Z6,V$1&" (6)",""))<lenb($Z6),6,IF(lenb(SUBSTITUTE($Z6,V$1&" (7)",""))<lenb($Z6),1,IF(lenb(SUBSTITUTE($Z6,V$1&" (8)",""))<lenb($Z6),8,IF(lenb(SUBSTITUTE($Z6,V$1&" (9)",""))<lenb($Z6),9,IF(lenb(SUBSTITUTE($Z6,V$1&" (10)",""))<lenb($Z6),10,IF(lenb(SUBSTITUTE($Z6,V$1,""))<lenb($Z6),"ERROR",IF($Z6=$Y$1,"-",0)))))))))))) -> - | W6: =IF(lenb(SUBSTITUTE($Z6,W$1&" (1)",""))<lenb($Z6),1,IF(lenb(SUBSTITUTE($Z6,W$1&" (2)",""))<lenb($Z6),2,IF(lenb(SUBSTITUTE($Z6,W$1&" (3)",""))<lenb($Z6),3,IF(lenb(SUBSTITUTE($Z6,W$1&" (4)",""))<lenb($Z6),4,IF(lenb(SUBSTITUTE($Z6,W$1&" (5)",""))<lenb($Z6),5,IF(lenb(SUBSTITUTE($Z6,W$1&" (6)",""))<lenb($Z6),6,IF(lenb(SUBSTITUTE($Z6,W$1&" (7)",""))<lenb($Z6),1,IF(lenb(SUBSTITUTE($Z6,W$1&" (8)",""))<lenb($Z6),8,IF(lenb(SUBSTITUTE($Z6,W$1&" (9)",""))<lenb($Z6),9,IF(lenb(SUBSTITUTE($Z6,W$1&" (10)",""))<lenb($Z6),10,IF(lenb(SUBSTITUTE($Z6,W$1,""))<lenb($Z6),"ERROR",IF($Z6=$Y$1,"-",0)))))))))))) -> - | X6: =IF(lenb(SUBSTITUTE($Z6,X$1&" (1)",""))<lenb($Z6),1,IF(lenb(SUBSTITUTE($Z6,X$1&" (2)",""))<lenb($Z6),2,IF(lenb(SUBSTITUTE($Z6,X$1&" (3)",""))<lenb($Z6),3,IF(lenb(SUBSTITUTE($Z6,X$1&" (4)",""))<lenb($Z6),4,IF(lenb(SUBSTITUTE($Z6,X$1&" (5)",""))<lenb($Z6),5,IF(lenb(SUBSTITUTE($Z6,X$1&" (6)",""))<lenb($Z6),6,IF(lenb(SUBSTITUTE($Z6,X$1&" (7)",""))<lenb($Z6),1,IF(lenb(SUBSTITUTE($Z6,X$1&" (8)",""))<lenb($Z6),8,IF(lenb(SUBSTITUTE($Z6,X$1&" (9)",""))<lenb($Z6),9,IF(lenb(SUBSTITUTE($Z6,X$1&" (10)",""))<lenb($Z6),10,IF(lenb(SUBSTITUTE($Z6,X$1,""))<lenb($Z6),"ERROR",IF($Z6=$Y$1,"-",0)))))))))))) -> - | Y6: =IF(Z6=Y$1,1,"-") -> 1 | Z6: No links | AA6: =ifs(U6="","",U6="-",0,U6="Erro",0,U6<>"",LEN(U6)-LEN(SUBSTITUTE(U6,CHAR(10),""))+1) -> 0 | AB6: =COUNTIFS(Links!B:B,"ICSE",Links!C:C,A6,Links!AD:AD,1) -> 0 | AC6: - | AD6: =ifs(AE6="None.","No",AE6="-","No",AND(AE6<>"None.",AE6<>"-"),"Yes") -> No | AE6: - | AF6: ---- | AG6: ---- | AH6: ---- | AI6: =IF(AH6="----",IF(AG6="----",IF(AF6="----","----",AF6),AF6&CHAR(10)&AG6),AF6&CHAR(10)&AG6&CHAR(10)&AH6) -> ---- | AJ6: =IFERROR( if(and(K6="Yes",AD6="No"),"Paper has link but no statement", if(and(K6="No",AD6="No"),"Paper has no link and no statement", if(and(K6="Yes",AD6="Yes"),"Paper has link and statement", if(and(K6="No",AD6="Yes"),"Paper has no link but has statement","")))),"") -> Paper has no link and no statement | AK6: 45035 | AL6: Technical | AM6: ="[IP"&TEXT(A6,"0000")&"]" -> [IP1848]
A7: 1849 | B7: Performance regression testing target prioritization via performance risk analysis | C7: 2014 | D7: No | E7: - | F7: - | G7: - | H7: - | I7: - | J7: - | K7: Yes | L7: Yes | M7: No | N7: No | O7: Yes | P7: No | Q7: No | R7: Yes | S7: - 4. IMPLEMENTATION - 8. CONCLUSIONS AND FUTURE WORK - FN 2 - 5. EVALUATION * | T7: http://cseweb.ucsd.edu/~peh003/perfscope http://ideone.com/6d70fJ | U7: http://cseweb.ucsd.edu/~peh003/perfscope http://ideone.com/6d70fJ | V7: =IF(lenb(SUBSTITUTE($Z7,V$1&" (1)",""))<lenb($Z7),1,IF(lenb(SUBSTITUTE($Z7,V$1&" (2)",""))<lenb($Z7),2,IF(lenb(SUBSTITUTE($Z7,V$1&" (3)",""))<lenb($Z7),3,IF(lenb(SUBSTITUTE($Z7,V$1&" (4)",""))<lenb($Z7),4,IF(lenb(SUBSTITUTE($Z7,V$1&" (5)",""))<lenb($Z7),5,IF(lenb(SUBSTITUTE($Z7,V$1&" (6)",""))<lenb($Z7),6,IF(lenb(SUBSTITUTE($Z7,V$1&" (7)",""))<lenb($Z7),1,IF(lenb(SUBSTITUTE($Z7,V$1&" (8)",""))<lenb($Z7),8,IF(lenb(SUBSTITUTE($Z7,V$1&" (9)",""))<lenb($Z7),9,IF(lenb(SUBSTITUTE($Z7,V$1&" (10)",""))<lenb($Z7),10,IF(lenb(SUBSTITUTE($Z7,V$1,""))<lenb($Z7),"ERROR",IF($Z7=$Y$1,"-",0)))))))))))) -> 2 | W7: =IF(lenb(SUBSTITUTE($Z7,W$1&" (1)",""))<lenb($Z7),1,IF(lenb(SUBSTITUTE($Z7,W$1&" (2)",""))<lenb($Z7),2,IF(lenb(SUBSTITUTE($Z7,W$1&" (3)",""))<lenb($Z7),3,IF(lenb(SUBSTITUTE($Z7,W$1&" (4)",""))<lenb($Z7),4,IF(lenb(SUBSTITUTE($Z7,W$1&" (5)",""))<lenb($Z7),5,IF(lenb(SUBSTITUTE($Z7,W$1&" (6)",""))<lenb($Z7),6,IF(lenb(SUBSTITUTE($Z7,W$1&" (7)",""))<lenb($Z7),1,IF(lenb(SUBSTITUTE($Z7,W$1&" (8)",""))<lenb($Z7),8,IF(lenb(SUBSTITUTE($Z7,W$1&" (9)",""))<lenb($Z7),9,IF(lenb(SUBSTITUTE($Z7,W$1&" (10)",""))<lenb($Z7),10,IF(lenb(SUBSTITUTE($Z7,W$1,""))<lenb($Z7),"ERROR",IF($Z7=$Y$1,"-",0)))))))))))) -> 0 | X7: =IF(lenb(SUBSTITUTE($Z7,X$1&" (1)",""))<lenb($Z7),1,IF(lenb(SUBSTITUTE($Z7,X$1&" (2)",""))<lenb($Z7),2,IF(lenb(SUBSTITUTE($Z7,X$1&" (3)",""))<lenb($Z7),3,IF(lenb(SUBSTITUTE($Z7,X$1&" (4)",""))<lenb($Z7),4,IF(lenb(SUBSTITUTE($Z7,X$1&" (5)",""))<lenb($Z7),5,IF(lenb(SUBSTITUTE($Z7,X$1&" (6)",""))<lenb($Z7),6,IF(lenb(SUBSTITUTE($Z7,X$1&" (7)",""))<lenb($Z7),1,IF(lenb(SUBSTITUTE($Z7,X$1&" (8)",""))<lenb($Z7),8,IF(lenb(SUBSTITUTE($Z7,X$1&" (9)",""))<lenb($Z7),9,IF(lenb(SUBSTITUTE($Z7,X$1&" (10)",""))<lenb($Z7),10,IF(lenb(SUBSTITUTE($Z7,X$1,""))<lenb($Z7),"ERROR",IF($Z7=$Y$1,"-",0)))))))))))) -> 0 | Y7: =IF(Z7=Y$1,1,"-") -> - | Z7: Publicly available (2) | AA7: =ifs(U7="","",U7="-",0,U7="Erro",0,U7<>"",LEN(U7)-LEN(SUBSTITUTE(U7,CHAR(10),""))+1) -> 2 | AB7: =COUNTIFS(Links!B:B,"ICSE",Links!C:C,A7,Links!AD:AD,1) -> 1 | AC7: No | AD7: =ifs(AE7="None.","No",AE7="-","No",AND(AE7<>"None.",AE7<>"-"),"Yes") -> No | AE7: - | AF7: ---- | AG7: ---- | AH7: ---- | AI7: =IF(AH7="----",IF(AG7="----",IF(AF7="----","----",AF7),AF7&CHAR(10)&AG7),AF7&CHAR(10)&AG7&CHAR(10)&AH7) -> ---- | AJ7: =IFERROR( if(and(K7="Yes",AD7="No"),"Paper has link but no statement", if(and(K7="No",AD7="No"),"Paper has no link and no statement", if(and(K7="Yes",AD7="Yes"),"Paper has link and statement", if(and(K7="No",AD7="Yes"),"Paper has no link but has statement","")))),"") -> Paper has link but no statement | AK7: 45035 | AL7: Technical | AM7: ="[IP"&TEXT(A7,"0000")&"]" -> [IP1849]
A8: 1850 | B8: Code coverage for suite evaluation by developers | C8: 2014 | D8: No | E8: - | F8: - | G8: - | H8: - | I8: - | J8: - | K8: Yes | L8: No | M8: Yes | N8: No | O8: No | P8: No | Q8: No | R8: Yes | S8: [17] 3. METHODOLOGY | T8: http://dx.doi.org/10.7910/DVN/24574 ( real link: https://dataverse.harvard.edu/dataset.xhtml?persistentId=doi:10.7910/DVN/24574 ) | U8: http://dx.doi.org/10.7910/DVN/24574 | V8: =IF(lenb(SUBSTITUTE($Z8,V$1&" (1)",""))<lenb($Z8),1,IF(lenb(SUBSTITUTE($Z8,V$1&" (2)",""))<lenb($Z8),2,IF(lenb(SUBSTITUTE($Z8,V$1&" (3)",""))<lenb($Z8),3,IF(lenb(SUBSTITUTE($Z8,V$1&" (4)",""))<lenb($Z8),4,IF(lenb(SUBSTITUTE($Z8,V$1&" (5)",""))<lenb($Z8),5,IF(lenb(SUBSTITUTE($Z8,V$1&" (6)",""))<lenb($Z8),6,IF(lenb(SUBSTITUTE($Z8,V$1&" (7)",""))<lenb($Z8),1,IF(lenb(SUBSTITUTE($Z8,V$1&" (8)",""))<lenb($Z8),8,IF(lenb(SUBSTITUTE($Z8,V$1&" (9)",""))<lenb($Z8),9,IF(lenb(SUBSTITUTE($Z8,V$1&" (10)",""))<lenb($Z8),10,IF(lenb(SUBSTITUTE($Z8,V$1,""))<lenb($Z8),"ERROR",IF($Z8=$Y$1,"-",0)))))))))))) -> 1 | W8: =IF(lenb(SUBSTITUTE($Z8,W$1&" (1)",""))<lenb($Z8),1,IF(lenb(SUBSTITUTE($Z8,W$1&" (2)",""))<lenb($Z8),2,IF(lenb(SUBSTITUTE($Z8,W$1&" (3)",""))<lenb($Z8),3,IF(lenb(SUBSTITUTE($Z8,W$1&" (4)",""))<lenb($Z8),4,IF(lenb(SUBSTITUTE($Z8,W$1&" (5)",""))<lenb($Z8),5,IF(lenb(SUBSTITUTE($Z8,W$1&" (6)",""))<lenb($Z8),6,IF(lenb(SUBSTITUTE($Z8,W$1&" (7)",""))<lenb($Z8),1,IF(lenb(SUBSTITUTE($Z8,W$1&" (8)",""))<lenb($Z8),8,IF(lenb(SUBSTITUTE($Z8,W$1&" (9)",""))<lenb($Z8),9,IF(lenb(SUBSTITUTE($Z8,W$1&" (10)",""))<lenb($Z8),10,IF(lenb(SUBSTITUTE($Z8,W$1,""))<lenb($Z8),"ERROR",IF($Z8=$Y$1,"-",0)))))))))))) -> 0 | X8: =IF(lenb(SUBSTITUTE($Z8,X$1&" (1)",""))<lenb($Z8),1,IF(lenb(SUBSTITUTE($Z8,X$1&" (2)",""))<lenb($Z8),2,IF(lenb(SUBSTITUTE($Z8,X$1&" (3)",""))<lenb($Z8),3,IF(lenb(SUBSTITUTE($Z8,X$1&" (4)",""))<lenb($Z8),4,IF(lenb(SUBSTITUTE($Z8,X$1&" (5)",""))<lenb($Z8),5,IF(lenb(SUBSTITUTE($Z8,X$1&" (6)",""))<lenb($Z8),6,IF(lenb(SUBSTITUTE($Z8,X$1&" (7)",""))<lenb($Z8),1,IF(lenb(SUBSTITUTE($Z8,X$1&" (8)",""))<lenb($Z8),8,IF(lenb(SUBSTITUTE($Z8,X$1&" (9)",""))<lenb($Z8),9,IF(lenb(SUBSTITUTE($Z8,X$1&" (10)",""))<lenb($Z8),10,IF(lenb(SUBSTITUTE($Z8,X$1,""))<lenb($Z8),"ERROR",IF($Z8=$Y$1,"-",0)))))))))))) -> 0 | Y8: =IF(Z8=Y$1,1,"-") -> - | Z8: Publicly available (1) | AA8: =ifs(U8="","",U8="-",0,U8="Erro",0,U8<>"",LEN(U8)-LEN(SUBSTITUTE(U8,CHAR(10),""))+1) -> 1 | AB8: =COUNTIFS(Links!B:B,"ICSE",Links!C:C,A8,Links!AD:AD,1) -> 1 | AC8: Yes | AD8: =ifs(AE8="None.","No",AE8="-","No",AND(AE8<>"None.",AE8<>"-"),"Yes") -> No | AE8: - | AF8: ---- | AG8: ---- | AH8: ---- | AI8: =IF(AH8="----",IF(AG8="----",IF(AF8="----","----",AF8),AF8&CHAR(10)&AG8),AF8&CHAR(10)&AG8&CHAR(10)&AH8) -> ---- | AJ8: =IFERROR( if(and(K8="Yes",AD8="No"),"Paper has link but no statement", if(and(K8="No",AD8="No"),"Paper has no link and no statement", if(and(K8="Yes",AD8="Yes"),"Paper has link and statement", if(and(K8="No",AD8="Yes"),"Paper has no link but has statement","")))),"") -> Paper has link but no statement | AK8: 45035 | AL8: Technical | AM8: ="[IP"&TEXT(A8,"0000")&"]" -> [IP1850]
A9: 1851 | B9: Time pressure: a controlled experiment of test case development and requirements review | C9: 2014 | D9: No | E9: - | F9: - | G9: - | H9: - | I9: - | J9: - | K9: Yes | L9: No | M9: Yes | N9: No | O9: No | P9: No | Q9: No | R9: Yes | S9: [39] - 3. RESEARCH METHODOLOGY * (4x) - 5. DISCUSSION * - 5.2 Threats to Validity | T9: http://users.tkk.fi/~mmantyla/TP/ | U9: http://users.tkk.fi/~mmantyla/TP/ | V9: =IF(lenb(SUBSTITUTE($Z9,V$1&" (1)",""))<lenb($Z9),1,IF(lenb(SUBSTITUTE($Z9,V$1&" (2)",""))<lenb($Z9),2,IF(lenb(SUBSTITUTE($Z9,V$1&" (3)",""))<lenb($Z9),3,IF(lenb(SUBSTITUTE($Z9,V$1&" (4)",""))<lenb($Z9),4,IF(lenb(SUBSTITUTE($Z9,V$1&" (5)",""))<lenb($Z9),5,IF(lenb(SUBSTITUTE($Z9,V$1&" (6)",""))<lenb($Z9),6,IF(lenb(SUBSTITUTE($Z9,V$1&" (7)",""))<lenb($Z9),1,IF(lenb(SUBSTITUTE($Z9,V$1&" (8)",""))<lenb($Z9),8,IF(lenb(SUBSTITUTE($Z9,V$1&" (9)",""))<lenb($Z9),9,IF(lenb(SUBSTITUTE($Z9,V$1&" (10)",""))<lenb($Z9),10,IF(lenb(SUBSTITUTE($Z9,V$1,""))<lenb($Z9),"ERROR",IF($Z9=$Y$1,"-",0)))))))))))) -> 0 | W9: =IF(lenb(SUBSTITUTE($Z9,W$1&" (1)",""))<lenb($Z9),1,IF(lenb(SUBSTITUTE($Z9,W$1&" (2)",""))<lenb($Z9),2,IF(lenb(SUBSTITUTE($Z9,W$1&" (3)",""))<lenb($Z9),3,IF(lenb(SUBSTITUTE($Z9,W$1&" (4)",""))<lenb($Z9),4,IF(lenb(SUBSTITUTE($Z9,W$1&" (5)",""))<lenb($Z9),5,IF(lenb(SUBSTITUTE($Z9,W$1&" (6)",""))<lenb($Z9),6,IF(lenb(SUBSTITUTE($Z9,W$1&" (7)",""))<lenb($Z9),1,IF(lenb(SUBSTITUTE($Z9,W$1&" (8)",""))<lenb($Z9),8,IF(lenb(SUBSTITUTE($Z9,W$1&" (9)",""))<lenb($Z9),9,IF(lenb(SUBSTITUTE($Z9,W$1&" (10)",""))<lenb($Z9),10,IF(lenb(SUBSTITUTE($Z9,W$1,""))<lenb($Z9),"ERROR",IF($Z9=$Y$1,"-",0)))))))))))) -> 1 | X9: =IF(lenb(SUBSTITUTE($Z9,X$1&" (1)",""))<lenb($Z9),1,IF(lenb(SUBSTITUTE($Z9,X$1&" (2)",""))<lenb($Z9),2,IF(lenb(SUBSTITUTE($Z9,X$1&" (3)",""))<lenb($Z9),3,IF(lenb(SUBSTITUTE($Z9,X$1&" (4)",""))<lenb($Z9),4,IF(lenb(SUBSTITUTE($Z9,X$1&" (5)",""))<lenb($Z9),5,IF(lenb(SUBSTITUTE($Z9,X$1&" (6)",""))<lenb($Z9),6,IF(lenb(SUBSTITUTE($Z9,X$1&" (7)",""))<lenb($Z9),1,IF(lenb(SUBSTITUTE($Z9,X$1&" (8)",""))<lenb($Z9),8,IF(lenb(SUBSTITUTE($Z9,X$1&" (9)",""))<lenb($Z9),9,IF(lenb(SUBSTITUTE($Z9,X$1&" (10)",""))<lenb($Z9),10,IF(lenb(SUBSTITUTE($Z9,X$1,""))<lenb($Z9),"ERROR",IF($Z9=$Y$1,"-",0)))))))))))) -> 0 | Y9: =IF(Z9=Y$1,1,"-") -> - | Z9: Not available (1) - Broken link. | AA9: =ifs(U9="","",U9="-",0,U9="Erro",0,U9<>"",LEN(U9)-LEN(SUBSTITUTE(U9,CHAR(10),""))+1) -> 1 | AB9: =COUNTIFS(Links!B:B,"ICSE",Links!C:C,A9,Links!AD:AD,1) -> 0 | AC9: No | AD9: =ifs(AE9="None.","No",AE9="-","No",AND(AE9<>"None.",AE9<>"-"),"Yes") -> No | AE9: - | AF9: ---- | AG9: ---- | AH9: ---- | AI9: =IF(AH9="----",IF(AG9="----",IF(AF9="----","----",AF9),AF9&CHAR(10)&AG9),AF9&CHAR(10)&AG9&CHAR(10)&AH9) -> ---- | AJ9: =IFERROR( if(and(K9="Yes",AD9="No"),"Paper has link but no statement", if(and(K9="No",AD9="No"),"Paper has no link and no statement", if(and(K9="Yes",AD9="Yes"),"Paper has link and statement", if(and(K9="No",AD9="Yes"),"Paper has no link but has statement","")))),"") -> Paper has link but no statement | AK9: 45035 | AL9: Technical | AM9: ="[IP"&TEXT(A9,"0000")&"]" -> [IP1851]
A10: 1852 | B10: Verifying component and connector models against crosscutting structural views | C10: 2014 | D10: No | E10: - | F10: - | G10: - | H10: - | I10: - | J10: - | K10: Yes | L10: No | M10: Yes | N10: No | O10: No | P10: No | Q10: No | R10: Yes | S10: [3] 2. OVERVIEW * 3. PRELIMINARIES 4. C&C VIEWS VERIFICATION * (2x) 5. EVALUATION (3x) * | T10: http://www.se-rwth.de/materials/cncviews/ | U10: http://www.se-rwth.de/materials/cncviews/ | V10: =IF(lenb(SUBSTITUTE($Z10,V$1&" (1)",""))<lenb($Z10),1,IF(lenb(SUBSTITUTE($Z10,V$1&" (2)",""))<lenb($Z10),2,IF(lenb(SUBSTITUTE($Z10,V$1&" (3)",""))<lenb($Z10),3,IF(lenb(SUBSTITUTE($Z10,V$1&" (4)",""))<lenb($Z10),4,IF(lenb(SUBSTITUTE($Z10,V$1&" (5)",""))<lenb($Z10),5,IF(lenb(SUBSTITUTE($Z10,V$1&" (6)",""))<lenb($Z10),6,IF(lenb(SUBSTITUTE($Z10,V$1&" (7)",""))<lenb($Z10),1,IF(lenb(SUBSTITUTE($Z10,V$1&" (8)",""))<lenb($Z10),8,IF(lenb(SUBSTITUTE($Z10,V$1&" (9)",""))<lenb($Z10),9,IF(lenb(SUBSTITUTE($Z10,V$1&" (10)",""))<lenb($Z10),10,IF(lenb(SUBSTITUTE($Z10,V$1,""))<lenb($Z10),"ERROR",IF($Z10=$Y$1,"-",0)))))))))))) -> 1 | W10: =IF(lenb(SUBSTITUTE($Z10,W$1&" (1)",""))<lenb($Z10),1,IF(lenb(SUBSTITUTE($Z10,W$1&" (2)",""))<lenb($Z10),2,IF(lenb(SUBSTITUTE($Z10,W$1&" (3)",""))<lenb($Z10),3,IF(lenb(SUBSTITUTE($Z10,W$1&" (4)",""))<lenb($Z10),4,IF(lenb(SUBSTITUTE($Z10,W$1&" (5)",""))<lenb($Z10),5,IF(lenb(SUBSTITUTE($Z10,W$1&" (6)",""))<lenb($Z10),6,IF(lenb(SUBSTITUTE($Z10,W$1&" (7)",""))<lenb($Z10),1,IF(lenb(SUBSTITUTE($Z10,W$1&" (8)",""))<lenb($Z10),8,IF(lenb(SUBSTITUTE($Z10,W$1&" (9)",""))<lenb($Z10),9,IF(lenb(SUBSTITUTE($Z10,W$1&" (10)",""))<lenb($Z10),10,IF(lenb(SUBSTITUTE($Z10,W$1,""))<lenb($Z10),"ERROR",IF($Z10=$Y$1,"-",0)))))))))))) -> 0 | X10: =IF(lenb(SUBSTITUTE($Z10,X$1&" (1)",""))<lenb($Z10),1,IF(lenb(SUBSTITUTE($Z10,X$1&" (2)",""))<lenb($Z10),2,IF(lenb(SUBSTITUTE($Z10,X$1&" (3)",""))<lenb($Z10),3,IF(lenb(SUBSTITUTE($Z10,X$1&" (4)",""))<lenb($Z10),4,IF(lenb(SUBSTITUTE($Z10,X$1&" (5)",""))<lenb($Z10),5,IF(lenb(SUBSTITUTE($Z10,X$1&" (6)",""))<lenb($Z10),6,IF(lenb(SUBSTITUTE($Z10,X$1&" (7)",""))<lenb($Z10),1,IF(lenb(SUBSTITUTE($Z10,X$1&" (8)",""))<lenb($Z10),8,IF(lenb(SUBSTITUTE($Z10,X$1&" (9)",""))<lenb($Z10),9,IF(lenb(SUBSTITUTE($Z10,X$1&" (10)",""))<lenb($Z10),10,IF(lenb(SUBSTITUTE($Z10,X$1,""))<lenb($Z10),"ERROR",IF($Z10=$Y$1,"-",0)))))))))))) -> 0 | Y10: =IF(Z10=Y$1,1,"-") -> - | Z10: Publicly available (1) | AA10: =ifs(U10="","",U10="-",0,U10="Erro",0,U10<>"",LEN(U10)-LEN(SUBSTITUTE(U10,CHAR(10),""))+1) -> 1 | AB10: =COUNTIFS(Links!B:B,"ICSE",Links!C:C,A10,Links!AD:AD,1) -> 1 | AC10: No | AD10: =ifs(AE10="None.","No",AE10="-","No",AND(AE10<>"None.",AE10<>"-"),"Yes") -> No | AE10: - | AF10: ---- | AG10: ---- | AH10: ---- | AI10: =IF(AH10="----",IF(AG10="----",IF(AF10="----","----",AF10),AF10&CHAR(10)&AG10),AF10&CHAR(10)&AG10&CHAR(10)&AH10) -> ---- | AJ10: =IFERROR( if(and(K10="Yes",AD10="No"),"Paper has link but no statement", if(and(K10="No",AD10="No"),"Paper has no link and no statement", if(and(K10="Yes",AD10="Yes"),"Paper has link and statement", if(and(K10="No",AD10="Yes"),"Paper has no link but has statement","")))),"") -> Paper has link but no statement | AK10: 45035 | AL10: Technical | AM10: ="[IP"&TEXT(A10,"0000")&"]" -> [IP1852]
A11: 1853 | B11: TradeMaker: automated dynamic analysis of synthesized tradespaces | C11: 2014 | D11: No | E11: - | F11: - | G11: - | H11: - | I11: - | J11: - | K11: Yes | L11: Yes | M11: No | N11: No | O11: No | P11: No | Q11: No | R11: Yes | S11: - FN 1 - 2. DRIVING PROBLEM - 5. DYNAMIC ANALYSIS EXPERIMENT * | T11: http://jazz.cs.virginia.edu:8080/Trademaker/data | U11: http://jazz.cs.virginia.edu:8080/Trademaker/data | V11: =IF(lenb(SUBSTITUTE($Z11,V$1&" (1)",""))<lenb($Z11),1,IF(lenb(SUBSTITUTE($Z11,V$1&" (2)",""))<lenb($Z11),2,IF(lenb(SUBSTITUTE($Z11,V$1&" (3)",""))<lenb($Z11),3,IF(lenb(SUBSTITUTE($Z11,V$1&" (4)",""))<lenb($Z11),4,IF(lenb(SUBSTITUTE($Z11,V$1&" (5)",""))<lenb($Z11),5,IF(lenb(SUBSTITUTE($Z11,V$1&" (6)",""))<lenb($Z11),6,IF(lenb(SUBSTITUTE($Z11,V$1&" (7)",""))<lenb($Z11),1,IF(lenb(SUBSTITUTE($Z11,V$1&" (8)",""))<lenb($Z11),8,IF(lenb(SUBSTITUTE($Z11,V$1&" (9)",""))<lenb($Z11),9,IF(lenb(SUBSTITUTE($Z11,V$1&" (10)",""))<lenb($Z11),10,IF(lenb(SUBSTITUTE($Z11,V$1,""))<lenb($Z11),"ERROR",IF($Z11=$Y$1,"-",0)))))))))))) -> 0 | W11: =IF(lenb(SUBSTITUTE($Z11,W$1&" (1)",""))<lenb($Z11),1,IF(lenb(SUBSTITUTE($Z11,W$1&" (2)",""))<lenb($Z11),2,IF(lenb(SUBSTITUTE($Z11,W$1&" (3)",""))<lenb($Z11),3,IF(lenb(SUBSTITUTE($Z11,W$1&" (4)",""))<lenb($Z11),4,IF(lenb(SUBSTITUTE($Z11,W$1&" (5)",""))<lenb($Z11),5,IF(lenb(SUBSTITUTE($Z11,W$1&" (6)",""))<lenb($Z11),6,IF(lenb(SUBSTITUTE($Z11,W$1&" (7)",""))<lenb($Z11),1,IF(lenb(SUBSTITUTE($Z11,W$1&" (8)",""))<lenb($Z11),8,IF(lenb(SUBSTITUTE($Z11,W$1&" (9)",""))<lenb($Z11),9,IF(lenb(SUBSTITUTE($Z11,W$1&" (10)",""))<lenb($Z11),10,IF(lenb(SUBSTITUTE($Z11,W$1,""))<lenb($Z11),"ERROR",IF($Z11=$Y$1,"-",0)))))))))))) -> 1 | X11: =IF(lenb(SUBSTITUTE($Z11,X$1&" (1)",""))<lenb($Z11),1,IF(lenb(SUBSTITUTE($Z11,X$1&" (2)",""))<lenb($Z11),2,IF(lenb(SUBSTITUTE($Z11,X$1&" (3)",""))<lenb($Z11),3,IF(lenb(SUBSTITUTE($Z11,X$1&" (4)",""))<lenb($Z11),4,IF(lenb(SUBSTITUTE($Z11,X$1&" (5)",""))<lenb($Z11),5,IF(lenb(SUBSTITUTE($Z11,X$1&" (6)",""))<lenb($Z11),6,IF(lenb(SUBSTITUTE($Z11,X$1&" (7)",""))<lenb($Z11),1,IF(lenb(SUBSTITUTE($Z11,X$1&" (8)",""))<lenb($Z11),8,IF(lenb(SUBSTITUTE($Z11,X$1&" (9)",""))<lenb($Z11),9,IF(lenb(SUBSTITUTE($Z11,X$1&" (10)",""))<lenb($Z11),10,IF(lenb(SUBSTITUTE($Z11,X$1,""))<lenb($Z11),"ERROR",IF($Z11=$Y$1,"-",0)))))))))))) -> 0 | Y11: =IF(Z11=Y$1,1,"-") -> - | Z11: Not available (1) - Broken link. | AA11: =ifs(U11="","",U11="-",0,U11="Erro",0,U11<>"",LEN(U11)-LEN(SUBSTITUTE(U11,CHAR(10),""))+1) -> 1 | AB11: =COUNTIFS(Links!B:B,"ICSE",Links!C:C,A11,Links!AD:AD,1) -> 1 | AC11: No | AD11: =ifs(AE11="None.","No",AE11="-","No",AND(AE11<>"None.",AE11<>"-"),"Yes") -> No | AE11: - | AF11: ---- | AG11: ---- | AH11: ---- | AI11: =IF(AH11="----",IF(AG11="----",IF(AF11="----","----",AF11),AF11&CHAR(10)&AG11),AF11&CHAR(10)&AG11&CHAR(10)&AH11) -> ---- | AJ11: =IFERROR( if(and(K11="Yes",AD11="No"),"Paper has link but no statement", if(and(K11="No",AD11="No"),"Paper has no link and no statement", if(and(K11="Yes",AD11="Yes"),"Paper has link and statement", if(and(K11="No",AD11="Yes"),"Paper has no link but has statement","")))),"") -> Paper has link but no statement | AK11: 45035 | AL11: Technical | AM11: ="[IP"&TEXT(A11,"0000")&"]" -> [IP1853]
A12: 1854 | B12: Lifting model transformations to product lines | C12: 2014 | D12: No | E12: - | F12: - | G12: - | H12: - | I12: - | J12: - | K12: No | L12: - | M12: - | N12: - | O12: - | P12: - | Q12: - | R12: - | S12: - | T12: - | U12: - | V12: =IF(lenb(SUBSTITUTE($Z12,V$1&" (1)",""))<lenb($Z12),1,IF(lenb(SUBSTITUTE($Z12,V$1&" (2)",""))<lenb($Z12),2,IF(lenb(SUBSTITUTE($Z12,V$1&" (3)",""))<lenb($Z12),3,IF(lenb(SUBSTITUTE($Z12,V$1&" (4)",""))<lenb($Z12),4,IF(lenb(SUBSTITUTE($Z12,V$1&" (5)",""))<lenb($Z12),5,IF(lenb(SUBSTITUTE($Z12,V$1&" (6)",""))<lenb($Z12),6,IF(lenb(SUBSTITUTE($Z12,V$1&" (7)",""))<lenb($Z12),1,IF(lenb(SUBSTITUTE($Z12,V$1&" (8)",""))<lenb($Z12),8,IF(lenb(SUBSTITUTE($Z12,V$1&" (9)",""))<lenb($Z12),9,IF(lenb(SUBSTITUTE($Z12,V$1&" (10)",""))<lenb($Z12),10,IF(lenb(SUBSTITUTE($Z12,V$1,""))<lenb($Z12),"ERROR",IF($Z12=$Y$1,"-",0)))))))))))) -> - | W12: =IF(lenb(SUBSTITUTE($Z12,W$1&" (1)",""))<lenb($Z12),1,IF(lenb(SUBSTITUTE($Z12,W$1&" (2)",""))<lenb($Z12),2,IF(lenb(SUBSTITUTE($Z12,W$1&" (3)",""))<lenb($Z12),3,IF(lenb(SUBSTITUTE($Z12,W$1&" (4)",""))<lenb($Z12),4,IF(lenb(SUBSTITUTE($Z12,W$1&" (5)",""))<lenb($Z12),5,IF(lenb(SUBSTITUTE($Z12,W$1&" (6)",""))<lenb($Z12),6,IF(lenb(SUBSTITUTE($Z12,W$1&" (7)",""))<lenb($Z12),1,IF(lenb(SUBSTITUTE($Z12,W$1&" (8)",""))<lenb($Z12),8,IF(lenb(SUBSTITUTE($Z12,W$1&" (9)",""))<lenb($Z12),9,IF(lenb(SUBSTITUTE($Z12,W$1&" (10)",""))<lenb($Z12),10,IF(lenb(SUBSTITUTE($Z12,W$1,""))<lenb($Z12),"ERROR",IF($Z12=$Y$1,"-",0)))))))))))) -> - | X12: =IF(lenb(SUBSTITUTE($Z12,X$1&" (1)",""))<lenb($Z12),1,IF(lenb(SUBSTITUTE($Z12,X$1&" (2)",""))<lenb($Z12),2,IF(lenb(SUBSTITUTE($Z12,X$1&" (3)",""))<lenb($Z12),3,IF(lenb(SUBSTITUTE($Z12,X$1&" (4)",""))<lenb($Z12),4,IF(lenb(SUBSTITUTE($Z12,X$1&" (5)",""))<lenb($Z12),5,IF(lenb(SUBSTITUTE($Z12,X$1&" (6)",""))<lenb($Z12),6,IF(lenb(SUBSTITUTE($Z12,X$1&" (7)",""))<lenb($Z12),1,IF(lenb(SUBSTITUTE($Z12,X$1&" (8)",""))<lenb($Z12),8,IF(lenb(SUBSTITUTE($Z12,X$1&" (9)",""))<lenb($Z12),9,IF(lenb(SUBSTITUTE($Z12,X$1&" (10)",""))<lenb($Z12),10,IF(lenb(SUBSTITUTE($Z12,X$1,""))<lenb($Z12),"ERROR",IF($Z12=$Y$1,"-",0)))))))))))) -> - | Y12: =IF(Z12=Y$1,1,"-") -> 1 | Z12: No links | AA12: =ifs(U12="","",U12="-",0,U12="Erro",0,U12<>"",LEN(U12)-LEN(SUBSTITUTE(U12,CHAR(10),""))+1) -> 0 | AB12: =COUNTIFS(Links!B:B,"ICSE",Links!C:C,A12,Links!AD:AD,1) -> 0 | AC12: - | AD12: =ifs(AE12="None.","No",AE12="-","No",AND(AE12<>"None.",AE12<>"-"),"Yes") -> No | AE12: - | AF12: ---- | AG12: ---- | AH12: ---- | AI12: =IF(AH12="----",IF(AG12="----",IF(AF12="----","----",AF12),AF12&CHAR(10)&AG12),AF12&CHAR(10)&AG12&CHAR(10)&AH12) -> ---- | AJ12: =IFERROR( if(and(K12="Yes",AD12="No"),"Paper has link but no statement", if(and(K12="No",AD12="No"),"Paper has no link and no statement", if(and(K12="Yes",AD12="Yes"),"Paper has link and statement", if(and(K12="No",AD12="Yes"),"Paper has no link but has statement","")))),"") -> Paper has no link and no statement | AK12: 45035 | AL12: Technical | AM12: ="[IP"&TEXT(A12,"0000")&"]" -> [IP1854]
A13: 1855 | B13: Automated goal operationalisation based on interpolation and SAT solving | C13: 2014 | D13: No | E13: - | F13: - | G13: - | H13: - | I13: - | J13: - | K13: Yes | L13: No | M13: No | N13: No | O13: No | P13: No | Q13: No | R13: Yes | S13: 6. DEMONSTRATING EXAMPLES | T13: http://dc.exa.unrc.edu.ar/staff/rdegiovanni/icse2014.zip | U13: http://dc.exa.unrc.edu.ar/staff/rdegiovanni/icse2014.zip | V13: =IF(lenb(SUBSTITUTE($Z13,V$1&" (1)",""))<lenb($Z13),1,IF(lenb(SUBSTITUTE($Z13,V$1&" (2)",""))<lenb($Z13),2,IF(lenb(SUBSTITUTE($Z13,V$1&" (3)",""))<lenb($Z13),3,IF(lenb(SUBSTITUTE($Z13,V$1&" (4)",""))<lenb($Z13),4,IF(lenb(SUBSTITUTE($Z13,V$1&" (5)",""))<lenb($Z13),5,IF(lenb(SUBSTITUTE($Z13,V$1&" (6)",""))<lenb($Z13),6,IF(lenb(SUBSTITUTE($Z13,V$1&" (7)",""))<lenb($Z13),1,IF(lenb(SUBSTITUTE($Z13,V$1&" (8)",""))<lenb($Z13),8,IF(lenb(SUBSTITUTE($Z13,V$1&" (9)",""))<lenb($Z13),9,IF(lenb(SUBSTITUTE($Z13,V$1&" (10)",""))<lenb($Z13),10,IF(lenb(SUBSTITUTE($Z13,V$1,""))<lenb($Z13),"ERROR",IF($Z13=$Y$1,"-",0)))))))))))) -> 1 | W13: =IF(lenb(SUBSTITUTE($Z13,W$1&" (1)",""))<lenb($Z13),1,IF(lenb(SUBSTITUTE($Z13,W$1&" (2)",""))<lenb($Z13),2,IF(lenb(SUBSTITUTE($Z13,W$1&" (3)",""))<lenb($Z13),3,IF(lenb(SUBSTITUTE($Z13,W$1&" (4)",""))<lenb($Z13),4,IF(lenb(SUBSTITUTE($Z13,W$1&" (5)",""))<lenb($Z13),5,IF(lenb(SUBSTITUTE($Z13,W$1&" (6)",""))<lenb($Z13),6,IF(lenb(SUBSTITUTE($Z13,W$1&" (7)",""))<lenb($Z13),1,IF(lenb(SUBSTITUTE($Z13,W$1&" (8)",""))<lenb($Z13),8,IF(lenb(SUBSTITUTE($Z13,W$1&" (9)",""))<lenb($Z13),9,IF(lenb(SUBSTITUTE($Z13,W$1&" (10)",""))<lenb($Z13),10,IF(lenb(SUBSTITUTE($Z13,W$1,""))<lenb($Z13),"ERROR",IF($Z13=$Y$1,"-",0)))))))))))) -> 0 | X13: =IF(lenb(SUBSTITUTE($Z13,X$1&" (1)",""))<lenb($Z13),1,IF(lenb(SUBSTITUTE($Z13,X$1&" (2)",""))<lenb($Z13),2,IF(lenb(SUBSTITUTE($Z13,X$1&" (3)",""))<lenb($Z13),3,IF(lenb(SUBSTITUTE($Z13,X$1&" (4)",""))<lenb($Z13),4,IF(lenb(SUBSTITUTE($Z13,X$1&" (5)",""))<lenb($Z13),5,IF(lenb(SUBSTITUTE($Z13,X$1&" (6)",""))<lenb($Z13),6,IF(lenb(SUBSTITUTE($Z13,X$1&" (7)",""))<lenb($Z13),1,IF(lenb(SUBSTITUTE($Z13,X$1&" (8)",""))<lenb($Z13),8,IF(lenb(SUBSTITUTE($Z13,X$1&" (9)",""))<lenb($Z13),9,IF(lenb(SUBSTITUTE($Z13,X$1&" (10)",""))<lenb($Z13),10,IF(lenb(SUBSTITUTE($Z13,X$1,""))<lenb($Z13),"ERROR",IF($Z13=$Y$1,"-",0)))))))))))) -> 0 | Y13: =IF(Z13=Y$1,1,"-") -> - | Z13: Publicly available (1) | AA13: =ifs(U13="","",U13="-",0,U13="Erro",0,U13<>"",LEN(U13)-LEN(SUBSTITUTE(U13,CHAR(10),""))+1) -> 1 | AB13: =COUNTIFS(Links!B:B,"ICSE",Links!C:C,A13,Links!AD:AD,1) -> 1 | AC13: No | AD13: =ifs(AE13="None.","No",AE13="-","No",AND(AE13<>"None.",AE13<>"-"),"Yes") -> No | AE13: - | AF13: ---- | AG13: ---- | AH13: ---- | AI13: =IF(AH13="----",IF(AG13="----",IF(AF13="----","----",AF13),AF13&CHAR(10)&AG13),AF13&CHAR(10)&AG13&CHAR(10)&AH13) -> ---- | AJ13: =IFERROR( if(and(K13="Yes",AD13="No"),"Paper has link but no statement", if(and(K13="No",AD13="No"),"Paper has no link and no statement", if(and(K13="Yes",AD13="Yes"),"Paper has link and statement", if(and(K13="No",AD13="Yes"),"Paper has no link but has statement","")))),"") -> Paper has link but no statement | AK13: 45035 | AL13: Technical | AM13: ="[IP"&TEXT(A13,"0000")&"]" -> [IP1855]
... A652: 780 | B652: On the Recall of Static Call Graph Construction in Practice | C652: 2020 | D652: Yes | E652: Yes | F652: No | G652: Yes | H652: No | I652: No | J652: - | K652: No | L652: - | M652: - | N652: - | O652: - | P652: - | Q652: - | R652: - | S652: - | T652: - | U652: - | V652: =IF(lenb(SUBSTITUTE($Z652,V$1&" (1)",""))<lenb($Z652),1,IF(lenb(SUBSTITUTE($Z652,V$1&" (2)",""))<lenb($Z652),2,IF(lenb(SUBSTITUTE($Z652,V$1&" (3)",""))<lenb($Z652),3,IF(lenb(SUBSTITUTE($Z652,V$1&" (4)",""))<lenb($Z652),4,IF(lenb(SUBSTITUTE($Z652,V$1&" (5)",""))<lenb($Z652),5,IF(lenb(SUBSTITUTE($Z652,V$1&" (6)",""))<lenb($Z652),6,IF(lenb(SUBSTITUTE($Z652,V$1&" (7)",""))<lenb($Z652),1,IF(lenb(SUBSTITUTE($Z652,V$1&" (8)",""))<lenb($Z652),8,IF(lenb(SUBSTITUTE($Z652,V$1&" (9)",""))<lenb($Z652),9,IF(lenb(SUBSTITUTE($Z652,V$1&" (10)",""))<lenb($Z652),10,IF(lenb(SUBSTITUTE($Z652,V$1,""))<lenb($Z652),"ERROR",IF($Z652=$Y$1,"-",0)))))))))))) -> - | W652: =IF(lenb(SUBSTITUTE($Z652,W$1&" (1)",""))<lenb($Z652),1,IF(lenb(SUBSTITUTE($Z652,W$1&" (2)",""))<lenb($Z652),2,IF(lenb(SUBSTITUTE($Z652,W$1&" (3)",""))<lenb($Z652),3,IF(lenb(SUBSTITUTE($Z652,W$1&" (4)",""))<lenb($Z652),4,IF(lenb(SUBSTITUTE($Z652,W$1&" (5)",""))<lenb($Z652),5,IF(lenb(SUBSTITUTE($Z652,W$1&" (6)",""))<lenb($Z652),6,IF(lenb(SUBSTITUTE($Z652,W$1&" (7)",""))<lenb($Z652),1,IF(lenb(SUBSTITUTE($Z652,W$1&" (8)",""))<lenb($Z652),8,IF(lenb(SUBSTITUTE($Z652,W$1&" (9)",""))<lenb($Z652),9,IF(lenb(SUBSTITUTE($Z652,W$1&" (10)",""))<lenb($Z652),10,IF(lenb(SUBSTITUTE($Z652,W$1,""))<lenb($Z652),"ERROR",IF($Z652=$Y$1,"-",0)))))))))))) -> - | X652: =IF(lenb(SUBSTITUTE($Z652,X$1&" (1)",""))<lenb($Z652),1,IF(lenb(SUBSTITUTE($Z652,X$1&" (2)",""))<lenb($Z652),2,IF(lenb(SUBSTITUTE($Z652,X$1&" (3)",""))<lenb($Z652),3,IF(lenb(SUBSTITUTE($Z652,X$1&" (4)",""))<lenb($Z652),4,IF(lenb(SUBSTITUTE($Z652,X$1&" (5)",""))<lenb($Z652),5,IF(lenb(SUBSTITUTE($Z652,X$1&" (6)",""))<lenb($Z652),6,IF(lenb(SUBSTITUTE($Z652,X$1&" (7)",""))<lenb($Z652),1,IF(lenb(SUBSTITUTE($Z652,X$1&" (8)",""))<lenb($Z652),8,IF(lenb(SUBSTITUTE($Z652,X$1&" (9)",""))<lenb($Z652),9,IF(lenb(SUBSTITUTE($Z652,X$1&" (10)",""))<lenb($Z652),10,IF(lenb(SUBSTITUTE($Z652,X$1,""))<lenb($Z652),"ERROR",IF($Z652=$Y$1,"-",0)))))))))))) -> - | Y652: =IF(Z652=Y$1,1,"-") -> 1 | Z652: No links | AA652: =ifs(U652="","",U652="-",0,U652="Erro",0,U652<>"",LEN(U652)-LEN(SUBSTITUTE(U652,CHAR(10),""))+1) -> 0 | AB652: =COUNTIFS(Links!B:B,"ICSE",Links!C:C,A652,Links!AD:AD,1) -> 0 | AC652: - | AD652: =ifs(AE652="None.","No",AE652="-","No",AND(AE652<>"None.",AE652<>"-"),"Yes") -> No | AE652: - | AF652: ---- | AG652: ---- | AH652: ---- | AI652: =IF(AH652="----",IF(AG652="----",IF(AF652="----","----",AF652),AF652&CHAR(10)&AG652),AF652&CHAR(10)&AG652&CHAR(10)&AH652) -> ---- | AJ652: =IFERROR( if(and(K652="Yes",AD652="No"),"Paper has link but no statement", if(and(K652="No",AD652="No"),"Paper has no link and no statement", if(and(K652="Yes",AD652="Yes"),"Paper has link and statement", if(and(K652="No",AD652="Yes"),"Paper has no link but has statement","")))),"") -> Paper has no link and no statement | AK652: 45027 | AL652: Technical | AM652: ="[IP"&TEXT(A652,"0000")&"]" -> [IP0780]
A653: 781 | B653: Heaps'n Leaks: How Heap Snapshots Improve Android Taint Analysis | C653: 2020 | D653: Yes | E653: Yes | F653: No | G653: Yes | H653: No | I653: No | J653: - | K653: Yes | L653: No | M653: No | N653: No | O653: Yes | P653: Yes | Q653: No | R653: No | S653: 7 CONCLUSION --- HL Replicability | T653: https://bit.ly/38F5tUH (real link: https://zenodo.org/record/3627973#.Xi6jnxNKhTY) | U653: https://bit.ly/38F5tUH | V653: =IF(lenb(SUBSTITUTE($Z653,V$1&" (1)",""))<lenb($Z653),1,IF(lenb(SUBSTITUTE($Z653,V$1&" (2)",""))<lenb($Z653),2,IF(lenb(SUBSTITUTE($Z653,V$1&" (3)",""))<lenb($Z653),3,IF(lenb(SUBSTITUTE($Z653,V$1&" (4)",""))<lenb($Z653),4,IF(lenb(SUBSTITUTE($Z653,V$1&" (5)",""))<lenb($Z653),5,IF(lenb(SUBSTITUTE($Z653,V$1&" (6)",""))<lenb($Z653),6,IF(lenb(SUBSTITUTE($Z653,V$1&" (7)",""))<lenb($Z653),1,IF(lenb(SUBSTITUTE($Z653,V$1&" (8)",""))<lenb($Z653),8,IF(lenb(SUBSTITUTE($Z653,V$1&" (9)",""))<lenb($Z653),9,IF(lenb(SUBSTITUTE($Z653,V$1&" (10)",""))<lenb($Z653),10,IF(lenb(SUBSTITUTE($Z653,V$1,""))<lenb($Z653),"ERROR",IF($Z653=$Y$1,"-",0)))))))))))) -> 1 | W653: =IF(lenb(SUBSTITUTE($Z653,W$1&" (1)",""))<lenb($Z653),1,IF(lenb(SUBSTITUTE($Z653,W$1&" (2)",""))<lenb($Z653),2,IF(lenb(SUBSTITUTE($Z653,W$1&" (3)",""))<lenb($Z653),3,IF(lenb(SUBSTITUTE($Z653,W$1&" (4)",""))<lenb($Z653),4,IF(lenb(SUBSTITUTE($Z653,W$1&" (5)",""))<lenb($Z653),5,IF(lenb(SUBSTITUTE($Z653,W$1&" (6)",""))<lenb($Z653),6,IF(lenb(SUBSTITUTE($Z653,W$1&" (7)",""))<lenb($Z653),1,IF(lenb(SUBSTITUTE($Z653,W$1&" (8)",""))<lenb($Z653),8,IF(lenb(SUBSTITUTE($Z653,W$1&" (9)",""))<lenb($Z653),9,IF(lenb(SUBSTITUTE($Z653,W$1&" (10)",""))<lenb($Z653),10,IF(lenb(SUBSTITUTE($Z653,W$1,""))<lenb($Z653),"ERROR",IF($Z653=$Y$1,"-",0)))))))))))) -> 0 | X653: =IF(lenb(SUBSTITUTE($Z653,X$1&" (1)",""))<lenb($Z653),1,IF(lenb(SUBSTITUTE($Z653,X$1&" (2)",""))<lenb($Z653),2,IF(lenb(SUBSTITUTE($Z653,X$1&" (3)",""))<lenb($Z653),3,IF(lenb(SUBSTITUTE($Z653,X$1&" (4)",""))<lenb($Z653),4,IF(lenb(SUBSTITUTE($Z653,X$1&" (5)",""))<lenb($Z653),5,IF(lenb(SUBSTITUTE($Z653,X$1&" (6)",""))<lenb($Z653),6,IF(lenb(SUBSTITUTE($Z653,X$1&" (7)",""))<lenb($Z653),1,IF(lenb(SUBSTITUTE($Z653,X$1&" (8)",""))<lenb($Z653),8,IF(lenb(SUBSTITUTE($Z653,X$1&" (9)",""))<lenb($Z653),9,IF(lenb(SUBSTITUTE($Z653,X$1&" (10)",""))<lenb($Z653),10,IF(lenb(SUBSTITUTE($Z653,X$1,""))<lenb($Z653),"ERROR",IF($Z653=$Y$1,"-",0)))))))))))) -> 0 | Y653: =IF(Z653=Y$1,1,"-") -> - | Z653: Publicly available (1) | AA653: =ifs(U653="","",U653="-",0,U653="Erro",0,U653<>"",LEN(U653)-LEN(SUBSTITUTE(U653,CHAR(10),""))+1) -> 1 | AB653: =COUNTIFS(Links!B:B,"ICSE",Links!C:C,A653,Links!AD:AD,1) -> 0 | AC653: No | AD653: =ifs(AE653="None.","No",AE653="-","No",AND(AE653<>"None.",AE653<>"-"),"Yes") -> Yes | AE653: Because DroidMacroBench comprises closed-source apps we cannot legally make it available as open source. We will make it available to other researchers, though, through a password-protected website. DroidMacroBench will also be made available to the artifact evaluation. | AF653: Barriers (Agreements and legal rights) | AG653: Limited access (Credentials required) | AH653: Future plans (—) | AI653: =if(AH653="-",if(AG653="-",if(AF653="-","-",AF653),AF653&char(10)&AG653),AF653&char(10)&AG653&char(10)&AH653) -> Barriers (Agreements and legal rights) Limited access (Credentials required) Future plans (—) | AJ653: =IFERROR( if(and(K653="Yes",AD653="No"),"Paper has link but no statement", if(and(K653="No",AD653="No"),"Paper has no link and no statement", if(and(K653="Yes",AD653="Yes"),"Paper has link and statement", if(and(K653="No",AD653="Yes"),"Paper has no link but has statement","")))),"") -> Paper has link and statement | AK653: 45027 | AL653: Technical | AM653: ="[IP"&TEXT(A653,"0000")&"]" -> [IP0781]
A654: 782 | B654: Big Code != Big Vocabulary: Open-Vocabulary Models for Source Code | C654: 2020 | D654: Yes | E654: Yes | F654: No | G654: Yes | H654: No | I654: No | J654: - | K654: Yes | L654: No | M654: No | N654: No | O654: No | P654: No | Q654: Yes | R654: No | S654: - 10 ARTIFACTS --- Table 4 - 10 ARTIFACTS | T654: https://doi.org/10.5281/zenodo.3628775 https://doi.org/10.5281/zenodo.3628784 https://doi.org/10.5281/zenodo.3628665 https://doi.org/10.5281/zenodo.3628638 https://doi.org/10.5281/zenodo.3628636 https://doi.org/10.5281/zenodo.3629271 https://doi.org/10.5281/zenodo.3628628 https://github.com/mast-group/OpenVocabCodeNLM | U654: https://doi.org/10.5281/zenodo.3628775 https://doi.org/10.5281/zenodo.3628784 https://doi.org/10.5281/zenodo.3628665 https://doi.org/10.5281/zenodo.3628638 https://doi.org/10.5281/zenodo.3628636 https://doi.org/10.5281/zenodo.3629271 https://doi.org/10.5281/zenodo.3628628 https://github.com/mast-group/OpenVocabCodeNLM | V654: =IF(lenb(SUBSTITUTE($Z654,V$1&" (1)",""))<lenb($Z654),1,IF(lenb(SUBSTITUTE($Z654,V$1&" (2)",""))<lenb($Z654),2,IF(lenb(SUBSTITUTE($Z654,V$1&" (3)",""))<lenb($Z654),3,IF(lenb(SUBSTITUTE($Z654,V$1&" (4)",""))<lenb($Z654),4,IF(lenb(SUBSTITUTE($Z654,V$1&" (5)",""))<lenb($Z654),5,IF(lenb(SUBSTITUTE($Z654,V$1&" (6)",""))<lenb($Z654),6,IF(lenb(SUBSTITUTE($Z654,V$1&" (7)",""))<lenb($Z654),1,IF(lenb(SUBSTITUTE($Z654,V$1&" (8)",""))<lenb($Z654),8,IF(lenb(SUBSTITUTE($Z654,V$1&" (9)",""))<lenb($Z654),9,IF(lenb(SUBSTITUTE($Z654,V$1&" (10)",""))<lenb($Z654),10,IF(lenb(SUBSTITUTE($Z654,V$1,""))<lenb($Z654),"ERROR",IF($Z654=$Y$1,"-",0)))))))))))) -> 8 | W654: =IF(lenb(SUBSTITUTE($Z654,W$1&" (1)",""))<lenb($Z654),1,IF(lenb(SUBSTITUTE($Z654,W$1&" (2)",""))<lenb($Z654),2,IF(lenb(SUBSTITUTE($Z654,W$1&" (3)",""))<lenb($Z654),3,IF(lenb(SUBSTITUTE($Z654,W$1&" (4)",""))<lenb($Z654),4,IF(lenb(SUBSTITUTE($Z654,W$1&" (5)",""))<lenb($Z654),5,IF(lenb(SUBSTITUTE($Z654,W$1&" (6)",""))<lenb($Z654),6,IF(lenb(SUBSTITUTE($Z654,W$1&" (7)",""))<lenb($Z654),1,IF(lenb(SUBSTITUTE($Z654,W$1&" (8)",""))<lenb($Z654),8,IF(lenb(SUBSTITUTE($Z654,W$1&" (9)",""))<lenb($Z654),9,IF(lenb(SUBSTITUTE($Z654,W$1&" (10)",""))<lenb($Z654),10,IF(lenb(SUBSTITUTE($Z654,W$1,""))<lenb($Z654),"ERROR",IF($Z654=$Y$1,"-",0)))))))))))) -> 0 | X654: =IF(lenb(SUBSTITUTE($Z654,X$1&" (1)",""))<lenb($Z654),1,IF(lenb(SUBSTITUTE($Z654,X$1&" (2)",""))<lenb($Z654),2,IF(lenb(SUBSTITUTE($Z654,X$1&" (3)",""))<lenb($Z654),3,IF(lenb(SUBSTITUTE($Z654,X$1&" (4)",""))<lenb($Z654),4,IF(lenb(SUBSTITUTE($Z654,X$1&" (5)",""))<lenb($Z654),5,IF(lenb(SUBSTITUTE($Z654,X$1&" (6)",""))<lenb($Z654),6,IF(lenb(SUBSTITUTE($Z654,X$1&" (7)",""))<lenb($Z654),1,IF(lenb(SUBSTITUTE($Z654,X$1&" (8)",""))<lenb($Z654),8,IF(lenb(SUBSTITUTE($Z654,X$1&" (9)",""))<lenb($Z654),9,IF(lenb(SUBSTITUTE($Z654,X$1&" (10)",""))<lenb($Z654),10,IF(lenb(SUBSTITUTE($Z654,X$1,""))<lenb($Z654),"ERROR",IF($Z654=$Y$1,"-",0)))))))))))) -> 0 | Y654: =IF(Z654=Y$1,1,"-") -> - | Z654: Publicly available (8) | AA654: =ifs(U654="","",U654="-",0,U654="Erro",0,U654<>"",LEN(U654)-LEN(SUBSTITUTE(U654,CHAR(10),""))+1) -> 8 | AB654: =COUNTIFS(Links!B:B,"ICSE",Links!C:C,A654,Links!AD:AD,1) -> 0 | AC654: Yes | AD654: =ifs(AE654="None.","No",AE654="-","No",AND(AE654<>"None.",AE654<>"-"),"Yes") -> No | AE654: - | AF654: ---- | AG654: ---- | AH654: ---- | AI654: =IF(AH654="----",IF(AG654="----",IF(AF654="----","----",AF654),AF654&CHAR(10)&AG654),AF654&CHAR(10)&AG654&CHAR(10)&AH654) -> ---- | AJ654: =IFERROR( if(and(K654="Yes",AD654="No"),"Paper has link but no statement", if(and(K654="No",AD654="No"),"Paper has no link and no statement", if(and(K654="Yes",AD654="Yes"),"Paper has link and statement", if(and(K654="No",AD654="Yes"),"Paper has no link but has statement","")))),"") -> Paper has link but no statement | AK654: 45027 | AL654: Technical | AM654: ="[IP"&TEXT(A654,"0000")&"]" -> [IP0782]
A655: 783 | B655: Improving Data Scientist Efficiency with Provenance | C655: 2020 | D655: Yes | E655: Yes | F655: No | G655: Yes | H655: No | I655: No | J655: - | K655: Yes | L655: No | M655: Yes | N655: No | O655: No | P655: Yes | Q655: No | R655: Yes | S655: [28] 8 DISCUSSION --- HL Data Availability | T655: https://doi.org/10.5281/zenodo.3628097 | U655: https://doi.org/10.5281/zenodo.3628097 | V655: =IF(lenb(SUBSTITUTE($Z655,V$1&" (1)",""))<lenb($Z655),1,IF(lenb(SUBSTITUTE($Z655,V$1&" (2)",""))<lenb($Z655),2,IF(lenb(SUBSTITUTE($Z655,V$1&" (3)",""))<lenb($Z655),3,IF(lenb(SUBSTITUTE($Z655,V$1&" (4)",""))<lenb($Z655),4,IF(lenb(SUBSTITUTE($Z655,V$1&" (5)",""))<lenb($Z655),5,IF(lenb(SUBSTITUTE($Z655,V$1&" (6)",""))<lenb($Z655),6,IF(lenb(SUBSTITUTE($Z655,V$1&" (7)",""))<lenb($Z655),1,IF(lenb(SUBSTITUTE($Z655,V$1&" (8)",""))<lenb($Z655),8,IF(lenb(SUBSTITUTE($Z655,V$1&" (9)",""))<lenb($Z655),9,IF(lenb(SUBSTITUTE($Z655,V$1&" (10)",""))<lenb($Z655),10,IF(lenb(SUBSTITUTE($Z655,V$1,""))<lenb($Z655),"ERROR",IF($Z655=$Y$1,"-",0)))))))))))) -> 1 | W655: =IF(lenb(SUBSTITUTE($Z655,W$1&" (1)",""))<lenb($Z655),1,IF(lenb(SUBSTITUTE($Z655,W$1&" (2)",""))<lenb($Z655),2,IF(lenb(SUBSTITUTE($Z655,W$1&" (3)",""))<lenb($Z655),3,IF(lenb(SUBSTITUTE($Z655,W$1&" (4)",""))<lenb($Z655),4,IF(lenb(SUBSTITUTE($Z655,W$1&" (5)",""))<lenb($Z655),5,IF(lenb(SUBSTITUTE($Z655,W$1&" (6)",""))<lenb($Z655),6,IF(lenb(SUBSTITUTE($Z655,W$1&" (7)",""))<lenb($Z655),1,IF(lenb(SUBSTITUTE($Z655,W$1&" (8)",""))<lenb($Z655),8,IF(lenb(SUBSTITUTE($Z655,W$1&" (9)",""))<lenb($Z655),9,IF(lenb(SUBSTITUTE($Z655,W$1&" (10)",""))<lenb($Z655),10,IF(lenb(SUBSTITUTE($Z655,W$1,""))<lenb($Z655),"ERROR",IF($Z655=$Y$1,"-",0)))))))))))) -> 0 | X655: =IF(lenb(SUBSTITUTE($Z655,X$1&" (1)",""))<lenb($Z655),1,IF(lenb(SUBSTITUTE($Z655,X$1&" (2)",""))<lenb($Z655),2,IF(lenb(SUBSTITUTE($Z655,X$1&" (3)",""))<lenb($Z655),3,IF(lenb(SUBSTITUTE($Z655,X$1&" (4)",""))<lenb($Z655),4,IF(lenb(SUBSTITUTE($Z655,X$1&" (5)",""))<lenb($Z655),5,IF(lenb(SUBSTITUTE($Z655,X$1&" (6)",""))<lenb($Z655),6,IF(lenb(SUBSTITUTE($Z655,X$1&" (7)",""))<lenb($Z655),1,IF(lenb(SUBSTITUTE($Z655,X$1&" (8)",""))<lenb($Z655),8,IF(lenb(SUBSTITUTE($Z655,X$1&" (9)",""))<lenb($Z655),9,IF(lenb(SUBSTITUTE($Z655,X$1&" (10)",""))<lenb($Z655),10,IF(lenb(SUBSTITUTE($Z655,X$1,""))<lenb($Z655),"ERROR",IF($Z655=$Y$1,"-",0)))))))))))) -> 0 | Y655: =IF(Z655=Y$1,1,"-") -> - | Z655: Publicly available (1) | AA655: =ifs(U655="","",U655="-",0,U655="Erro",0,U655<>"",LEN(U655)-LEN(SUBSTITUTE(U655,CHAR(10),""))+1) -> 1 | AB655: =COUNTIFS(Links!B:B,"ICSE",Links!C:C,A655,Links!AD:AD,1) -> 0 | AC655: Yes | AD655: =ifs(AE655="None.","No",AE655="-","No",AND(AE655<>"None.",AE655<>"-"),"Yes") -> No | AE655: - | AF655: ---- | AG655: ---- | AH655: ---- | AI655: =IF(AH655="----",IF(AG655="----",IF(AF655="----","----",AF655),AF655&CHAR(10)&AG655),AF655&CHAR(10)&AG655&CHAR(10)&AH655) -> ---- | AJ655: =IFERROR( if(and(K655="Yes",AD655="No"),"Paper has link but no statement", if(and(K655="No",AD655="No"),"Paper has no link and no statement", if(and(K655="Yes",AD655="Yes"),"Paper has link and statement", if(and(K655="No",AD655="Yes"),"Paper has no link but has statement","")))),"") -> Paper has link but no statement | AK655: 45027 | AL655: Technical | AM655: ="[IP"&TEXT(A655,"0000")&"]" -> [IP0783]
A656: 784 | B656: Managing data constraints in database-backed web applications | C656: 2020 | D656: Yes | E656: Yes | F656: No | G656: Yes | H656: No | I656: No | J656: - | K656: Yes | L656: No | M656: Yes | N656: Yes | O656: No | P656: No | Q656: No | R656: No | S656: [12] 1 INTRODUCTION * | T656: https://hyperloop-rails.github.io/vibranium/ | U656: https://hyperloop-rails.github.io/vibranium/ | V656: =IF(lenb(SUBSTITUTE($Z656,V$1&" (1)",""))<lenb($Z656),1,IF(lenb(SUBSTITUTE($Z656,V$1&" (2)",""))<lenb($Z656),2,IF(lenb(SUBSTITUTE($Z656,V$1&" (3)",""))<lenb($Z656),3,IF(lenb(SUBSTITUTE($Z656,V$1&" (4)",""))<lenb($Z656),4,IF(lenb(SUBSTITUTE($Z656,V$1&" (5)",""))<lenb($Z656),5,IF(lenb(SUBSTITUTE($Z656,V$1&" (6)",""))<lenb($Z656),6,IF(lenb(SUBSTITUTE($Z656,V$1&" (7)",""))<lenb($Z656),1,IF(lenb(SUBSTITUTE($Z656,V$1&" (8)",""))<lenb($Z656),8,IF(lenb(SUBSTITUTE($Z656,V$1&" (9)",""))<lenb($Z656),9,IF(lenb(SUBSTITUTE($Z656,V$1&" (10)",""))<lenb($Z656),10,IF(lenb(SUBSTITUTE($Z656,V$1,""))<lenb($Z656),"ERROR",IF($Z656=$Y$1,"-",0)))))))))))) -> 1 | W656: =IF(lenb(SUBSTITUTE($Z656,W$1&" (1)",""))<lenb($Z656),1,IF(lenb(SUBSTITUTE($Z656,W$1&" (2)",""))<lenb($Z656),2,IF(lenb(SUBSTITUTE($Z656,W$1&" (3)",""))<lenb($Z656),3,IF(lenb(SUBSTITUTE($Z656,W$1&" (4)",""))<lenb($Z656),4,IF(lenb(SUBSTITUTE($Z656,W$1&" (5)",""))<lenb($Z656),5,IF(lenb(SUBSTITUTE($Z656,W$1&" (6)",""))<lenb($Z656),6,IF(lenb(SUBSTITUTE($Z656,W$1&" (7)",""))<lenb($Z656),1,IF(lenb(SUBSTITUTE($Z656,W$1&" (8)",""))<lenb($Z656),8,IF(lenb(SUBSTITUTE($Z656,W$1&" (9)",""))<lenb($Z656),9,IF(lenb(SUBSTITUTE($Z656,W$1&" (10)",""))<lenb($Z656),10,IF(lenb(SUBSTITUTE($Z656,W$1,""))<lenb($Z656),"ERROR",IF($Z656=$Y$1,"-",0)))))))))))) -> 0 | X656: =IF(lenb(SUBSTITUTE($Z656,X$1&" (1)",""))<lenb($Z656),1,IF(lenb(SUBSTITUTE($Z656,X$1&" (2)",""))<lenb($Z656),2,IF(lenb(SUBSTITUTE($Z656,X$1&" (3)",""))<lenb($Z656),3,IF(lenb(SUBSTITUTE($Z656,X$1&" (4)",""))<lenb($Z656),4,IF(lenb(SUBSTITUTE($Z656,X$1&" (5)",""))<lenb($Z656),5,IF(lenb(SUBSTITUTE($Z656,X$1&" (6)",""))<lenb($Z656),6,IF(lenb(SUBSTITUTE($Z656,X$1&" (7)",""))<lenb($Z656),1,IF(lenb(SUBSTITUTE($Z656,X$1&" (8)",""))<lenb($Z656),8,IF(lenb(SUBSTITUTE($Z656,X$1&" (9)",""))<lenb($Z656),9,IF(lenb(SUBSTITUTE($Z656,X$1&" (10)",""))<lenb($Z656),10,IF(lenb(SUBSTITUTE($Z656,X$1,""))<lenb($Z656),"ERROR",IF($Z656=$Y$1,"-",0)))))))))))) -> 0 | Y656: =IF(Z656=Y$1,1,"-") -> - | Z656: Publicly available (1) | AA656: =ifs(U656="","",U656="-",0,U656="Erro",0,U656<>"",LEN(U656)-LEN(SUBSTITUTE(U656,CHAR(10),""))+1) -> 1 | AB656: =COUNTIFS(Links!B:B,"ICSE",Links!C:C,A656,Links!AD:AD,1) -> 0 | AC656: No | AD656: =ifs(AE656="None.","No",AE656="-","No",AND(AE656<>"None.",AE656<>"-"),"Yes") -> No | AE656: - | AF656: ---- | AG656: ---- | AH656: ---- | AI656: =IF(AH656="----",IF(AG656="----",IF(AF656="----","----",AF656),AF656&CHAR(10)&AG656),AF656&CHAR(10)&AG656&CHAR(10)&AH656) -> ---- | AJ656: =IFERROR( if(and(K656="Yes",AD656="No"),"Paper has link but no statement", if(and(K656="No",AD656="No"),"Paper has no link and no statement", if(and(K656="Yes",AD656="Yes"),"Paper has link and statement", if(and(K656="No",AD656="Yes"),"Paper has no link but has statement","")))),"") -> Paper has link but no statement | AK656: 45027 | AL656: Technical | AM656: ="[IP"&TEXT(A656,"0000")&"]" -> [IP0784]
A657: 785 | B657: Taxonomy of Real Faults in Deep Learning Systems | C657: 2020 | D657: Yes | E657: Yes | F657: No | G657: Yes | H657: No | I657: No | J657: - | K657: Yes | L657: No | M657: Yes | N657: No | O657: No | P657: No | Q657: No | R657: Yes | S657: [8] - 3 METHODOLOGY * (3x) - 4 RESULTS | T657: https://github.com/dlfaults/dl_faults | U657: https://github.com/dlfaults/dl_faults | V657: =IF(lenb(SUBSTITUTE($Z657,V$1&" (1)",""))<lenb($Z657),1,IF(lenb(SUBSTITUTE($Z657,V$1&" (2)",""))<lenb($Z657),2,IF(lenb(SUBSTITUTE($Z657,V$1&" (3)",""))<lenb($Z657),3,IF(lenb(SUBSTITUTE($Z657,V$1&" (4)",""))<lenb($Z657),4,IF(lenb(SUBSTITUTE($Z657,V$1&" (5)",""))<lenb($Z657),5,IF(lenb(SUBSTITUTE($Z657,V$1&" (6)",""))<lenb($Z657),6,IF(lenb(SUBSTITUTE($Z657,V$1&" (7)",""))<lenb($Z657),1,IF(lenb(SUBSTITUTE($Z657,V$1&" (8)",""))<lenb($Z657),8,IF(lenb(SUBSTITUTE($Z657,V$1&" (9)",""))<lenb($Z657),9,IF(lenb(SUBSTITUTE($Z657,V$1&" (10)",""))<lenb($Z657),10,IF(lenb(SUBSTITUTE($Z657,V$1,""))<lenb($Z657),"ERROR",IF($Z657=$Y$1,"-",0)))))))))))) -> 1 | W657: =IF(lenb(SUBSTITUTE($Z657,W$1&" (1)",""))<lenb($Z657),1,IF(lenb(SUBSTITUTE($Z657,W$1&" (2)",""))<lenb($Z657),2,IF(lenb(SUBSTITUTE($Z657,W$1&" (3)",""))<lenb($Z657),3,IF(lenb(SUBSTITUTE($Z657,W$1&" (4)",""))<lenb($Z657),4,IF(lenb(SUBSTITUTE($Z657,W$1&" (5)",""))<lenb($Z657),5,IF(lenb(SUBSTITUTE($Z657,W$1&" (6)",""))<lenb($Z657),6,IF(lenb(SUBSTITUTE($Z657,W$1&" (7)",""))<lenb($Z657),1,IF(lenb(SUBSTITUTE($Z657,W$1&" (8)",""))<lenb($Z657),8,IF(lenb(SUBSTITUTE($Z657,W$1&" (9)",""))<lenb($Z657),9,IF(lenb(SUBSTITUTE($Z657,W$1&" (10)",""))<lenb($Z657),10,IF(lenb(SUBSTITUTE($Z657,W$1,""))<lenb($Z657),"ERROR",IF($Z657=$Y$1,"-",0)))))))))))) -> 0 | X657: =IF(lenb(SUBSTITUTE($Z657,X$1&" (1)",""))<lenb($Z657),1,IF(lenb(SUBSTITUTE($Z657,X$1&" (2)",""))<lenb($Z657),2,IF(lenb(SUBSTITUTE($Z657,X$1&" (3)",""))<lenb($Z657),3,IF(lenb(SUBSTITUTE($Z657,X$1&" (4)",""))<lenb($Z657),4,IF(lenb(SUBSTITUTE($Z657,X$1&" (5)",""))<lenb($Z657),5,IF(lenb(SUBSTITUTE($Z657,X$1&" (6)",""))<lenb($Z657),6,IF(lenb(SUBSTITUTE($Z657,X$1&" (7)",""))<lenb($Z657),1,IF(lenb(SUBSTITUTE($Z657,X$1&" (8)",""))<lenb($Z657),8,IF(lenb(SUBSTITUTE($Z657,X$1&" (9)",""))<lenb($Z657),9,IF(lenb(SUBSTITUTE($Z657,X$1&" (10)",""))<lenb($Z657),10,IF(lenb(SUBSTITUTE($Z657,X$1,""))<lenb($Z657),"ERROR",IF($Z657=$Y$1,"-",0)))))))))))) -> 0 | Y657: =IF(Z657=Y$1,1,"-") -> - | Z657: Publicly available (1) | AA657: =ifs(U657="","",U657="-",0,U657="Erro",0,U657<>"",LEN(U657)-LEN(SUBSTITUTE(U657,CHAR(10),""))+1) -> 1 | AB657: =COUNTIFS(Links!B:B,"ICSE",Links!C:C,A657,Links!AD:AD,1) -> 0 | AC657: No | AD657: =ifs(AE657="None.","No",AE657="-","No",AND(AE657<>"None.",AE657<>"-"),"Yes") -> No | AE657: - | AF657: ---- | AG657: ---- | AH657: ---- | AI657: =IF(AH657="----",IF(AG657="----",IF(AF657="----","----",AF657),AF657&CHAR(10)&AG657),AF657&CHAR(10)&AG657&CHAR(10)&AH657) -> ---- | AJ657: =IFERROR( if(and(K657="Yes",AD657="No"),"Paper has link but no statement", if(and(K657="No",AD657="No"),"Paper has no link and no statement", if(and(K657="Yes",AD657="Yes"),"Paper has link and statement", if(and(K657="No",AD657="Yes"),"Paper has no link but has statement","")))),"") -> Paper has link but no statement | AK657: 45027 | AL657: Technical | AM657: ="[IP"&TEXT(A657,"0000")&"]" -> [IP0785]
A658: 786 | B658: Testing DNN Image Classifiers for Confusion & Bias Errors | C658: 2020 | D658: Yes | E658: Yes | F658: No | G658: Yes | H658: No | I658: No | J658: - | K658: Yes | L658: No | M658: No | N658: Yes | O658: No | P658: No | Q658: No | R658: No | S658: Links in "1 INTRODUCTION | T658: https://github.com/ARiSE-Lab/DeepInspect https://www.ariselab.info/deepinspect | U658: https://github.com/ARiSE-Lab/DeepInspect https://www.ariselab.info/deepinspect | V658: =IF(lenb(SUBSTITUTE($Z658,V$1&" (1)",""))<lenb($Z658),1,IF(lenb(SUBSTITUTE($Z658,V$1&" (2)",""))<lenb($Z658),2,IF(lenb(SUBSTITUTE($Z658,V$1&" (3)",""))<lenb($Z658),3,IF(lenb(SUBSTITUTE($Z658,V$1&" (4)",""))<lenb($Z658),4,IF(lenb(SUBSTITUTE($Z658,V$1&" (5)",""))<lenb($Z658),5,IF(lenb(SUBSTITUTE($Z658,V$1&" (6)",""))<lenb($Z658),6,IF(lenb(SUBSTITUTE($Z658,V$1&" (7)",""))<lenb($Z658),1,IF(lenb(SUBSTITUTE($Z658,V$1&" (8)",""))<lenb($Z658),8,IF(lenb(SUBSTITUTE($Z658,V$1&" (9)",""))<lenb($Z658),9,IF(lenb(SUBSTITUTE($Z658,V$1&" (10)",""))<lenb($Z658),10,IF(lenb(SUBSTITUTE($Z658,V$1,""))<lenb($Z658),"ERROR",IF($Z658=$Y$1,"-",0)))))))))))) -> 2 | W658: =IF(lenb(SUBSTITUTE($Z658,W$1&" (1)",""))<lenb($Z658),1,IF(lenb(SUBSTITUTE($Z658,W$1&" (2)",""))<lenb($Z658),2,IF(lenb(SUBSTITUTE($Z658,W$1&" (3)",""))<lenb($Z658),3,IF(lenb(SUBSTITUTE($Z658,W$1&" (4)",""))<lenb($Z658),4,IF(lenb(SUBSTITUTE($Z658,W$1&" (5)",""))<lenb($Z658),5,IF(lenb(SUBSTITUTE($Z658,W$1&" (6)",""))<lenb($Z658),6,IF(lenb(SUBSTITUTE($Z658,W$1&" (7)",""))<lenb($Z658),1,IF(lenb(SUBSTITUTE($Z658,W$1&" (8)",""))<lenb($Z658),8,IF(lenb(SUBSTITUTE($Z658,W$1&" (9)",""))<lenb($Z658),9,IF(lenb(SUBSTITUTE($Z658,W$1&" (10)",""))<lenb($Z658),10,IF(lenb(SUBSTITUTE($Z658,W$1,""))<lenb($Z658),"ERROR",IF($Z658=$Y$1,"-",0)))))))))))) -> 0 | X658: =IF(lenb(SUBSTITUTE($Z658,X$1&" (1)",""))<lenb($Z658),1,IF(lenb(SUBSTITUTE($Z658,X$1&" (2)",""))<lenb($Z658),2,IF(lenb(SUBSTITUTE($Z658,X$1&" (3)",""))<lenb($Z658),3,IF(lenb(SUBSTITUTE($Z658,X$1&" (4)",""))<lenb($Z658),4,IF(lenb(SUBSTITUTE($Z658,X$1&" (5)",""))<lenb($Z658),5,IF(lenb(SUBSTITUTE($Z658,X$1&" (6)",""))<lenb($Z658),6,IF(lenb(SUBSTITUTE($Z658,X$1&" (7)",""))<lenb($Z658),1,IF(lenb(SUBSTITUTE($Z658,X$1&" (8)",""))<lenb($Z658),8,IF(lenb(SUBSTITUTE($Z658,X$1&" (9)",""))<lenb($Z658),9,IF(lenb(SUBSTITUTE($Z658,X$1&" (10)",""))<lenb($Z658),10,IF(lenb(SUBSTITUTE($Z658,X$1,""))<lenb($Z658),"ERROR",IF($Z658=$Y$1,"-",0)))))))))))) -> 0 | Y658: =IF(Z658=Y$1,1,"-") -> - | Z658: Publicly available (2) | AA658: =ifs(U658="","",U658="-",0,U658="Erro",0,U658<>"",LEN(U658)-LEN(SUBSTITUTE(U658,CHAR(10),""))+1) -> 2 | AB658: =COUNTIFS(Links!B:B,"ICSE",Links!C:C,A658,Links!AD:AD,1) -> 0 | AC658: No | AD658: =ifs(AE658="None.","No",AE658="-","No",AND(AE658<>"None.",AE658<>"-"),"Yes") -> No | AE658: - | AF658: ---- | AG658: ---- | AH658: ---- | AI658: =IF(AH658="----",IF(AG658="----",IF(AF658="----","----",AF658),AF658&CHAR(10)&AG658),AF658&CHAR(10)&AG658&CHAR(10)&AH658) -> ---- | AJ658: =IFERROR( if(and(K658="Yes",AD658="No"),"Paper has link but no statement", if(and(K658="No",AD658="No"),"Paper has no link and no statement", if(and(K658="Yes",AD658="Yes"),"Paper has link and statement", if(and(K658="No",AD658="Yes"),"Paper has no link but has statement","")))),"") -> Paper has link but no statement | AK658: 45027 | AL658: Technical | AM658: ="[IP"&TEXT(A658,"0000")&"]" -> [IP0786]
A659: 787 | B659: Repairing Deep Neural Networks: Fix Patterns and Challenges | C659: 2020 | D659: Yes | E659: Yes | F659: No | G659: Yes | H659: No | I659: No | J659: - | K659: Yes | L659: No | M659: Yes | N659: Yes | O659: No | P659: No | Q659: No | R659: No | S659: [13] 1 INTRODUCTION | T659: https://github.com/lab-design/ICSE2020DNNBugRepair | U659: https://github.com/lab-design/ICSE2020DNNBugRepair | V659: =IF(lenb(SUBSTITUTE($Z659,V$1&" (1)",""))<lenb($Z659),1,IF(lenb(SUBSTITUTE($Z659,V$1&" (2)",""))<lenb($Z659),2,IF(lenb(SUBSTITUTE($Z659,V$1&" (3)",""))<lenb($Z659),3,IF(lenb(SUBSTITUTE($Z659,V$1&" (4)",""))<lenb($Z659),4,IF(lenb(SUBSTITUTE($Z659,V$1&" (5)",""))<lenb($Z659),5,IF(lenb(SUBSTITUTE($Z659,V$1&" (6)",""))<lenb($Z659),6,IF(lenb(SUBSTITUTE($Z659,V$1&" (7)",""))<lenb($Z659),1,IF(lenb(SUBSTITUTE($Z659,V$1&" (8)",""))<lenb($Z659),8,IF(lenb(SUBSTITUTE($Z659,V$1&" (9)",""))<lenb($Z659),9,IF(lenb(SUBSTITUTE($Z659,V$1&" (10)",""))<lenb($Z659),10,IF(lenb(SUBSTITUTE($Z659,V$1,""))<lenb($Z659),"ERROR",IF($Z659=$Y$1,"-",0)))))))))))) -> 1 | W659: =IF(lenb(SUBSTITUTE($Z659,W$1&" (1)",""))<lenb($Z659),1,IF(lenb(SUBSTITUTE($Z659,W$1&" (2)",""))<lenb($Z659),2,IF(lenb(SUBSTITUTE($Z659,W$1&" (3)",""))<lenb($Z659),3,IF(lenb(SUBSTITUTE($Z659,W$1&" (4)",""))<lenb($Z659),4,IF(lenb(SUBSTITUTE($Z659,W$1&" (5)",""))<lenb($Z659),5,IF(lenb(SUBSTITUTE($Z659,W$1&" (6)",""))<lenb($Z659),6,IF(lenb(SUBSTITUTE($Z659,W$1&" (7)",""))<lenb($Z659),1,IF(lenb(SUBSTITUTE($Z659,W$1&" (8)",""))<lenb($Z659),8,IF(lenb(SUBSTITUTE($Z659,W$1&" (9)",""))<lenb($Z659),9,IF(lenb(SUBSTITUTE($Z659,W$1&" (10)",""))<lenb($Z659),10,IF(lenb(SUBSTITUTE($Z659,W$1,""))<lenb($Z659),"ERROR",IF($Z659=$Y$1,"-",0)))))))))))) -> 0 | X659: =IF(lenb(SUBSTITUTE($Z659,X$1&" (1)",""))<lenb($Z659),1,IF(lenb(SUBSTITUTE($Z659,X$1&" (2)",""))<lenb($Z659),2,IF(lenb(SUBSTITUTE($Z659,X$1&" (3)",""))<lenb($Z659),3,IF(lenb(SUBSTITUTE($Z659,X$1&" (4)",""))<lenb($Z659),4,IF(lenb(SUBSTITUTE($Z659,X$1&" (5)",""))<lenb($Z659),5,IF(lenb(SUBSTITUTE($Z659,X$1&" (6)",""))<lenb($Z659),6,IF(lenb(SUBSTITUTE($Z659,X$1&" (7)",""))<lenb($Z659),1,IF(lenb(SUBSTITUTE($Z659,X$1&" (8)",""))<lenb($Z659),8,IF(lenb(SUBSTITUTE($Z659,X$1&" (9)",""))<lenb($Z659),9,IF(lenb(SUBSTITUTE($Z659,X$1&" (10)",""))<lenb($Z659),10,IF(lenb(SUBSTITUTE($Z659,X$1,""))<lenb($Z659),"ERROR",IF($Z659=$Y$1,"-",0)))))))))))) -> 0 | Y659: =IF(Z659=Y$1,1,"-") -> - | Z659: Publicly available (1) | AA659: =ifs(U659="","",U659="-",0,U659="Erro",0,U659<>"",LEN(U659)-LEN(SUBSTITUTE(U659,CHAR(10),""))+1) -> 1 | AB659: =COUNTIFS(Links!B:B,"ICSE",Links!C:C,A659,Links!AD:AD,1) -> 0 | AC659: No | AD659: =ifs(AE659="None.","No",AE659="-","No",AND(AE659<>"None.",AE659<>"-"),"Yes") -> No | AE659: - | AF659: ---- | AG659: ---- | AH659: ---- | AI659: =IF(AH659="----",IF(AG659="----",IF(AF659="----","----",AF659),AF659&CHAR(10)&AG659),AF659&CHAR(10)&AG659&CHAR(10)&AH659) -> ---- | AJ659: =IFERROR( if(and(K659="Yes",AD659="No"),"Paper has link but no statement", if(and(K659="No",AD659="No"),"Paper has no link and no statement", if(and(K659="Yes",AD659="Yes"),"Paper has link and statement", if(and(K659="No",AD659="Yes"),"Paper has no link but has statement","")))),"") -> Paper has link but no statement | AK659: 45027 | AL659: Technical | AM659: ="[IP"&TEXT(A659,"0000")&"]" -> [IP0787]
A660: 788 | B660: Fuzz Testing based Data Augmentation to Improve Robustness of Deep Neural Networks | C660: 2020 | D660: No | E660: - | F660: - | G660: - | H660: - | I660: - | J660: - | K660: Yes | L660: Yes | M660: No | N660: No | O660: No | P660: No | Q660: Yes | R660: Yes | S660: FN 1 - 4 EXPERIMENTAL SETUP --- 4.1 Dataset and Models | T660: https://sensei-2020.github.io | U660: https://sensei-2020.github.io | V660: =IF(lenb(SUBSTITUTE($Z660,V$1&" (1)",""))<lenb($Z660),1,IF(lenb(SUBSTITUTE($Z660,V$1&" (2)",""))<lenb($Z660),2,IF(lenb(SUBSTITUTE($Z660,V$1&" (3)",""))<lenb($Z660),3,IF(lenb(SUBSTITUTE($Z660,V$1&" (4)",""))<lenb($Z660),4,IF(lenb(SUBSTITUTE($Z660,V$1&" (5)",""))<lenb($Z660),5,IF(lenb(SUBSTITUTE($Z660,V$1&" (6)",""))<lenb($Z660),6,IF(lenb(SUBSTITUTE($Z660,V$1&" (7)",""))<lenb($Z660),1,IF(lenb(SUBSTITUTE($Z660,V$1&" (8)",""))<lenb($Z660),8,IF(lenb(SUBSTITUTE($Z660,V$1&" (9)",""))<lenb($Z660),9,IF(lenb(SUBSTITUTE($Z660,V$1&" (10)",""))<lenb($Z660),10,IF(lenb(SUBSTITUTE($Z660,V$1,""))<lenb($Z660),"ERROR",IF($Z660=$Y$1,"-",0)))))))))))) -> 1 | W660: =IF(lenb(SUBSTITUTE($Z660,W$1&" (1)",""))<lenb($Z660),1,IF(lenb(SUBSTITUTE($Z660,W$1&" (2)",""))<lenb($Z660),2,IF(lenb(SUBSTITUTE($Z660,W$1&" (3)",""))<lenb($Z660),3,IF(lenb(SUBSTITUTE($Z660,W$1&" (4)",""))<lenb($Z660),4,IF(lenb(SUBSTITUTE($Z660,W$1&" (5)",""))<lenb($Z660),5,IF(lenb(SUBSTITUTE($Z660,W$1&" (6)",""))<lenb($Z660),6,IF(lenb(SUBSTITUTE($Z660,W$1&" (7)",""))<lenb($Z660),1,IF(lenb(SUBSTITUTE($Z660,W$1&" (8)",""))<lenb($Z660),8,IF(lenb(SUBSTITUTE($Z660,W$1&" (9)",""))<lenb($Z660),9,IF(lenb(SUBSTITUTE($Z660,W$1&" (10)",""))<lenb($Z660),10,IF(lenb(SUBSTITUTE($Z660,W$1,""))<lenb($Z660),"ERROR",IF($Z660=$Y$1,"-",0)))))))))))) -> 0 | X660: =IF(lenb(SUBSTITUTE($Z660,X$1&" (1)",""))<lenb($Z660),1,IF(lenb(SUBSTITUTE($Z660,X$1&" (2)",""))<lenb($Z660),2,IF(lenb(SUBSTITUTE($Z660,X$1&" (3)",""))<lenb($Z660),3,IF(lenb(SUBSTITUTE($Z660,X$1&" (4)",""))<lenb($Z660),4,IF(lenb(SUBSTITUTE($Z660,X$1&" (5)",""))<lenb($Z660),5,IF(lenb(SUBSTITUTE($Z660,X$1&" (6)",""))<lenb($Z660),6,IF(lenb(SUBSTITUTE($Z660,X$1&" (7)",""))<lenb($Z660),1,IF(lenb(SUBSTITUTE($Z660,X$1&" (8)",""))<lenb($Z660),8,IF(lenb(SUBSTITUTE($Z660,X$1&" (9)",""))<lenb($Z660),9,IF(lenb(SUBSTITUTE($Z660,X$1&" (10)",""))<lenb($Z660),10,IF(lenb(SUBSTITUTE($Z660,X$1,""))<lenb($Z660),"ERROR",IF($Z660=$Y$1,"-",0)))))))))))) -> 0 | Y660: =IF(Z660=Y$1,1,"-") -> - | Z660: Publicly available (1) | AA660: =ifs(U660="","",U660="-",0,U660="Erro",0,U660<>"",LEN(U660)-LEN(SUBSTITUTE(U660,CHAR(10),""))+1) -> 1 | AB660: =COUNTIFS(Links!B:B,"ICSE",Links!C:C,A660,Links!AD:AD,1) -> 0 | AC660: No | AD660: =ifs(AE660="None.","No",AE660="-","No",AND(AE660<>"None.",AE660<>"-"),"Yes") -> No | AE660: - | AF660: ---- | AG660: ---- | AH660: ---- | AI660: =IF(AH660="----",IF(AG660="----",IF(AF660="----","----",AF660),AF660&CHAR(10)&AG660),AF660&CHAR(10)&AG660&CHAR(10)&AH660) -> ---- | AJ660: =IFERROR( if(and(K660="Yes",AD660="No"),"Paper has link but no statement", if(and(K660="No",AD660="No"),"Paper has no link and no statement", if(and(K660="Yes",AD660="Yes"),"Paper has link and statement", if(and(K660="No",AD660="Yes"),"Paper has no link but has statement","")))),"") -> Paper has link but no statement | AK660: 45027 | AL660: Technical | AM660: ="[IP"&TEXT(A660,"0000")&"]" -> [IP0788]
A661: 789 | B661: An Empirical Study on Program Failures of Deep Learning Jobs | C661: 2020 | D661: No | E661: - | F661: - | G661: - | H661: - | I661: - | J661: - | K661: No | L661: - | M661: - | N661: - | O661: - | P661: - | Q661: - | R661: - | S661: - | T661: - | U661: - | V661: =IF(lenb(SUBSTITUTE($Z661,V$1&" (1)",""))<lenb($Z661),1,IF(lenb(SUBSTITUTE($Z661,V$1&" (2)",""))<lenb($Z661),2,IF(lenb(SUBSTITUTE($Z661,V$1&" (3)",""))<lenb($Z661),3,IF(lenb(SUBSTITUTE($Z661,V$1&" (4)",""))<lenb($Z661),4,IF(lenb(SUBSTITUTE($Z661,V$1&" (5)",""))<lenb($Z661),5,IF(lenb(SUBSTITUTE($Z661,V$1&" (6)",""))<lenb($Z661),6,IF(lenb(SUBSTITUTE($Z661,V$1&" (7)",""))<lenb($Z661),1,IF(lenb(SUBSTITUTE($Z661,V$1&" (8)",""))<lenb($Z661),8,IF(lenb(SUBSTITUTE($Z661,V$1&" (9)",""))<lenb($Z661),9,IF(lenb(SUBSTITUTE($Z661,V$1&" (10)",""))<lenb($Z661),10,IF(lenb(SUBSTITUTE($Z661,V$1,""))<lenb($Z661),"ERROR",IF($Z661=$Y$1,"-",0)))))))))))) -> - | W661: =IF(lenb(SUBSTITUTE($Z661,W$1&" (1)",""))<lenb($Z661),1,IF(lenb(SUBSTITUTE($Z661,W$1&" (2)",""))<lenb($Z661),2,IF(lenb(SUBSTITUTE($Z661,W$1&" (3)",""))<lenb($Z661),3,IF(lenb(SUBSTITUTE($Z661,W$1&" (4)",""))<lenb($Z661),4,IF(lenb(SUBSTITUTE($Z661,W$1&" (5)",""))<lenb($Z661),5,IF(lenb(SUBSTITUTE($Z661,W$1&" (6)",""))<lenb($Z661),6,IF(lenb(SUBSTITUTE($Z661,W$1&" (7)",""))<lenb($Z661),1,IF(lenb(SUBSTITUTE($Z661,W$1&" (8)",""))<lenb($Z661),8,IF(lenb(SUBSTITUTE($Z661,W$1&" (9)",""))<lenb($Z661),9,IF(lenb(SUBSTITUTE($Z661,W$1&" (10)",""))<lenb($Z661),10,IF(lenb(SUBSTITUTE($Z661,W$1,""))<lenb($Z661),"ERROR",IF($Z661=$Y$1,"-",0)))))))))))) -> - | X661: =IF(lenb(SUBSTITUTE($Z661,X$1&" (1)",""))<lenb($Z661),1,IF(lenb(SUBSTITUTE($Z661,X$1&" (2)",""))<lenb($Z661),2,IF(lenb(SUBSTITUTE($Z661,X$1&" (3)",""))<lenb($Z661),3,IF(lenb(SUBSTITUTE($Z661,X$1&" (4)",""))<lenb($Z661),4,IF(lenb(SUBSTITUTE($Z661,X$1&" (5)",""))<lenb($Z661),5,IF(lenb(SUBSTITUTE($Z661,X$1&" (6)",""))<lenb($Z661),6,IF(lenb(SUBSTITUTE($Z661,X$1&" (7)",""))<lenb($Z661),1,IF(lenb(SUBSTITUTE($Z661,X$1&" (8)",""))<lenb($Z661),8,IF(lenb(SUBSTITUTE($Z661,X$1&" (9)",""))<lenb($Z661),9,IF(lenb(SUBSTITUTE($Z661,X$1&" (10)",""))<lenb($Z661),10,IF(lenb(SUBSTITUTE($Z661,X$1,""))<lenb($Z661),"ERROR",IF($Z661=$Y$1,"-",0)))))))))))) -> - | Y661: =IF(Z661=Y$1,1,"-") -> 1 | Z661: No links | AA661: =ifs(U661="","",U661="-",0,U661="Erro",0,U661<>"",LEN(U661)-LEN(SUBSTITUTE(U661,CHAR(10),""))+1) -> 0 | AB661: =COUNTIFS(Links!B:B,"ICSE",Links!C:C,A661,Links!AD:AD,1) -> 0 | AC661: - | AD661: =ifs(AE661="None.","No",AE661="-","No",AND(AE661<>"None.",AE661<>"-"),"Yes") -> No | AE661: - | AF661: ---- | AG661: ---- | AH661: ---- | AI661: =IF(AH661="----",IF(AG661="----",IF(AF661="----","----",AF661),AF661&CHAR(10)&AG661),AF661&CHAR(10)&AG661&CHAR(10)&AH661) -> ---- | AJ661: =IFERROR( if(and(K661="Yes",AD661="No"),"Paper has link but no statement", if(and(K661="No",AD661="No"),"Paper has no link and no statement", if(and(K661="Yes",AD661="Yes"),"Paper has link and statement", if(and(K661="No",AD661="Yes"),"Paper has no link but has statement","")))),"") -> Paper has no link and no statement | AK661: 45027 | AL661: Technical | AM661: ="[IP"&TEXT(A661,"0000")&"]" -> [IP0789]
A662: 790 | B662: Primers or Reminders? The Effects of Existing Review Comments on Code Review | C662: 2020 | D662: Yes | E662: Yes | F662: No | G662: Yes | H662: No | I662: No | J662: - | K662: Yes | L662: No | M662: Yes | N662: No | O662: No | P662: No | Q662: No | R662: Yes | S662: - Abstract - [45] 3 EXPERIMENTAL DESIGN * | T662: https://doi.org/10.5281/zenodo.3653856 | U662: https://doi.org/10.5281/zenodo.3653856 | V662: =IF(lenb(SUBSTITUTE($Z662,V$1&" (1)",""))<lenb($Z662),1,IF(lenb(SUBSTITUTE($Z662,V$1&" (2)",""))<lenb($Z662),2,IF(lenb(SUBSTITUTE($Z662,V$1&" (3)",""))<lenb($Z662),3,IF(lenb(SUBSTITUTE($Z662,V$1&" (4)",""))<lenb($Z662),4,IF(lenb(SUBSTITUTE($Z662,V$1&" (5)",""))<lenb($Z662),5,IF(lenb(SUBSTITUTE($Z662,V$1&" (6)",""))<lenb($Z662),6,IF(lenb(SUBSTITUTE($Z662,V$1&" (7)",""))<lenb($Z662),1,IF(lenb(SUBSTITUTE($Z662,V$1&" (8)",""))<lenb($Z662),8,IF(lenb(SUBSTITUTE($Z662,V$1&" (9)",""))<lenb($Z662),9,IF(lenb(SUBSTITUTE($Z662,V$1&" (10)",""))<lenb($Z662),10,IF(lenb(SUBSTITUTE($Z662,V$1,""))<lenb($Z662),"ERROR",IF($Z662=$Y$1,"-",0)))))))))))) -> 1 | W662: =IF(lenb(SUBSTITUTE($Z662,W$1&" (1)",""))<lenb($Z662),1,IF(lenb(SUBSTITUTE($Z662,W$1&" (2)",""))<lenb($Z662),2,IF(lenb(SUBSTITUTE($Z662,W$1&" (3)",""))<lenb($Z662),3,IF(lenb(SUBSTITUTE($Z662,W$1&" (4)",""))<lenb($Z662),4,IF(lenb(SUBSTITUTE($Z662,W$1&" (5)",""))<lenb($Z662),5,IF(lenb(SUBSTITUTE($Z662,W$1&" (6)",""))<lenb($Z662),6,IF(lenb(SUBSTITUTE($Z662,W$1&" (7)",""))<lenb($Z662),1,IF(lenb(SUBSTITUTE($Z662,W$1&" (8)",""))<lenb($Z662),8,IF(lenb(SUBSTITUTE($Z662,W$1&" (9)",""))<lenb($Z662),9,IF(lenb(SUBSTITUTE($Z662,W$1&" (10)",""))<lenb($Z662),10,IF(lenb(SUBSTITUTE($Z662,W$1,""))<lenb($Z662),"ERROR",IF($Z662=$Y$1,"-",0)))))))))))) -> 0 | X662: =IF(lenb(SUBSTITUTE($Z662,X$1&" (1)",""))<lenb($Z662),1,IF(lenb(SUBSTITUTE($Z662,X$1&" (2)",""))<lenb($Z662),2,IF(lenb(SUBSTITUTE($Z662,X$1&" (3)",""))<lenb($Z662),3,IF(lenb(SUBSTITUTE($Z662,X$1&" (4)",""))<lenb($Z662),4,IF(lenb(SUBSTITUTE($Z662,X$1&" (5)",""))<lenb($Z662),5,IF(lenb(SUBSTITUTE($Z662,X$1&" (6)",""))<lenb($Z662),6,IF(lenb(SUBSTITUTE($Z662,X$1&" (7)",""))<lenb($Z662),1,IF(lenb(SUBSTITUTE($Z662,X$1&" (8)",""))<lenb($Z662),8,IF(lenb(SUBSTITUTE($Z662,X$1&" (9)",""))<lenb($Z662),9,IF(lenb(SUBSTITUTE($Z662,X$1&" (10)",""))<lenb($Z662),10,IF(lenb(SUBSTITUTE($Z662,X$1,""))<lenb($Z662),"ERROR",IF($Z662=$Y$1,"-",0)))))))))))) -> 0 | Y662: =IF(Z662=Y$1,1,"-") -> - | Z662: Publicly available (1) | AA662: =ifs(U662="","",U662="-",0,U662="Erro",0,U662<>"",LEN(U662)-LEN(SUBSTITUTE(U662,CHAR(10),""))+1) -> 1 | AB662: =COUNTIFS(Links!B:B,"ICSE",Links!C:C,A662,Links!AD:AD,1) -> 0 | AC662: Yes | AD662: =ifs(AE662="None.","No",AE662="-","No",AND(AE662<>"None.",AE662<>"-"),"Yes") -> No | AE662: - | AF662: ---- | AG662: ---- | AH662: ---- | AI662: =IF(AH662="----",IF(AG662="----",IF(AF662="----","----",AF662),AF662&CHAR(10)&AG662),AF662&CHAR(10)&AG662&CHAR(10)&AH662) -> ---- | AJ662: =IFERROR( if(and(K662="Yes",AD662="No"),"Paper has link but no statement", if(and(K662="No",AD662="No"),"Paper has no link and no statement", if(and(K662="Yes",AD662="Yes"),"Paper has link and statement", if(and(K662="No",AD662="Yes"),"Paper has no link but has statement","")))),"") -> Paper has link but no statement | AK662: 45027 | AL662: Technical | AM662: ="[IP"&TEXT(A662,"0000")&"]" -> [IP0790]
A663: 791 | B663: Mitigating Turnover with Code Review Recommendation: Balancing Expertise, Workload, and Knowledge Distribution | C663: 2020 | D663: Yes | E663: Yes | F663: No | G663: No | H663: No | I663: No | J663: - | K663: Yes | L663: No | M663: Yes | N663: Yes | O663: No | P663: Yes | Q663: No | R663: Yes | S663: [28] 5 THE SOFIA BOT ON GITHUB [29] - 1 INTRODUCTION - 3 PROJECT SELECTION AND DATA (4x) * - 6 THREATS TO VALIDITY --- HL Replication and Reproducability - 7 DISCUSSION AND LITERATURE * [30] - 1 INTRODUCTION - 5 THE SOFIA BOT ON GITHUB | T663: https://github.com/cesel/relationalgit https://github.com/cesel/Sofia https://github.com/apps/sofiarec | U663: https://github.com/cesel/relationalgit https://github.com/cesel/Sofia https://github.com/apps/sofiarec | V663: =IF(lenb(SUBSTITUTE($Z663,V$1&" (1)",""))<lenb($Z663),1,IF(lenb(SUBSTITUTE($Z663,V$1&" (2)",""))<lenb($Z663),2,IF(lenb(SUBSTITUTE($Z663,V$1&" (3)",""))<lenb($Z663),3,IF(lenb(SUBSTITUTE($Z663,V$1&" (4)",""))<lenb($Z663),4,IF(lenb(SUBSTITUTE($Z663,V$1&" (5)",""))<lenb($Z663),5,IF(lenb(SUBSTITUTE($Z663,V$1&" (6)",""))<lenb($Z663),6,IF(lenb(SUBSTITUTE($Z663,V$1&" (7)",""))<lenb($Z663),1,IF(lenb(SUBSTITUTE($Z663,V$1&" (8)",""))<lenb($Z663),8,IF(lenb(SUBSTITUTE($Z663,V$1&" (9)",""))<lenb($Z663),9,IF(lenb(SUBSTITUTE($Z663,V$1&" (10)",""))<lenb($Z663),10,IF(lenb(SUBSTITUTE($Z663,V$1,""))<lenb($Z663),"ERROR",IF($Z663=$Y$1,"-",0)))))))))))) -> 3 | W663: =IF(lenb(SUBSTITUTE($Z663,W$1&" (1)",""))<lenb($Z663),1,IF(lenb(SUBSTITUTE($Z663,W$1&" (2)",""))<lenb($Z663),2,IF(lenb(SUBSTITUTE($Z663,W$1&" (3)",""))<lenb($Z663),3,IF(lenb(SUBSTITUTE($Z663,W$1&" (4)",""))<lenb($Z663),4,IF(lenb(SUBSTITUTE($Z663,W$1&" (5)",""))<lenb($Z663),5,IF(lenb(SUBSTITUTE($Z663,W$1&" (6)",""))<lenb($Z663),6,IF(lenb(SUBSTITUTE($Z663,W$1&" (7)",""))<lenb($Z663),1,IF(lenb(SUBSTITUTE($Z663,W$1&" (8)",""))<lenb($Z663),8,IF(lenb(SUBSTITUTE($Z663,W$1&" (9)",""))<lenb($Z663),9,IF(lenb(SUBSTITUTE($Z663,W$1&" (10)",""))<lenb($Z663),10,IF(lenb(SUBSTITUTE($Z663,W$1,""))<lenb($Z663),"ERROR",IF($Z663=$Y$1,"-",0)))))))))))) -> 0 | X663: =IF(lenb(SUBSTITUTE($Z663,X$1&" (1)",""))<lenb($Z663),1,IF(lenb(SUBSTITUTE($Z663,X$1&" (2)",""))<lenb($Z663),2,IF(lenb(SUBSTITUTE($Z663,X$1&" (3)",""))<lenb($Z663),3,IF(lenb(SUBSTITUTE($Z663,X$1&" (4)",""))<lenb($Z663),4,IF(lenb(SUBSTITUTE($Z663,X$1&" (5)",""))<lenb($Z663),5,IF(lenb(SUBSTITUTE($Z663,X$1&" (6)",""))<lenb($Z663),6,IF(lenb(SUBSTITUTE($Z663,X$1&" (7)",""))<lenb($Z663),1,IF(lenb(SUBSTITUTE($Z663,X$1&" (8)",""))<lenb($Z663),8,IF(lenb(SUBSTITUTE($Z663,X$1&" (9)",""))<lenb($Z663),9,IF(lenb(SUBSTITUTE($Z663,X$1&" (10)",""))<lenb($Z663),10,IF(lenb(SUBSTITUTE($Z663,X$1,""))<lenb($Z663),"ERROR",IF($Z663=$Y$1,"-",0)))))))))))) -> 0 | Y663: =IF(Z663=Y$1,1,"-") -> - | Z663: Publicly available (3) | AA663: =ifs(U663="","",U663="-",0,U663="Erro",0,U663<>"",LEN(U663)-LEN(SUBSTITUTE(U663,CHAR(10),""))+1) -> 3 | AB663: =COUNTIFS(Links!B:B,"ICSE",Links!C:C,A663,Links!AD:AD,1) -> 0 | AC663: No | AD663: =ifs(AE663="None.","No",AE663="-","No",AND(AE663<>"None.",AE663<>"-"),"Yes") -> No | AE663: - | AF663: ---- | AG663: ---- | AH663: ---- | AI663: =IF(AH663="----",IF(AG663="----",IF(AF663="----","----",AF663),AF663&CHAR(10)&AG663),AF663&CHAR(10)&AG663&CHAR(10)&AH663) -> ---- | AJ663: =IFERROR( if(and(K663="Yes",AD663="No"),"Paper has link but no statement", if(and(K663="No",AD663="No"),"Paper has no link and no statement", if(and(K663="Yes",AD663="Yes"),"Paper has link and statement", if(and(K663="No",AD663="Yes"),"Paper has no link but has statement","")))),"") -> Paper has link but no statement | AK663: 45027 | AL663: Technical | AM663: ="[IP"&TEXT(A663,"0000")&"]" -> [IP0791]
A664: 792 | B664: How Do Companies Collaborate in Open Source Ecosystems? An Empirical Study of OpenStack | C664: 2020 | D664: No | E664: - | F664: - | G664: - | H664: - | I664: - | J664: - | K664: Yes | L664: No | M664: Yes | N664: No | O664: No | P664: No | Q664: No | R664: Yes | S664: [94] - 3 STUDY DESIGN * - 4 RESULTS * - 5 DISCUSSION * | T664: https://github.com/yuxia-zhang/ICSE2020-Company-Collaboration-in-OSS | U664: https://github.com/yuxia-zhang/ICSE2020-Company-Collaboration-in-OSS | V664: =IF(lenb(SUBSTITUTE($Z664,V$1&" (1)",""))<lenb($Z664),1,IF(lenb(SUBSTITUTE($Z664,V$1&" (2)",""))<lenb($Z664),2,IF(lenb(SUBSTITUTE($Z664,V$1&" (3)",""))<lenb($Z664),3,IF(lenb(SUBSTITUTE($Z664,V$1&" (4)",""))<lenb($Z664),4,IF(lenb(SUBSTITUTE($Z664,V$1&" (5)",""))<lenb($Z664),5,IF(lenb(SUBSTITUTE($Z664,V$1&" (6)",""))<lenb($Z664),6,IF(lenb(SUBSTITUTE($Z664,V$1&" (7)",""))<lenb($Z664),1,IF(lenb(SUBSTITUTE($Z664,V$1&" (8)",""))<lenb($Z664),8,IF(lenb(SUBSTITUTE($Z664,V$1&" (9)",""))<lenb($Z664),9,IF(lenb(SUBSTITUTE($Z664,V$1&" (10)",""))<lenb($Z664),10,IF(lenb(SUBSTITUTE($Z664,V$1,""))<lenb($Z664),"ERROR",IF($Z664=$Y$1,"-",0)))))))))))) -> 1 | W664: =IF(lenb(SUBSTITUTE($Z664,W$1&" (1)",""))<lenb($Z664),1,IF(lenb(SUBSTITUTE($Z664,W$1&" (2)",""))<lenb($Z664),2,IF(lenb(SUBSTITUTE($Z664,W$1&" (3)",""))<lenb($Z664),3,IF(lenb(SUBSTITUTE($Z664,W$1&" (4)",""))<lenb($Z664),4,IF(lenb(SUBSTITUTE($Z664,W$1&" (5)",""))<lenb($Z664),5,IF(lenb(SUBSTITUTE($Z664,W$1&" (6)",""))<lenb($Z664),6,IF(lenb(SUBSTITUTE($Z664,W$1&" (7)",""))<lenb($Z664),1,IF(lenb(SUBSTITUTE($Z664,W$1&" (8)",""))<lenb($Z664),8,IF(lenb(SUBSTITUTE($Z664,W$1&" (9)",""))<lenb($Z664),9,IF(lenb(SUBSTITUTE($Z664,W$1&" (10)",""))<lenb($Z664),10,IF(lenb(SUBSTITUTE($Z664,W$1,""))<lenb($Z664),"ERROR",IF($Z664=$Y$1,"-",0)))))))))))) -> 0 | X664: =IF(lenb(SUBSTITUTE($Z664,X$1&" (1)",""))<lenb($Z664),1,IF(lenb(SUBSTITUTE($Z664,X$1&" (2)",""))<lenb($Z664),2,IF(lenb(SUBSTITUTE($Z664,X$1&" (3)",""))<lenb($Z664),3,IF(lenb(SUBSTITUTE($Z664,X$1&" (4)",""))<lenb($Z664),4,IF(lenb(SUBSTITUTE($Z664,X$1&" (5)",""))<lenb($Z664),5,IF(lenb(SUBSTITUTE($Z664,X$1&" (6)",""))<lenb($Z664),6,IF(lenb(SUBSTITUTE($Z664,X$1&" (7)",""))<lenb($Z664),1,IF(lenb(SUBSTITUTE($Z664,X$1&" (8)",""))<lenb($Z664),8,IF(lenb(SUBSTITUTE($Z664,X$1&" (9)",""))<lenb($Z664),9,IF(lenb(SUBSTITUTE($Z664,X$1&" (10)",""))<lenb($Z664),10,IF(lenb(SUBSTITUTE($Z664,X$1,""))<lenb($Z664),"ERROR",IF($Z664=$Y$1,"-",0)))))))))))) -> 0 | Y664: =IF(Z664=Y$1,1,"-") -> - | Z664: Publicly available (1) | AA664: =ifs(U664="","",U664="-",0,U664="Erro",0,U664<>"",LEN(U664)-LEN(SUBSTITUTE(U664,CHAR(10),""))+1) -> 1 | AB664: =COUNTIFS(Links!B:B,"ICSE",Links!C:C,A664,Links!AD:AD,1) -> 0 | AC664: No | AD664: =ifs(AE664="None.","No",AE664="-","No",AND(AE664<>"None.",AE664<>"-"),"Yes") -> No | AE664: - | AF664: ---- | AG664: ---- | AH664: ---- | AI664: =IF(AH664="----",IF(AG664="----",IF(AF664="----","----",AF664),AF664&CHAR(10)&AG664),AF664&CHAR(10)&AG664&CHAR(10)&AH664) -> ---- | AJ664: =IFERROR( if(and(K664="Yes",AD664="No"),"Paper has link but no statement", if(and(K664="No",AD664="No"),"Paper has no link and no statement", if(and(K664="Yes",AD664="Yes"),"Paper has link and statement", if(and(K664="No",AD664="Yes"),"Paper has no link but has statement","")))),"") -> Paper has link but no statement | AK664: 45027 | AL664: Technical | AM664: ="[IP"&TEXT(A664,"0000")&"]" -> [IP0792]
A665: 793 | B665: How to Not Get Rich: An Empirical Study of Donations in Op€n $our¢e | C665: 2020 | D665: Yes | E665: No | F665: No | G665: Yes | H665: No | I665: No | J665: - | K665: Yes | L665: No | M665: No | N665: No | O665: No | P665: No | Q665: Yes | R665: No | S665: SUPPLEMENTARY MATERIAL AND REPLICATION PACKAGE | T665: https://github.com/CMUSTRUDEL/oss-donations | U665: https://github.com/CMUSTRUDEL/oss-donations | V665: =IF(lenb(SUBSTITUTE($Z665,V$1&" (1)",""))<lenb($Z665),1,IF(lenb(SUBSTITUTE($Z665,V$1&" (2)",""))<lenb($Z665),2,IF(lenb(SUBSTITUTE($Z665,V$1&" (3)",""))<lenb($Z665),3,IF(lenb(SUBSTITUTE($Z665,V$1&" (4)",""))<lenb($Z665),4,IF(lenb(SUBSTITUTE($Z665,V$1&" (5)",""))<lenb($Z665),5,IF(lenb(SUBSTITUTE($Z665,V$1&" (6)",""))<lenb($Z665),6,IF(lenb(SUBSTITUTE($Z665,V$1&" (7)",""))<lenb($Z665),1,IF(lenb(SUBSTITUTE($Z665,V$1&" (8)",""))<lenb($Z665),8,IF(lenb(SUBSTITUTE($Z665,V$1&" (9)",""))<lenb($Z665),9,IF(lenb(SUBSTITUTE($Z665,V$1&" (10)",""))<lenb($Z665),10,IF(lenb(SUBSTITUTE($Z665,V$1,""))<lenb($Z665),"ERROR",IF($Z665=$Y$1,"-",0)))))))))))) -> 1 | W665: =IF(lenb(SUBSTITUTE($Z665,W$1&" (1)",""))<lenb($Z665),1,IF(lenb(SUBSTITUTE($Z665,W$1&" (2)",""))<lenb($Z665),2,IF(lenb(SUBSTITUTE($Z665,W$1&" (3)",""))<lenb($Z665),3,IF(lenb(SUBSTITUTE($Z665,W$1&" (4)",""))<lenb($Z665),4,IF(lenb(SUBSTITUTE($Z665,W$1&" (5)",""))<lenb($Z665),5,IF(lenb(SUBSTITUTE($Z665,W$1&" (6)",""))<lenb($Z665),6,IF(lenb(SUBSTITUTE($Z665,W$1&" (7)",""))<lenb($Z665),1,IF(lenb(SUBSTITUTE($Z665,W$1&" (8)",""))<lenb($Z665),8,IF(lenb(SUBSTITUTE($Z665,W$1&" (9)",""))<lenb($Z665),9,IF(lenb(SUBSTITUTE($Z665,W$1&" (10)",""))<lenb($Z665),10,IF(lenb(SUBSTITUTE($Z665,W$1,""))<lenb($Z665),"ERROR",IF($Z665=$Y$1,"-",0)))))))))))) -> 0 | X665: =IF(lenb(SUBSTITUTE($Z665,X$1&" (1)",""))<lenb($Z665),1,IF(lenb(SUBSTITUTE($Z665,X$1&" (2)",""))<lenb($Z665),2,IF(lenb(SUBSTITUTE($Z665,X$1&" (3)",""))<lenb($Z665),3,IF(lenb(SUBSTITUTE($Z665,X$1&" (4)",""))<lenb($Z665),4,IF(lenb(SUBSTITUTE($Z665,X$1&" (5)",""))<lenb($Z665),5,IF(lenb(SUBSTITUTE($Z665,X$1&" (6)",""))<lenb($Z665),6,IF(lenb(SUBSTITUTE($Z665,X$1&" (7)",""))<lenb($Z665),1,IF(lenb(SUBSTITUTE($Z665,X$1&" (8)",""))<lenb($Z665),8,IF(lenb(SUBSTITUTE($Z665,X$1&" (9)",""))<lenb($Z665),9,IF(lenb(SUBSTITUTE($Z665,X$1&" (10)",""))<lenb($Z665),10,IF(lenb(SUBSTITUTE($Z665,X$1,""))<lenb($Z665),"ERROR",IF($Z665=$Y$1,"-",0)))))))))))) -> 0 | Y665: =IF(Z665=Y$1,1,"-") -> - | Z665: Publicly available (1) | AA665: =ifs(U665="","",U665="-",0,U665="Erro",0,U665<>"",LEN(U665)-LEN(SUBSTITUTE(U665,CHAR(10),""))+1) -> 1 | AB665: =COUNTIFS(Links!B:B,"ICSE",Links!C:C,A665,Links!AD:AD,1) -> 0 | AC665: No | AD665: =ifs(AE665="None.","No",AE665="-","No",AND(AE665<>"None.",AE665<>"-"),"Yes") -> No | AE665: - | AF665: ---- | AG665: ---- | AH665: ---- | AI665: =IF(AH665="----",IF(AG665="----",IF(AF665="----","----",AF665),AF665&CHAR(10)&AG665),AF665&CHAR(10)&AG665&CHAR(10)&AH665) -> ---- | AJ665: =IFERROR( if(and(K665="Yes",AD665="No"),"Paper has link but no statement", if(and(K665="No",AD665="No"),"Paper has no link and no statement", if(and(K665="Yes",AD665="Yes"),"Paper has link and statement", if(and(K665="No",AD665="Yes"),"Paper has no link but has statement","")))),"") -> Paper has link but no statement | AK665: 45027 | AL665: Technical | AM665: ="[IP"&TEXT(A665,"0000")&"]" -> [IP0793]
... A1237: 2231 | B1237: An Empirical Study on Software Bill of Materials: Where We Stand and the Road Ahead | C1237: 2023 | D1237: No | E1237: - | F1237: - | G1237: - | H1237: - | I1237: - | J1237: - | K1237: Yes | L1237: Yes | M1237: No | N1237: No | O1237: No | P1237: No | Q1237: No | R1237: Yes | S1237: FN 1 - III. RESEARCH METHODOLOGY | T1237: https://drive.google.com/drive/folders/1gylBoeF09sJRg2xEpJh2tWnjp0cCMhxM?usp=sharing | U1237: https://drive.google.com/drive/folders/1gylBoeF09sJRg2xEpJh2tWnjp0cCMhxM?usp=sharing | V1237: =IF(lenb(SUBSTITUTE($Z1237,V$1&" (1)",""))<lenb($Z1237),1,IF(lenb(SUBSTITUTE($Z1237,V$1&" (2)",""))<lenb($Z1237),2,IF(lenb(SUBSTITUTE($Z1237,V$1&" (3)",""))<lenb($Z1237),3,IF(lenb(SUBSTITUTE($Z1237,V$1&" (4)",""))<lenb($Z1237),4,IF(lenb(SUBSTITUTE($Z1237,V$1&" (5)",""))<lenb($Z1237),5,IF(lenb(SUBSTITUTE($Z1237,V$1&" (6)",""))<lenb($Z1237),6,IF(lenb(SUBSTITUTE($Z1237,V$1&" (7)",""))<lenb($Z1237),1,IF(lenb(SUBSTITUTE($Z1237,V$1&" (8)",""))<lenb($Z1237),8,IF(lenb(SUBSTITUTE($Z1237,V$1&" (9)",""))<lenb($Z1237),9,IF(lenb(SUBSTITUTE($Z1237,V$1&" (10)",""))<lenb($Z1237),10,IF(lenb(SUBSTITUTE($Z1237,V$1,""))<lenb($Z1237),"ERROR",IF($Z1237=$Y$1,"-",0)))))))))))) -> 1 | W1237: =IF(lenb(SUBSTITUTE($Z1237,W$1&" (1)",""))<lenb($Z1237),1,IF(lenb(SUBSTITUTE($Z1237,W$1&" (2)",""))<lenb($Z1237),2,IF(lenb(SUBSTITUTE($Z1237,W$1&" (3)",""))<lenb($Z1237),3,IF(lenb(SUBSTITUTE($Z1237,W$1&" (4)",""))<lenb($Z1237),4,IF(lenb(SUBSTITUTE($Z1237,W$1&" (5)",""))<lenb($Z1237),5,IF(lenb(SUBSTITUTE($Z1237,W$1&" (6)",""))<lenb($Z1237),6,IF(lenb(SUBSTITUTE($Z1237,W$1&" (7)",""))<lenb($Z1237),1,IF(lenb(SUBSTITUTE($Z1237,W$1&" (8)",""))<lenb($Z1237),8,IF(lenb(SUBSTITUTE($Z1237,W$1&" (9)",""))<lenb($Z1237),9,IF(lenb(SUBSTITUTE($Z1237,W$1&" (10)",""))<lenb($Z1237),10,IF(lenb(SUBSTITUTE($Z1237,W$1,""))<lenb($Z1237),"ERROR",IF($Z1237=$Y$1,"-",0)))))))))))) -> 0 | X1237: =IF(lenb(SUBSTITUTE($Z1237,X$1&" (1)",""))<lenb($Z1237),1,IF(lenb(SUBSTITUTE($Z1237,X$1&" (2)",""))<lenb($Z1237),2,IF(lenb(SUBSTITUTE($Z1237,X$1&" (3)",""))<lenb($Z1237),3,IF(lenb(SUBSTITUTE($Z1237,X$1&" (4)",""))<lenb($Z1237),4,IF(lenb(SUBSTITUTE($Z1237,X$1&" (5)",""))<lenb($Z1237),5,IF(lenb(SUBSTITUTE($Z1237,X$1&" (6)",""))<lenb($Z1237),6,IF(lenb(SUBSTITUTE($Z1237,X$1&" (7)",""))<lenb($Z1237),1,IF(lenb(SUBSTITUTE($Z1237,X$1&" (8)",""))<lenb($Z1237),8,IF(lenb(SUBSTITUTE($Z1237,X$1&" (9)",""))<lenb($Z1237),9,IF(lenb(SUBSTITUTE($Z1237,X$1&" (10)",""))<lenb($Z1237),10,IF(lenb(SUBSTITUTE($Z1237,X$1,""))<lenb($Z1237),"ERROR",IF($Z1237=$Y$1,"-",0)))))))))))) -> 0 | Y1237: =IF(Z1237=Y$1,1,"-") -> - | Z1237: Publicly available (1) | AA1237: =ifs(U1237="","",U1237="-",0,U1237="Erro",0,U1237<>"",LEN(U1237)-LEN(SUBSTITUTE(U1237,CHAR(10),""))+1) -> 1 | AB1237: =COUNTIFS(Links!B:B,"ICSE",Links!C:C,A1237,Links!AD:AD,1) -> 0 | AC1237: No | AD1237: =ifs(AE1237="None.","No",AE1237="-","No",AND(AE1237<>"None.",AE1237<>"-"),"Yes") -> No | AE1237: - | AF1237: ---- | AG1237: ---- | AH1237: ---- | AI1237: =IF(AH1237="----",IF(AG1237="----",IF(AF1237="----","----",AF1237),AF1237&CHAR(10)&AG1237),AF1237&CHAR(10)&AG1237&CHAR(10)&AH1237) -> ---- | AJ1237: =IFERROR( if(and(K1237="Yes",AD1237="No"),"Paper has link but no statement", if(and(K1237="No",AD1237="No"),"Paper has no link and no statement", if(and(K1237="Yes",AD1237="Yes"),"Paper has link and statement", if(and(K1237="No",AD1237="Yes"),"Paper has no link but has statement","")))),"") -> Paper has link but no statement | AK1237: 45070 | AL1237: Technical | AM1237: ="[IP"&TEXT(A1237,"0000")&"]" -> [IP2231]

Sheet FSE
A1: Paper ID | B1: Paper Title | C1: Year | D1: Successfully passed AE | E1: Artifacts Available badge | F1: Functional - Artifacts Evaluated badge | G1: Reusable - Artifacts Evaluated badge | H1: Results Replicated - Results Validated badge | I1: Results Reproduced - Results Validated badge | J1: Other badge | K1: Artifact link | L1: Footnote | M1: References | N1: Introduction | O1: Conclusion | P1: Highlight | Q1: Specific section or subsection | R1: Other Place | S1: Where is talking about the link? | T1: Artifact link(s) | U1: ="All artifact links whitout repetition - column "&SUBSTITUTE(ADDRESS(ROW(T1),COLUMN(T1),4),1,"")&" for artifact sharing (without real link)" -> All artifact links whitout repetition - column T for artifact sharing (without real link) | V1: Publicly Available | W1: Not Available | X1: Restrict Access | Y1: No links | Z1: ="Status of the links in 09/18/2024 - "&SUBSTITUTE(ADDRESS(ROW(T1),COLUMN(T1),4),1,"") -> Status of the links in 09/18/2024 - T | AA1: # of different links | AB1: University domain | AC1: unique identifier | AD1: Is there a statement? | AE1: Statements for non-disclosure or partial disclosure of the research artifacts | AF1: Statements 1 | AG1: Statements 2 | AH1: Statements 3 | AI1: ="All statement labels "&SUBSTITUTE(ADDRESS(ROW(AF1),COLUMN(AF1),4),1,"")&" + "&SUBSTITUTE(ADDRESS(ROW(AG1),COLUMN(AG1),4),1,"")&" + "&SUBSTITUTE(ADDRESS(ROW(AH1),COLUMN(AH1),4),1,"") -> All statement labels AF + AG + AH | AJ1: ="Link and statement analysis "&SUBSTITUTE(ADDRESS(ROW(K1),COLUMN(K1),4),1,"")&" and "&SUBSTITUTE(ADDRESS(ROW(AD1),COLUMN(AD1),4),1,"") -> Link and statement analysis K and AD | AK1: Paper download | AL1: Track | AM1: Paper ID
A2: 780 | B2: Developers' code context models for change tasks | C2: 2014 | D2: No | E2: - | F2: - | G2: - | H2: - | I2: - | J2: - | K2: Yes | L2: No | M2: Yes | N2: No | O2: No | P2: No | Q2: No | R2: Yes | S2: 2.4 Data Collection and Analysis | T2: https://github.com/abb-iss/study-artifacts-for-code-context-models | U2: https://github.com/abb-iss/study-artifacts-for-code-context-models | V2: =IF(lenb(SUBSTITUTE($Z2,V$1&" (1)",""))<lenb($Z2),1, IF(lenb(SUBSTITUTE($Z2,V$1&" (2)",""))<lenb($Z2),2, IF(lenb(SUBSTITUTE($Z2,V$1&" (3)",""))<lenb($Z2),3, IF(lenb(SUBSTITUTE($Z2,V$1&" (4)",""))<lenb($Z2),4, IF(lenb(SUBSTITUTE($Z2,V$1&" (5)",""))<lenb($Z2),5, IF(lenb(SUBSTITUTE($Z2,V$1&" (6)",""))<lenb($Z2),6, IF(lenb(SUBSTITUTE($Z2,V$1&" (7)",""))<lenb($Z2),1, IF(lenb(SUBSTITUTE($Z2,V$1&" (8)",""))<lenb($Z2),8, IF(lenb(SUBSTITUTE($Z2,V$1&" (9)",""))<lenb($Z2),9, IF(lenb(SUBSTITUTE($Z2,V$1&" (10)",""))<lenb($Z2),10, IF(lenb(SUBSTITUTE($Z2,V$1&" (26)",""))<lenb($Z2),26, IF(lenb(SUBSTITUTE($Z2,V$1,""))<lenb($Z2),"ERROR", IF($Z2=$Y$1,"-",0))))))))))))) -> 1 | W2: =IF(lenb(SUBSTITUTE($Z2,W$1&" (1)",""))<lenb($Z2),1,IF(lenb(SUBSTITUTE($Z2,W$1&" (2)",""))<lenb($Z2),2,IF(lenb(SUBSTITUTE($Z2,W$1&" (3)",""))<lenb($Z2),3,IF(lenb(SUBSTITUTE($Z2,W$1&" (4)",""))<lenb($Z2),4,IF(lenb(SUBSTITUTE($Z2,W$1&" (5)",""))<lenb($Z2),5,IF(lenb(SUBSTITUTE($Z2,W$1&" (6)",""))<lenb($Z2),6,IF(lenb(SUBSTITUTE($Z2,W$1&" (7)",""))<lenb($Z2),1,IF(lenb(SUBSTITUTE($Z2,W$1&" (8)",""))<lenb($Z2),8,IF(lenb(SUBSTITUTE($Z2,W$1&" (9)",""))<lenb($Z2),9,IF(lenb(SUBSTITUTE($Z2,W$1&" (10)",""))<lenb($Z2),10,IF(lenb(SUBSTITUTE($Z2,W$1,""))<lenb($Z2),"ERROR",IF($Z2=$Y$1,"-",0)))))))))))) -> 0 | X2: =IF(lenb(SUBSTITUTE($Z2,X$1&" (1)",""))<lenb($Z2),1,IF(lenb(SUBSTITUTE($Z2,X$1&" (2)",""))<lenb($Z2),2,IF(lenb(SUBSTITUTE($Z2,X$1&" (3)",""))<lenb($Z2),3,IF(lenb(SUBSTITUTE($Z2,X$1&" (4)",""))<lenb($Z2),4,IF(lenb(SUBSTITUTE($Z2,X$1&" (5)",""))<lenb($Z2),5,IF(lenb(SUBSTITUTE($Z2,X$1&" (6)",""))<lenb($Z2),6,IF(lenb(SUBSTITUTE($Z2,X$1&" (7)",""))<lenb($Z2),1,IF(lenb(SUBSTITUTE($Z2,X$1&" (8)",""))<lenb($Z2),8,IF(lenb(SUBSTITUTE($Z2,X$1&" (9)",""))<lenb($Z2),9,IF(lenb(SUBSTITUTE($Z2,X$1&" (10)",""))<lenb($Z2),10,IF(lenb(SUBSTITUTE($Z2,X$1,""))<lenb($Z2),"ERROR",IF($Z2=$Y$1,"-",0)))))))))))) -> 0 | Y2: =IF(Z2=Y$1,1,"-") -> - | Z2: Publicly Available (1) | AA2: =ifs(U2="","",U2="-",0,U2="Erro",0,U2<>"",LEN(U2)-LEN(SUBSTITUTE(U2,CHAR(10),""))+1) -> 1 | AB2: =COUNTIFS(Links!B:B,"FSE",Links!C:C,A2,Links!AD:AD,1) -> 0 | AC2: No | AD2: No | AE2: - | AF2: ---- | AG2: ---- | AH2: ---- | AI2: =IF(AH2="----",IF(AG2="----",IF(AF2="----","----",AF2),AF2&CHAR(10)&AG2),AF2&CHAR(10)&AG2&CHAR(10)&AH2) -> ---- | AJ2: =IFERROR( IF(AND(K2="Yes",AD2="No"),"Paper has link but no statement", IF(AND(K2="No",AD2="No"),"Paper has no link and no statement", IF(AND(K2="Yes",AD2="Yes"),"Paper has link and statement", IF(AND(K2="No",AD2="Yes"),"Paper has no link but has statement","")))),"") -> Paper has link but no statement | AK2: 26-29/08/2024 | AL2: Research Papers | AM2: ="[FP"&TEXT(A2,"0000")&"]" -> [FP0780]
A3: 781 | B3: Software developers' perceptions of productivity | C3: 2014 | D3: No | E3: - | F3: - | G3: - | H3: - | I3: - | J3: - | K3: Yes | L3: No | M3: Yes | N3: No | O3: No | P3: No | Q3: No | R3: Yes | S3: 3.1 Participants and Method 4.2 Results 4.1 Participants and Method | T3: www.ifi.uzh.ch/seal/people/meyer/developers-productivity | U3: www.ifi.uzh.ch/seal/people/meyer/developers-productivity | V3: =IF(lenb(SUBSTITUTE($Z3,V$1&" (1)",""))<lenb($Z3),1, IF(lenb(SUBSTITUTE($Z3,V$1&" (2)",""))<lenb($Z3),2, IF(lenb(SUBSTITUTE($Z3,V$1&" (3)",""))<lenb($Z3),3, IF(lenb(SUBSTITUTE($Z3,V$1&" (4)",""))<lenb($Z3),4, IF(lenb(SUBSTITUTE($Z3,V$1&" (5)",""))<lenb($Z3),5, IF(lenb(SUBSTITUTE($Z3,V$1&" (6)",""))<lenb($Z3),6, IF(lenb(SUBSTITUTE($Z3,V$1&" (7)",""))<lenb($Z3),1, IF(lenb(SUBSTITUTE($Z3,V$1&" (8)",""))<lenb($Z3),8, IF(lenb(SUBSTITUTE($Z3,V$1&" (9)",""))<lenb($Z3),9, IF(lenb(SUBSTITUTE($Z3,V$1&" (10)",""))<lenb($Z3),10, IF(lenb(SUBSTITUTE($Z3,V$1&" (26)",""))<lenb($Z3),26, IF(lenb(SUBSTITUTE($Z3,V$1,""))<lenb($Z3),"ERROR", IF($Z3=$Y$1,"-",0))))))))))))) -> 1 | W3: =IF(lenb(SUBSTITUTE($Z3,W$1&" (1)",""))<lenb($Z3),1,IF(lenb(SUBSTITUTE($Z3,W$1&" (2)",""))<lenb($Z3),2,IF(lenb(SUBSTITUTE($Z3,W$1&" (3)",""))<lenb($Z3),3,IF(lenb(SUBSTITUTE($Z3,W$1&" (4)",""))<lenb($Z3),4,IF(lenb(SUBSTITUTE($Z3,W$1&" (5)",""))<lenb($Z3),5,IF(lenb(SUBSTITUTE($Z3,W$1&" (6)",""))<lenb($Z3),6,IF(lenb(SUBSTITUTE($Z3,W$1&" (7)",""))<lenb($Z3),1,IF(lenb(SUBSTITUTE($Z3,W$1&" (8)",""))<lenb($Z3),8,IF(lenb(SUBSTITUTE($Z3,W$1&" (9)",""))<lenb($Z3),9,IF(lenb(SUBSTITUTE($Z3,W$1&" (10)",""))<lenb($Z3),10,IF(lenb(SUBSTITUTE($Z3,W$1,""))<lenb($Z3),"ERROR",IF($Z3=$Y$1,"-",0)))))))))))) -> 0 | X3: =IF(lenb(SUBSTITUTE($Z3,X$1&" (1)",""))<lenb($Z3),1,IF(lenb(SUBSTITUTE($Z3,X$1&" (2)",""))<lenb($Z3),2,IF(lenb(SUBSTITUTE($Z3,X$1&" (3)",""))<lenb($Z3),3,IF(lenb(SUBSTITUTE($Z3,X$1&" (4)",""))<lenb($Z3),4,IF(lenb(SUBSTITUTE($Z3,X$1&" (5)",""))<lenb($Z3),5,IF(lenb(SUBSTITUTE($Z3,X$1&" (6)",""))<lenb($Z3),6,IF(lenb(SUBSTITUTE($Z3,X$1&" (7)",""))<lenb($Z3),1,IF(lenb(SUBSTITUTE($Z3,X$1&" (8)",""))<lenb($Z3),8,IF(lenb(SUBSTITUTE($Z3,X$1&" (9)",""))<lenb($Z3),9,IF(lenb(SUBSTITUTE($Z3,X$1&" (10)",""))<lenb($Z3),10,IF(lenb(SUBSTITUTE($Z3,X$1,""))<lenb($Z3),"ERROR",IF($Z3=$Y$1,"-",0)))))))))))) -> 0 | Y3: =IF(Z3=Y$1,1,"-") -> - | Z3: Publicly Available (1) | AA3: =ifs(U3="","",U3="-",0,U3="Erro",0,U3<>"",LEN(U3)-LEN(SUBSTITUTE(U3,CHAR(10),""))+1) -> 1 | AB3: =COUNTIFS(Links!B:B,"FSE",Links!C:C,A3,Links!AD:AD,1) -> 1 | AC3: No | AD3: Yes | AE3: Due to confidentiality reasons, we are not able to share the observation logs. | AF3: Barriers (Confidentiality and privacy) | AG3: ---- | AH3: ---- | AI3: =IF(AH3="----",IF(AG3="----",IF(AF3="----","----",AF3),AF3&CHAR(10)&AG3),AF3&CHAR(10)&AG3&CHAR(10)&AH3) -> Barriers (Confidentiality and privacy) | AJ3: =IFERROR( IF(AND(K3="Yes",AD3="No"),"Paper has link but no statement", IF(AND(K3="No",AD3="No"),"Paper has no link and no statement", IF(AND(K3="Yes",AD3="Yes"),"Paper has link and statement", IF(AND(K3="No",AD3="Yes"),"Paper has no link but has statement","")))),"") -> Paper has link and statement | AK3: 26-29/08/2024 | AL3: Research Papers | AM3: ="[FP"&TEXT(A3,"0000")&"]" -> [FP0781]
A4: 782 | B4: Enablers, inhibitors, and perceptions of testing in novice software teams | C4: 2014 | D4: No | E4: - | F4: - | G4: - | H4: - | I4: - | J4: - | K4: No | L4: - | M4: - | N4: - | O4: - | P4: - | Q4: - | R4: - | S4: ---- | T4: - | U4: - | V4: =IF(lenb(SUBSTITUTE($Z4,V$1&" (1)",""))<lenb($Z4),1, IF(lenb(SUBSTITUTE($Z4,V$1&" (2)",""))<lenb($Z4),2, IF(lenb(SUBSTITUTE($Z4,V$1&" (3)",""))<lenb($Z4),3, IF(lenb(SUBSTITUTE($Z4,V$1&" (4)",""))<lenb($Z4),4, IF(lenb(SUBSTITUTE($Z4,V$1&" (5)",""))<lenb($Z4),5, IF(lenb(SUBSTITUTE($Z4,V$1&" (6)",""))<lenb($Z4),6, IF(lenb(SUBSTITUTE($Z4,V$1&" (7)",""))<lenb($Z4),1, IF(lenb(SUBSTITUTE($Z4,V$1&" (8)",""))<lenb($Z4),8, IF(lenb(SUBSTITUTE($Z4,V$1&" (9)",""))<lenb($Z4),9, IF(lenb(SUBSTITUTE($Z4,V$1&" (10)",""))<lenb($Z4),10, IF(lenb(SUBSTITUTE($Z4,V$1&" (26)",""))<lenb($Z4),26, IF(lenb(SUBSTITUTE($Z4,V$1,""))<lenb($Z4),"ERROR", IF($Z4=$Y$1,"-",0))))))))))))) -> - | W4: =IF(lenb(SUBSTITUTE($Z4,W$1&" (1)",""))<lenb($Z4),1,IF(lenb(SUBSTITUTE($Z4,W$1&" (2)",""))<lenb($Z4),2,IF(lenb(SUBSTITUTE($Z4,W$1&" (3)",""))<lenb($Z4),3,IF(lenb(SUBSTITUTE($Z4,W$1&" (4)",""))<lenb($Z4),4,IF(lenb(SUBSTITUTE($Z4,W$1&" (5)",""))<lenb($Z4),5,IF(lenb(SUBSTITUTE($Z4,W$1&" (6)",""))<lenb($Z4),6,IF(lenb(SUBSTITUTE($Z4,W$1&" (7)",""))<lenb($Z4),1,IF(lenb(SUBSTITUTE($Z4,W$1&" (8)",""))<lenb($Z4),8,IF(lenb(SUBSTITUTE($Z4,W$1&" (9)",""))<lenb($Z4),9,IF(lenb(SUBSTITUTE($Z4,W$1&" (10)",""))<lenb($Z4),10,IF(lenb(SUBSTITUTE($Z4,W$1,""))<lenb($Z4),"ERROR",IF($Z4=$Y$1,"-",0)))))))))))) -> - | X4: =IF(lenb(SUBSTITUTE($Z4,X$1&" (1)",""))<lenb($Z4),1,IF(lenb(SUBSTITUTE($Z4,X$1&" (2)",""))<lenb($Z4),2,IF(lenb(SUBSTITUTE($Z4,X$1&" (3)",""))<lenb($Z4),3,IF(lenb(SUBSTITUTE($Z4,X$1&" (4)",""))<lenb($Z4),4,IF(lenb(SUBSTITUTE($Z4,X$1&" (5)",""))<lenb($Z4),5,IF(lenb(SUBSTITUTE($Z4,X$1&" (6)",""))<lenb($Z4),6,IF(lenb(SUBSTITUTE($Z4,X$1&" (7)",""))<lenb($Z4),1,IF(lenb(SUBSTITUTE($Z4,X$1&" (8)",""))<lenb($Z4),8,IF(lenb(SUBSTITUTE($Z4,X$1&" (9)",""))<lenb($Z4),9,IF(lenb(SUBSTITUTE($Z4,X$1&" (10)",""))<lenb($Z4),10,IF(lenb(SUBSTITUTE($Z4,X$1,""))<lenb($Z4),"ERROR",IF($Z4=$Y$1,"-",0)))))))))))) -> - | Y4: =IF(Z4=Y$1,1,"-") -> 1 | Z4: No links | AA4: =ifs(U4="","",U4="-",0,U4="Erro",0,U4<>"",LEN(U4)-LEN(SUBSTITUTE(U4,CHAR(10),""))+1) -> 0 | AB4: =COUNTIFS(Links!B:B,"FSE",Links!C:C,A4,Links!AD:AD,1) -> 0 | AC4: - | AD4: No | AE4: - | AF4: ---- | AG4: ---- | AH4: ---- | AI4: =IF(AH4="----",IF(AG4="----",IF(AF4="----","----",AF4),AF4&CHAR(10)&AG4),AF4&CHAR(10)&AG4&CHAR(10)&AH4) -> ---- | AJ4: =IFERROR( IF(AND(K4="Yes",AD4="No"),"Paper has link but no statement", IF(AND(K4="No",AD4="No"),"Paper has no link and no statement", IF(AND(K4="Yes",AD4="Yes"),"Paper has link and statement", IF(AND(K4="No",AD4="Yes"),"Paper has no link but has statement","")))),"") -> Paper has no link and no statement | AK4: 26-29/08/2024 | AL4: Research Papers | AM4: ="[FP"&TEXT(A4,"0000")&"]" -> [FP0782]
A5: 783 | B5: Feedback generation for performance problems in introductory programming assignments | C5: 2014 | D5: Yes | E5: - | F5: - | G5: - | H5: - | I5: - | J5: Source: Winter et al. (2022) and email from the chair. | K5: Yes | L5: No | M5: Yes | N5: No | O5: No | P5: No | Q5: No | R5: Yes | S5: 6.1 Experimental Setup | T5: http://pexforfun.com/makingprogramsefficient http://forsyte.at/static/people/radicek/fse14 CoRR, abs/1403.4064 - real link: https://arxiv.org/abs/1403.4064 | U5: http://pexforfun.com/makingprogramsefficient http://forsyte.at/static/people/radicek/fse14 CoRR, abs/1403.4064 - real link: https://arxiv.org/abs/1403.4064 | V5: =IF(lenb(SUBSTITUTE($Z5,V$1&" (1)",""))<lenb($Z5),1, IF(lenb(SUBSTITUTE($Z5,V$1&" (2)",""))<lenb($Z5),2, IF(lenb(SUBSTITUTE($Z5,V$1&" (3)",""))<lenb($Z5),3, IF(lenb(SUBSTITUTE($Z5,V$1&" (4)",""))<lenb($Z5),4, IF(lenb(SUBSTITUTE($Z5,V$1&" (5)",""))<lenb($Z5),5, IF(lenb(SUBSTITUTE($Z5,V$1&" (6)",""))<lenb($Z5),6, IF(lenb(SUBSTITUTE($Z5,V$1&" (7)",""))<lenb($Z5),1, IF(lenb(SUBSTITUTE($Z5,V$1&" (8)",""))<lenb($Z5),8, IF(lenb(SUBSTITUTE($Z5,V$1&" (9)",""))<lenb($Z5),9, IF(lenb(SUBSTITUTE($Z5,V$1&" (10)",""))<lenb($Z5),10, IF(lenb(SUBSTITUTE($Z5,V$1&" (26)",""))<lenb($Z5),26, IF(lenb(SUBSTITUTE($Z5,V$1,""))<lenb($Z5),"ERROR", IF($Z5=$Y$1,"-",0))))))))))))) -> 2 | W5: =IF(lenb(SUBSTITUTE($Z5,W$1&" (1)",""))<lenb($Z5),1,IF(lenb(SUBSTITUTE($Z5,W$1&" (2)",""))<lenb($Z5),2,IF(lenb(SUBSTITUTE($Z5,W$1&" (3)",""))<lenb($Z5),3,IF(lenb(SUBSTITUTE($Z5,W$1&" (4)",""))<lenb($Z5),4,IF(lenb(SUBSTITUTE($Z5,W$1&" (5)",""))<lenb($Z5),5,IF(lenb(SUBSTITUTE($Z5,W$1&" (6)",""))<lenb($Z5),6,IF(lenb(SUBSTITUTE($Z5,W$1&" (7)",""))<lenb($Z5),1,IF(lenb(SUBSTITUTE($Z5,W$1&" (8)",""))<lenb($Z5),8,IF(lenb(SUBSTITUTE($Z5,W$1&" (9)",""))<lenb($Z5),9,IF(lenb(SUBSTITUTE($Z5,W$1&" (10)",""))<lenb($Z5),10,IF(lenb(SUBSTITUTE($Z5,W$1,""))<lenb($Z5),"ERROR",IF($Z5=$Y$1,"-",0)))))))))))) -> 1 | X5: =IF(lenb(SUBSTITUTE($Z5,X$1&" (1)",""))<lenb($Z5),1,IF(lenb(SUBSTITUTE($Z5,X$1&" (2)",""))<lenb($Z5),2,IF(lenb(SUBSTITUTE($Z5,X$1&" (3)",""))<lenb($Z5),3,IF(lenb(SUBSTITUTE($Z5,X$1&" (4)",""))<lenb($Z5),4,IF(lenb(SUBSTITUTE($Z5,X$1&" (5)",""))<lenb($Z5),5,IF(lenb(SUBSTITUTE($Z5,X$1&" (6)",""))<lenb($Z5),6,IF(lenb(SUBSTITUTE($Z5,X$1&" (7)",""))<lenb($Z5),1,IF(lenb(SUBSTITUTE($Z5,X$1&" (8)",""))<lenb($Z5),8,IF(lenb(SUBSTITUTE($Z5,X$1&" (9)",""))<lenb($Z5),9,IF(lenb(SUBSTITUTE($Z5,X$1&" (10)",""))<lenb($Z5),10,IF(lenb(SUBSTITUTE($Z5,X$1,""))<lenb($Z5),"ERROR",IF($Z5=$Y$1,"-",0)))))))))))) -> 0 | Y5: =IF(Z5=Y$1,1,"-") -> - | Z5: Not Available (1) Publicly Available (2) | AA5: =ifs(U5="","",U5="-",0,U5="Erro",0,U5<>"",LEN(U5)-LEN(SUBSTITUTE(U5,CHAR(10),""))+1) -> 3 | AB5: =COUNTIFS(Links!B:B,"FSE",Links!C:C,A5,Links!AD:AD,1) -> 1 | AC5: Yes | AD5: No | AE5: - | AF5: ---- | AG5: ---- | AH5: ---- | AI5: =IF(AH5="----",IF(AG5="----",IF(AF5="----","----",AF5),AF5&CHAR(10)&AG5),AF5&CHAR(10)&AG5&CHAR(10)&AH5) -> ---- | AJ5: =IFERROR( IF(AND(K5="Yes",AD5="No"),"Paper has link but no statement", IF(AND(K5="No",AD5="No"),"Paper has no link and no statement", IF(AND(K5="Yes",AD5="Yes"),"Paper has link and statement", IF(AND(K5="No",AD5="Yes"),"Paper has no link but has statement","")))),"") -> Paper has link but no statement | AK5: 26-29/08/2024 | AL5: Research Papers | AM5: ="[FP"&TEXT(A5,"0000")&"]" -> [FP0783]
A6: 784 | B6: Test case purification for improving fault localization | C6: 2014 | D6: Yes | E6: - | F6: - | G6: - | H6: - | I6: - | J6: Source: Winter et al. (2022) and email from the chair. | K6: No | L6: - | M6: - | N6: - | O6: - | P6: - | Q6: - | R6: - | S6: ---- | T6: - | U6: - | V6: =IF(lenb(SUBSTITUTE($Z6,V$1&" (1)",""))<lenb($Z6),1, IF(lenb(SUBSTITUTE($Z6,V$1&" (2)",""))<lenb($Z6),2, IF(lenb(SUBSTITUTE($Z6,V$1&" (3)",""))<lenb($Z6),3, IF(lenb(SUBSTITUTE($Z6,V$1&" (4)",""))<lenb($Z6),4, IF(lenb(SUBSTITUTE($Z6,V$1&" (5)",""))<lenb($Z6),5, IF(lenb(SUBSTITUTE($Z6,V$1&" (6)",""))<lenb($Z6),6, IF(lenb(SUBSTITUTE($Z6,V$1&" (7)",""))<lenb($Z6),1, IF(lenb(SUBSTITUTE($Z6,V$1&" (8)",""))<lenb($Z6),8, IF(lenb(SUBSTITUTE($Z6,V$1&" (9)",""))<lenb($Z6),9, IF(lenb(SUBSTITUTE($Z6,V$1&" (10)",""))<lenb($Z6),10, IF(lenb(SUBSTITUTE($Z6,V$1&" (26)",""))<lenb($Z6),26, IF(lenb(SUBSTITUTE($Z6,V$1,""))<lenb($Z6),"ERROR", IF($Z6=$Y$1,"-",0))))))))))))) -> - | W6: =IF(lenb(SUBSTITUTE($Z6,W$1&" (1)",""))<lenb($Z6),1,IF(lenb(SUBSTITUTE($Z6,W$1&" (2)",""))<lenb($Z6),2,IF(lenb(SUBSTITUTE($Z6,W$1&" (3)",""))<lenb($Z6),3,IF(lenb(SUBSTITUTE($Z6,W$1&" (4)",""))<lenb($Z6),4,IF(lenb(SUBSTITUTE($Z6,W$1&" (5)",""))<lenb($Z6),5,IF(lenb(SUBSTITUTE($Z6,W$1&" (6)",""))<lenb($Z6),6,IF(lenb(SUBSTITUTE($Z6,W$1&" (7)",""))<lenb($Z6),1,IF(lenb(SUBSTITUTE($Z6,W$1&" (8)",""))<lenb($Z6),8,IF(lenb(SUBSTITUTE($Z6,W$1&" (9)",""))<lenb($Z6),9,IF(lenb(SUBSTITUTE($Z6,W$1&" (10)",""))<lenb($Z6),10,IF(lenb(SUBSTITUTE($Z6,W$1,""))<lenb($Z6),"ERROR",IF($Z6=$Y$1,"-",0)))))))))))) -> - | X6: =IF(lenb(SUBSTITUTE($Z6,X$1&" (1)",""))<lenb($Z6),1,IF(lenb(SUBSTITUTE($Z6,X$1&" (2)",""))<lenb($Z6),2,IF(lenb(SUBSTITUTE($Z6,X$1&" (3)",""))<lenb($Z6),3,IF(lenb(SUBSTITUTE($Z6,X$1&" (4)",""))<lenb($Z6),4,IF(lenb(SUBSTITUTE($Z6,X$1&" (5)",""))<lenb($Z6),5,IF(lenb(SUBSTITUTE($Z6,X$1&" (6)",""))<lenb($Z6),6,IF(lenb(SUBSTITUTE($Z6,X$1&" (7)",""))<lenb($Z6),1,IF(lenb(SUBSTITUTE($Z6,X$1&" (8)",""))<lenb($Z6),8,IF(lenb(SUBSTITUTE($Z6,X$1&" (9)",""))<lenb($Z6),9,IF(lenb(SUBSTITUTE($Z6,X$1&" (10)",""))<lenb($Z6),10,IF(lenb(SUBSTITUTE($Z6,X$1,""))<lenb($Z6),"ERROR",IF($Z6=$Y$1,"-",0)))))))))))) -> - | Y6: =IF(Z6=Y$1,1,"-") -> 1 | Z6: No links | AA6: =ifs(U6="","",U6="-",0,U6="Erro",0,U6<>"",LEN(U6)-LEN(SUBSTITUTE(U6,CHAR(10),""))+1) -> 0 | AB6: =COUNTIFS(Links!B:B,"FSE",Links!C:C,A6,Links!AD:AD,1) -> 0 | AC6: - | AD6: No | AE6: - | AF6: ---- | AG6: ---- | AH6: ---- | AI6: =IF(AH6="----",IF(AG6="----",IF(AF6="----","----",AF6),AF6&CHAR(10)&AG6),AF6&CHAR(10)&AG6&CHAR(10)&AH6) -> ---- | AJ6: =IFERROR( IF(AND(K6="Yes",AD6="No"),"Paper has link but no statement", IF(AND(K6="No",AD6="No"),"Paper has no link and no statement", IF(AND(K6="Yes",AD6="Yes"),"Paper has link and statement", IF(AND(K6="No",AD6="Yes"),"Paper has no link but has statement","")))),"") -> Paper has no link and no statement | AK6: 26-29/08/2024 | AL6: Research Papers | AM6: ="[FP"&TEXT(A6,"0000")&"]" -> [FP0784]
A7: 785 | B7: Automatically generated patches as debugging aids: a human study | C7: 2014 | D7: No | E7: - | F7: - | G7: - | H7: - | I7: - | J7: - | K7: Yes | L7: No | M7: No | N7: No | O7: No | P7: No | Q7: No | R7: Yes | S7: 3.5 Regression Analysis - Last paragraph | T7: http://www.cse.ust.hk/~idagoo/autofix/regression_analysis.html http://pishon.cse.ust.hk/userstudy/ | U7: http://www.cse.ust.hk/~idagoo/autofix/regression_analysis.html http://pishon.cse.ust.hk/userstudy/ | V7: =IF(lenb(SUBSTITUTE($Z7,V$1&" (1)",""))<lenb($Z7),1, IF(lenb(SUBSTITUTE($Z7,V$1&" (2)",""))<lenb($Z7),2, IF(lenb(SUBSTITUTE($Z7,V$1&" (3)",""))<lenb($Z7),3, IF(lenb(SUBSTITUTE($Z7,V$1&" (4)",""))<lenb($Z7),4, IF(lenb(SUBSTITUTE($Z7,V$1&" (5)",""))<lenb($Z7),5, IF(lenb(SUBSTITUTE($Z7,V$1&" (6)",""))<lenb($Z7),6, IF(lenb(SUBSTITUTE($Z7,V$1&" (7)",""))<lenb($Z7),1, IF(lenb(SUBSTITUTE($Z7,V$1&" (8)",""))<lenb($Z7),8, IF(lenb(SUBSTITUTE($Z7,V$1&" (9)",""))<lenb($Z7),9, IF(lenb(SUBSTITUTE($Z7,V$1&" (10)",""))<lenb($Z7),10, IF(lenb(SUBSTITUTE($Z7,V$1&" (26)",""))<lenb($Z7),26, IF(lenb(SUBSTITUTE($Z7,V$1,""))<lenb($Z7),"ERROR", IF($Z7=$Y$1,"-",0))))))))))))) -> 0 | W7: =IF(lenb(SUBSTITUTE($Z7,W$1&" (1)",""))<lenb($Z7),1,IF(lenb(SUBSTITUTE($Z7,W$1&" (2)",""))<lenb($Z7),2,IF(lenb(SUBSTITUTE($Z7,W$1&" (3)",""))<lenb($Z7),3,IF(lenb(SUBSTITUTE($Z7,W$1&" (4)",""))<lenb($Z7),4,IF(lenb(SUBSTITUTE($Z7,W$1&" (5)",""))<lenb($Z7),5,IF(lenb(SUBSTITUTE($Z7,W$1&" (6)",""))<lenb($Z7),6,IF(lenb(SUBSTITUTE($Z7,W$1&" (7)",""))<lenb($Z7),1,IF(lenb(SUBSTITUTE($Z7,W$1&" (8)",""))<lenb($Z7),8,IF(lenb(SUBSTITUTE($Z7,W$1&" (9)",""))<lenb($Z7),9,IF(lenb(SUBSTITUTE($Z7,W$1&" (10)",""))<lenb($Z7),10,IF(lenb(SUBSTITUTE($Z7,W$1,""))<lenb($Z7),"ERROR",IF($Z7=$Y$1,"-",0)))))))))))) -> 2 | X7: =IF(lenb(SUBSTITUTE($Z7,X$1&" (1)",""))<lenb($Z7),1,IF(lenb(SUBSTITUTE($Z7,X$1&" (2)",""))<lenb($Z7),2,IF(lenb(SUBSTITUTE($Z7,X$1&" (3)",""))<lenb($Z7),3,IF(lenb(SUBSTITUTE($Z7,X$1&" (4)",""))<lenb($Z7),4,IF(lenb(SUBSTITUTE($Z7,X$1&" (5)",""))<lenb($Z7),5,IF(lenb(SUBSTITUTE($Z7,X$1&" (6)",""))<lenb($Z7),6,IF(lenb(SUBSTITUTE($Z7,X$1&" (7)",""))<lenb($Z7),1,IF(lenb(SUBSTITUTE($Z7,X$1&" (8)",""))<lenb($Z7),8,IF(lenb(SUBSTITUTE($Z7,X$1&" (9)",""))<lenb($Z7),9,IF(lenb(SUBSTITUTE($Z7,X$1&" (10)",""))<lenb($Z7),10,IF(lenb(SUBSTITUTE($Z7,X$1,""))<lenb($Z7),"ERROR",IF($Z7=$Y$1,"-",0)))))))))))) -> 0 | Y7: =IF(Z7=Y$1,1,"-") -> - | Z7: Not Available (2) | AA7: =ifs(U7="","",U7="-",0,U7="Erro",0,U7<>"",LEN(U7)-LEN(SUBSTITUTE(U7,CHAR(10),""))+1) -> 2 | AB7: =COUNTIFS(Links!B:B,"FSE",Links!C:C,A7,Links!AD:AD,1) -> 1 | AC7: No | AD7: No | AE7: - | AF7: ---- | AG7: ---- | AH7: ---- | AI7: =IF(AH7="----",IF(AG7="----",IF(AF7="----","----",AF7),AF7&CHAR(10)&AG7),AF7&CHAR(10)&AG7&CHAR(10)&AH7) -> ---- | AJ7: =IFERROR( IF(AND(K7="Yes",AD7="No"),"Paper has link but no statement", IF(AND(K7="No",AD7="No"),"Paper has no link and no statement", IF(AND(K7="Yes",AD7="Yes"),"Paper has link and statement", IF(AND(K7="No",AD7="Yes"),"Paper has no link but has statement","")))),"") -> Paper has link but no statement | AK7: 26-29/08/2024 | AL7: Research Papers | AM7: ="[FP"&TEXT(A7,"0000")&"]" -> [FP0785]
A8: 786 | B8: A foundation for refactoring C with macros | C8: 2014 | D8: No | E8: - | F8: - | G8: - | H8: - | I8: - | J8: - | K8: Yes | L8: No | M8: No | N8: No | O8: Yes | P8: No | Q8: No | R8: No | S8: 10. FUTURE WORK AND CONCLUSION | T8: https://sites.google.com/site/cpprefactoring/ | U8: https://sites.google.com/site/cpprefactoring/ | V8: =IF(lenb(SUBSTITUTE($Z8,V$1&" (1)",""))<lenb($Z8),1, IF(lenb(SUBSTITUTE($Z8,V$1&" (2)",""))<lenb($Z8),2, IF(lenb(SUBSTITUTE($Z8,V$1&" (3)",""))<lenb($Z8),3, IF(lenb(SUBSTITUTE($Z8,V$1&" (4)",""))<lenb($Z8),4, IF(lenb(SUBSTITUTE($Z8,V$1&" (5)",""))<lenb($Z8),5, IF(lenb(SUBSTITUTE($Z8,V$1&" (6)",""))<lenb($Z8),6, IF(lenb(SUBSTITUTE($Z8,V$1&" (7)",""))<lenb($Z8),1, IF(lenb(SUBSTITUTE($Z8,V$1&" (8)",""))<lenb($Z8),8, IF(lenb(SUBSTITUTE($Z8,V$1&" (9)",""))<lenb($Z8),9, IF(lenb(SUBSTITUTE($Z8,V$1&" (10)",""))<lenb($Z8),10, IF(lenb(SUBSTITUTE($Z8,V$1&" (26)",""))<lenb($Z8),26, IF(lenb(SUBSTITUTE($Z8,V$1,""))<lenb($Z8),"ERROR", IF($Z8=$Y$1,"-",0))))))))))))) -> 0 | W8: =IF(lenb(SUBSTITUTE($Z8,W$1&" (1)",""))<lenb($Z8),1,IF(lenb(SUBSTITUTE($Z8,W$1&" (2)",""))<lenb($Z8),2,IF(lenb(SUBSTITUTE($Z8,W$1&" (3)",""))<lenb($Z8),3,IF(lenb(SUBSTITUTE($Z8,W$1&" (4)",""))<lenb($Z8),4,IF(lenb(SUBSTITUTE($Z8,W$1&" (5)",""))<lenb($Z8),5,IF(lenb(SUBSTITUTE($Z8,W$1&" (6)",""))<lenb($Z8),6,IF(lenb(SUBSTITUTE($Z8,W$1&" (7)",""))<lenb($Z8),1,IF(lenb(SUBSTITUTE($Z8,W$1&" (8)",""))<lenb($Z8),8,IF(lenb(SUBSTITUTE($Z8,W$1&" (9)",""))<lenb($Z8),9,IF(lenb(SUBSTITUTE($Z8,W$1&" (10)",""))<lenb($Z8),10,IF(lenb(SUBSTITUTE($Z8,W$1,""))<lenb($Z8),"ERROR",IF($Z8=$Y$1,"-",0)))))))))))) -> 1 | X8: =IF(lenb(SUBSTITUTE($Z8,X$1&" (1)",""))<lenb($Z8),1,IF(lenb(SUBSTITUTE($Z8,X$1&" (2)",""))<lenb($Z8),2,IF(lenb(SUBSTITUTE($Z8,X$1&" (3)",""))<lenb($Z8),3,IF(lenb(SUBSTITUTE($Z8,X$1&" (4)",""))<lenb($Z8),4,IF(lenb(SUBSTITUTE($Z8,X$1&" (5)",""))<lenb($Z8),5,IF(lenb(SUBSTITUTE($Z8,X$1&" (6)",""))<lenb($Z8),6,IF(lenb(SUBSTITUTE($Z8,X$1&" (7)",""))<lenb($Z8),1,IF(lenb(SUBSTITUTE($Z8,X$1&" (8)",""))<lenb($Z8),8,IF(lenb(SUBSTITUTE($Z8,X$1&" (9)",""))<lenb($Z8),9,IF(lenb(SUBSTITUTE($Z8,X$1&" (10)",""))<lenb($Z8),10,IF(lenb(SUBSTITUTE($Z8,X$1,""))<lenb($Z8),"ERROR",IF($Z8=$Y$1,"-",0)))))))))))) -> 0 | Y8: =IF(Z8=Y$1,1,"-") -> - | Z8: Not Available (1) | AA8: =ifs(U8="","",U8="-",0,U8="Erro",0,U8<>"",LEN(U8)-LEN(SUBSTITUTE(U8,CHAR(10),""))+1) -> 1 | AB8: =COUNTIFS(Links!B:B,"FSE",Links!C:C,A8,Links!AD:AD,1) -> 0 | AC8: No | AD8: No | AE8: - | AF8: ---- | AG8: ---- | AH8: ---- | AI8: =IF(AH8="----",IF(AG8="----",IF(AF8="----","----",AF8),AF8&CHAR(10)&AG8),AF8&CHAR(10)&AG8&CHAR(10)&AH8) -> ---- | AJ8: =IFERROR( IF(AND(K8="Yes",AD8="No"),"Paper has link but no statement", IF(AND(K8="No",AD8="No"),"Paper has no link and no statement", IF(AND(K8="Yes",AD8="Yes"),"Paper has link and statement", IF(AND(K8="No",AD8="Yes"),"Paper has no link but has statement","")))),"") -> Paper has link but no statement | AK8: 26-29/08/2024 | AL8: Research Papers | AM8: ="[FP"&TEXT(A8,"0000")&"]" -> [FP0786]
A9: 787 | B9: Vector abstraction and concretization for scalable detection of refactorings | C9: 2014 | D9: No | E9: - | F9: - | G9: - | H9: - | I9: - | J9: - | K9: No | L9: - | M9: - | N9: - | O9: - | P9: - | Q9: - | R9: - | S9: ---- | T9: - | U9: - | V9: =IF(lenb(SUBSTITUTE($Z9,V$1&" (1)",""))<lenb($Z9),1, IF(lenb(SUBSTITUTE($Z9,V$1&" (2)",""))<lenb($Z9),2, IF(lenb(SUBSTITUTE($Z9,V$1&" (3)",""))<lenb($Z9),3, IF(lenb(SUBSTITUTE($Z9,V$1&" (4)",""))<lenb($Z9),4, IF(lenb(SUBSTITUTE($Z9,V$1&" (5)",""))<lenb($Z9),5, IF(lenb(SUBSTITUTE($Z9,V$1&" (6)",""))<lenb($Z9),6, IF(lenb(SUBSTITUTE($Z9,V$1&" (7)",""))<lenb($Z9),1, IF(lenb(SUBSTITUTE($Z9,V$1&" (8)",""))<lenb($Z9),8, IF(lenb(SUBSTITUTE($Z9,V$1&" (9)",""))<lenb($Z9),9, IF(lenb(SUBSTITUTE($Z9,V$1&" (10)",""))<lenb($Z9),10, IF(lenb(SUBSTITUTE($Z9,V$1&" (26)",""))<lenb($Z9),26, IF(lenb(SUBSTITUTE($Z9,V$1,""))<lenb($Z9),"ERROR", IF($Z9=$Y$1,"-",0))))))))))))) -> - | W9: =IF(lenb(SUBSTITUTE($Z9,W$1&" (1)",""))<lenb($Z9),1,IF(lenb(SUBSTITUTE($Z9,W$1&" (2)",""))<lenb($Z9),2,IF(lenb(SUBSTITUTE($Z9,W$1&" (3)",""))<lenb($Z9),3,IF(lenb(SUBSTITUTE($Z9,W$1&" (4)",""))<lenb($Z9),4,IF(lenb(SUBSTITUTE($Z9,W$1&" (5)",""))<lenb($Z9),5,IF(lenb(SUBSTITUTE($Z9,W$1&" (6)",""))<lenb($Z9),6,IF(lenb(SUBSTITUTE($Z9,W$1&" (7)",""))<lenb($Z9),1,IF(lenb(SUBSTITUTE($Z9,W$1&" (8)",""))<lenb($Z9),8,IF(lenb(SUBSTITUTE($Z9,W$1&" (9)",""))<lenb($Z9),9,IF(lenb(SUBSTITUTE($Z9,W$1&" (10)",""))<lenb($Z9),10,IF(lenb(SUBSTITUTE($Z9,W$1,""))<lenb($Z9),"ERROR",IF($Z9=$Y$1,"-",0)))))))))))) -> - | X9: =IF(lenb(SUBSTITUTE($Z9,X$1&" (1)",""))<lenb($Z9),1,IF(lenb(SUBSTITUTE($Z9,X$1&" (2)",""))<lenb($Z9),2,IF(lenb(SUBSTITUTE($Z9,X$1&" (3)",""))<lenb($Z9),3,IF(lenb(SUBSTITUTE($Z9,X$1&" (4)",""))<lenb($Z9),4,IF(lenb(SUBSTITUTE($Z9,X$1&" (5)",""))<lenb($Z9),5,IF(lenb(SUBSTITUTE($Z9,X$1&" (6)",""))<lenb($Z9),6,IF(lenb(SUBSTITUTE($Z9,X$1&" (7)",""))<lenb($Z9),1,IF(lenb(SUBSTITUTE($Z9,X$1&" (8)",""))<lenb($Z9),8,IF(lenb(SUBSTITUTE($Z9,X$1&" (9)",""))<lenb($Z9),9,IF(lenb(SUBSTITUTE($Z9,X$1&" (10)",""))<lenb($Z9),10,IF(lenb(SUBSTITUTE($Z9,X$1,""))<lenb($Z9),"ERROR",IF($Z9=$Y$1,"-",0)))))))))))) -> - | Y9: =IF(Z9=Y$1,1,"-") -> 1 | Z9: No links | AA9: =ifs(U9="","",U9="-",0,U9="Erro",0,U9<>"",LEN(U9)-LEN(SUBSTITUTE(U9,CHAR(10),""))+1) -> 0 | AB9: =COUNTIFS(Links!B:B,"FSE",Links!C:C,A9,Links!AD:AD,1) -> 0 | AC9: - | AD9: No | AE9: - | AF9: ---- | AG9: ---- | AH9: ---- | AI9: =IF(AH9="----",IF(AG9="----",IF(AF9="----","----",AF9),AF9&CHAR(10)&AG9),AF9&CHAR(10)&AG9&CHAR(10)&AH9) -> ---- | AJ9: =IFERROR( IF(AND(K9="Yes",AD9="No"),"Paper has link but no statement", IF(AND(K9="No",AD9="No"),"Paper has no link and no statement", IF(AND(K9="Yes",AD9="Yes"),"Paper has link and statement", IF(AND(K9="No",AD9="Yes"),"Paper has no link but has statement","")))),"") -> Paper has no link and no statement | AK9: 26-29/08/2024 | AL9: Research Papers | AM9: ="[FP"&TEXT(A9,"0000")&"]" -> [FP0787]
A10: 788 | B10: FlowTwist: efficient context-sensitive inside-out taint analysis for large codebases | C10: 2014 | D10: No | E10: - | F10: - | G10: - | H10: - | I10: - | J10: - | K10: Yes | L10: Yes | M10: No | N10: No | O10: No | P10: No | Q10: No | R10: Yes | S10: FN 3 - 3. ANALYSIS DESIGN | T10: https://github.com/johanneslerch/FlowTwist | U10: https://github.com/johanneslerch/FlowTwist | V10: =IF(lenb(SUBSTITUTE($Z10,V$1&" (1)",""))<lenb($Z10),1, IF(lenb(SUBSTITUTE($Z10,V$1&" (2)",""))<lenb($Z10),2, IF(lenb(SUBSTITUTE($Z10,V$1&" (3)",""))<lenb($Z10),3, IF(lenb(SUBSTITUTE($Z10,V$1&" (4)",""))<lenb($Z10),4, IF(lenb(SUBSTITUTE($Z10,V$1&" (5)",""))<lenb($Z10),5, IF(lenb(SUBSTITUTE($Z10,V$1&" (6)",""))<lenb($Z10),6, IF(lenb(SUBSTITUTE($Z10,V$1&" (7)",""))<lenb($Z10),1, IF(lenb(SUBSTITUTE($Z10,V$1&" (8)",""))<lenb($Z10),8, IF(lenb(SUBSTITUTE($Z10,V$1&" (9)",""))<lenb($Z10),9, IF(lenb(SUBSTITUTE($Z10,V$1&" (10)",""))<lenb($Z10),10, IF(lenb(SUBSTITUTE($Z10,V$1&" (26)",""))<lenb($Z10),26, IF(lenb(SUBSTITUTE($Z10,V$1,""))<lenb($Z10),"ERROR", IF($Z10=$Y$1,"-",0))))))))))))) -> 1 | W10: =IF(lenb(SUBSTITUTE($Z10,W$1&" (1)",""))<lenb($Z10),1,IF(lenb(SUBSTITUTE($Z10,W$1&" (2)",""))<lenb($Z10),2,IF(lenb(SUBSTITUTE($Z10,W$1&" (3)",""))<lenb($Z10),3,IF(lenb(SUBSTITUTE($Z10,W$1&" (4)",""))<lenb($Z10),4,IF(lenb(SUBSTITUTE($Z10,W$1&" (5)",""))<lenb($Z10),5,IF(lenb(SUBSTITUTE($Z10,W$1&" (6)",""))<lenb($Z10),6,IF(lenb(SUBSTITUTE($Z10,W$1&" (7)",""))<lenb($Z10),1,IF(lenb(SUBSTITUTE($Z10,W$1&" (8)",""))<lenb($Z10),8,IF(lenb(SUBSTITUTE($Z10,W$1&" (9)",""))<lenb($Z10),9,IF(lenb(SUBSTITUTE($Z10,W$1&" (10)",""))<lenb($Z10),10,IF(lenb(SUBSTITUTE($Z10,W$1,""))<lenb($Z10),"ERROR",IF($Z10=$Y$1,"-",0)))))))))))) -> 0 | X10: =IF(lenb(SUBSTITUTE($Z10,X$1&" (1)",""))<lenb($Z10),1,IF(lenb(SUBSTITUTE($Z10,X$1&" (2)",""))<lenb($Z10),2,IF(lenb(SUBSTITUTE($Z10,X$1&" (3)",""))<lenb($Z10),3,IF(lenb(SUBSTITUTE($Z10,X$1&" (4)",""))<lenb($Z10),4,IF(lenb(SUBSTITUTE($Z10,X$1&" (5)",""))<lenb($Z10),5,IF(lenb(SUBSTITUTE($Z10,X$1&" (6)",""))<lenb($Z10),6,IF(lenb(SUBSTITUTE($Z10,X$1&" (7)",""))<lenb($Z10),1,IF(lenb(SUBSTITUTE($Z10,X$1&" (8)",""))<lenb($Z10),8,IF(lenb(SUBSTITUTE($Z10,X$1&" (9)",""))<lenb($Z10),9,IF(lenb(SUBSTITUTE($Z10,X$1&" (10)",""))<lenb($Z10),10,IF(lenb(SUBSTITUTE($Z10,X$1,""))<lenb($Z10),"ERROR",IF($Z10=$Y$1,"-",0)))))))))))) -> 0 | Y10: =IF(Z10=Y$1,1,"-") -> - | Z10: Publicly Available (1) | AA10: =ifs(U10="","",U10="-",0,U10="Erro",0,U10<>"",LEN(U10)-LEN(SUBSTITUTE(U10,CHAR(10),""))+1) -> 1 | AB10: =COUNTIFS(Links!B:B,"FSE",Links!C:C,A10,Links!AD:AD,1) -> 0 | AC10: No | AD10: No | AE10: - | AF10: ---- | AG10: ---- | AH10: ---- | AI10: =IF(AH10="----",IF(AG10="----",IF(AF10="----","----",AF10),AF10&CHAR(10)&AG10),AF10&CHAR(10)&AG10&CHAR(10)&AH10) -> ---- | AJ10: =IFERROR( IF(AND(K10="Yes",AD10="No"),"Paper has link but no statement", IF(AND(K10="No",AD10="No"),"Paper has no link and no statement", IF(AND(K10="Yes",AD10="Yes"),"Paper has link and statement", IF(AND(K10="No",AD10="Yes"),"Paper has no link but has statement","")))),"") -> Paper has link but no statement | AK10: 26-29/08/2024 | AL10: Research Papers | AM10: ="[FP"&TEXT(A10,"0000")&"]" -> [FP0788]
A11: 789 | B11: ORBS: language-independent program slicing | C11: 2014 | D11: No | E11: - | F11: - | G11: - | H11: - | I11: - | J11: - | K11: Yes | L11: Yes | M11: No | N11: No | O11: Yes | P11: No | Q11: No | R11: No | S11: 10. CONCLUSION | T11: crest.cs.ucl.ac.uk/resources/orbs/ | U11: crest.cs.ucl.ac.uk/resources/orbs/ | V11: =IF(lenb(SUBSTITUTE($Z11,V$1&" (1)",""))<lenb($Z11),1, IF(lenb(SUBSTITUTE($Z11,V$1&" (2)",""))<lenb($Z11),2, IF(lenb(SUBSTITUTE($Z11,V$1&" (3)",""))<lenb($Z11),3, IF(lenb(SUBSTITUTE($Z11,V$1&" (4)",""))<lenb($Z11),4, IF(lenb(SUBSTITUTE($Z11,V$1&" (5)",""))<lenb($Z11),5, IF(lenb(SUBSTITUTE($Z11,V$1&" (6)",""))<lenb($Z11),6, IF(lenb(SUBSTITUTE($Z11,V$1&" (7)",""))<lenb($Z11),1, IF(lenb(SUBSTITUTE($Z11,V$1&" (8)",""))<lenb($Z11),8, IF(lenb(SUBSTITUTE($Z11,V$1&" (9)",""))<lenb($Z11),9, IF(lenb(SUBSTITUTE($Z11,V$1&" (10)",""))<lenb($Z11),10, IF(lenb(SUBSTITUTE($Z11,V$1&" (26)",""))<lenb($Z11),26, IF(lenb(SUBSTITUTE($Z11,V$1,""))<lenb($Z11),"ERROR", IF($Z11=$Y$1,"-",0))))))))))))) -> 1 | W11: =IF(lenb(SUBSTITUTE($Z11,W$1&" (1)",""))<lenb($Z11),1,IF(lenb(SUBSTITUTE($Z11,W$1&" (2)",""))<lenb($Z11),2,IF(lenb(SUBSTITUTE($Z11,W$1&" (3)",""))<lenb($Z11),3,IF(lenb(SUBSTITUTE($Z11,W$1&" (4)",""))<lenb($Z11),4,IF(lenb(SUBSTITUTE($Z11,W$1&" (5)",""))<lenb($Z11),5,IF(lenb(SUBSTITUTE($Z11,W$1&" (6)",""))<lenb($Z11),6,IF(lenb(SUBSTITUTE($Z11,W$1&" (7)",""))<lenb($Z11),1,IF(lenb(SUBSTITUTE($Z11,W$1&" (8)",""))<lenb($Z11),8,IF(lenb(SUBSTITUTE($Z11,W$1&" (9)",""))<lenb($Z11),9,IF(lenb(SUBSTITUTE($Z11,W$1&" (10)",""))<lenb($Z11),10,IF(lenb(SUBSTITUTE($Z11,W$1,""))<lenb($Z11),"ERROR",IF($Z11=$Y$1,"-",0)))))))))))) -> 0 | X11: =IF(lenb(SUBSTITUTE($Z11,X$1&" (1)",""))<lenb($Z11),1,IF(lenb(SUBSTITUTE($Z11,X$1&" (2)",""))<lenb($Z11),2,IF(lenb(SUBSTITUTE($Z11,X$1&" (3)",""))<lenb($Z11),3,IF(lenb(SUBSTITUTE($Z11,X$1&" (4)",""))<lenb($Z11),4,IF(lenb(SUBSTITUTE($Z11,X$1&" (5)",""))<lenb($Z11),5,IF(lenb(SUBSTITUTE($Z11,X$1&" (6)",""))<lenb($Z11),6,IF(lenb(SUBSTITUTE($Z11,X$1&" (7)",""))<lenb($Z11),1,IF(lenb(SUBSTITUTE($Z11,X$1&" (8)",""))<lenb($Z11),8,IF(lenb(SUBSTITUTE($Z11,X$1&" (9)",""))<lenb($Z11),9,IF(lenb(SUBSTITUTE($Z11,X$1&" (10)",""))<lenb($Z11),10,IF(lenb(SUBSTITUTE($Z11,X$1,""))<lenb($Z11),"ERROR",IF($Z11=$Y$1,"-",0)))))))))))) -> 0 | Y11: =IF(Z11=Y$1,1,"-") -> - | Z11: Publicly Available (1) | AA11: =ifs(U11="","",U11="-",0,U11="Erro",0,U11<>"",LEN(U11)-LEN(SUBSTITUTE(U11,CHAR(10),""))+1) -> 1 | AB11: =COUNTIFS(Links!B:B,"FSE",Links!C:C,A11,Links!AD:AD,1) -> 1 | AC11: No | AD11: No | AE11: - | AF11: ---- | AG11: ---- | AH11: ---- | AI11: =IF(AH11="----",IF(AG11="----",IF(AF11="----","----",AF11),AF11&CHAR(10)&AG11),AF11&CHAR(10)&AG11&CHAR(10)&AH11) -> ---- | AJ11: =IFERROR( IF(AND(K11="Yes",AD11="No"),"Paper has link but no statement", IF(AND(K11="No",AD11="No"),"Paper has no link and no statement", IF(AND(K11="Yes",AD11="Yes"),"Paper has link and statement", IF(AND(K11="No",AD11="Yes"),"Paper has no link but has statement","")))),"") -> Paper has link but no statement | AK11: 26-29/08/2024 | AL11: Research Papers | AM11: ="[FP"&TEXT(A11,"0000")&"]" -> [FP0789]
A12: 790 | B12: JSAI: a static analysis platform for JavaScript | C12: 2014 | D12: Yes | E12: - | F12: - | G12: - | H12: - | I12: - | J12: Source: Winter et al. (2022) and email from the chair. | K12: Yes | L12: Yes | M12: No | N12: Yes | O12: No | P12: No | Q12: No | R12: No | S12: 1. INTRODUCTION | T12: http://www.cs.ucsb.edu/~pllab | U12: http://www.cs.ucsb.edu/~pllab | V12: =IF(lenb(SUBSTITUTE($Z12,V$1&" (1)",""))<lenb($Z12),1, IF(lenb(SUBSTITUTE($Z12,V$1&" (2)",""))<lenb($Z12),2, IF(lenb(SUBSTITUTE($Z12,V$1&" (3)",""))<lenb($Z12),3, IF(lenb(SUBSTITUTE($Z12,V$1&" (4)",""))<lenb($Z12),4, IF(lenb(SUBSTITUTE($Z12,V$1&" (5)",""))<lenb($Z12),5, IF(lenb(SUBSTITUTE($Z12,V$1&" (6)",""))<lenb($Z12),6, IF(lenb(SUBSTITUTE($Z12,V$1&" (7)",""))<lenb($Z12),1, IF(lenb(SUBSTITUTE($Z12,V$1&" (8)",""))<lenb($Z12),8, IF(lenb(SUBSTITUTE($Z12,V$1&" (9)",""))<lenb($Z12),9, IF(lenb(SUBSTITUTE($Z12,V$1&" (10)",""))<lenb($Z12),10, IF(lenb(SUBSTITUTE($Z12,V$1&" (26)",""))<lenb($Z12),26, IF(lenb(SUBSTITUTE($Z12,V$1,""))<lenb($Z12),"ERROR", IF($Z12=$Y$1,"-",0))))))))))))) -> 1 | W12: =IF(lenb(SUBSTITUTE($Z12,W$1&" (1)",""))<lenb($Z12),1,IF(lenb(SUBSTITUTE($Z12,W$1&" (2)",""))<lenb($Z12),2,IF(lenb(SUBSTITUTE($Z12,W$1&" (3)",""))<lenb($Z12),3,IF(lenb(SUBSTITUTE($Z12,W$1&" (4)",""))<lenb($Z12),4,IF(lenb(SUBSTITUTE($Z12,W$1&" (5)",""))<lenb($Z12),5,IF(lenb(SUBSTITUTE($Z12,W$1&" (6)",""))<lenb($Z12),6,IF(lenb(SUBSTITUTE($Z12,W$1&" (7)",""))<lenb($Z12),1,IF(lenb(SUBSTITUTE($Z12,W$1&" (8)",""))<lenb($Z12),8,IF(lenb(SUBSTITUTE($Z12,W$1&" (9)",""))<lenb($Z12),9,IF(lenb(SUBSTITUTE($Z12,W$1&" (10)",""))<lenb($Z12),10,IF(lenb(SUBSTITUTE($Z12,W$1,""))<lenb($Z12),"ERROR",IF($Z12=$Y$1,"-",0)))))))))))) -> 0 | X12: =IF(lenb(SUBSTITUTE($Z12,X$1&" (1)",""))<lenb($Z12),1,IF(lenb(SUBSTITUTE($Z12,X$1&" (2)",""))<lenb($Z12),2,IF(lenb(SUBSTITUTE($Z12,X$1&" (3)",""))<lenb($Z12),3,IF(lenb(SUBSTITUTE($Z12,X$1&" (4)",""))<lenb($Z12),4,IF(lenb(SUBSTITUTE($Z12,X$1&" (5)",""))<lenb($Z12),5,IF(lenb(SUBSTITUTE($Z12,X$1&" (6)",""))<lenb($Z12),6,IF(lenb(SUBSTITUTE($Z12,X$1&" (7)",""))<lenb($Z12),1,IF(lenb(SUBSTITUTE($Z12,X$1&" (8)",""))<lenb($Z12),8,IF(lenb(SUBSTITUTE($Z12,X$1&" (9)",""))<lenb($Z12),9,IF(lenb(SUBSTITUTE($Z12,X$1&" (10)",""))<lenb($Z12),10,IF(lenb(SUBSTITUTE($Z12,X$1,""))<lenb($Z12),"ERROR",IF($Z12=$Y$1,"-",0)))))))))))) -> 0 | Y12: =IF(Z12=Y$1,1,"-") -> - | Z12: Publicly Available (1) | AA12: =ifs(U12="","",U12="-",0,U12="Erro",0,U12<>"",LEN(U12)-LEN(SUBSTITUTE(U12,CHAR(10),""))+1) -> 1 | AB12: =COUNTIFS(Links!B:B,"FSE",Links!C:C,A12,Links!AD:AD,1) -> 1 | AC12: No | AD12: No | AE12: - | AF12: ---- | AG12: ---- | AH12: ---- | AI12: =IF(AH12="----",IF(AG12="----",IF(AF12="----","----",AF12),AF12&CHAR(10)&AG12),AF12&CHAR(10)&AG12&CHAR(10)&AH12) -> ---- | AJ12: =IFERROR( IF(AND(K12="Yes",AD12="No"),"Paper has link but no statement", IF(AND(K12="No",AD12="No"),"Paper has no link and no statement", IF(AND(K12="Yes",AD12="Yes"),"Paper has link and statement", IF(AND(K12="No",AD12="Yes"),"Paper has no link but has statement","")))),"") -> Paper has link but no statement | AK12: 26-29/08/2024 | AL12: Research Papers | AM12: ="[FP"&TEXT(A12,"0000")&"]" -> [FP0790]
A13: 791 | B13: A path-sensitively sliced control flow graph | C13: 2014 | D13: No | E13: - | F13: - | G13: - | H13: - | I13: - | J13: - | K13: No | L13: - | M13: - | N13: - | O13: - | P13: - | Q13: - | R13: - | S13: ---- | T13: - | U13: - | V13: =IF(lenb(SUBSTITUTE($Z13,V$1&" (1)",""))<lenb($Z13),1, IF(lenb(SUBSTITUTE($Z13,V$1&" (2)",""))<lenb($Z13),2, IF(lenb(SUBSTITUTE($Z13,V$1&" (3)",""))<lenb($Z13),3, IF(lenb(SUBSTITUTE($Z13,V$1&" (4)",""))<lenb($Z13),4, IF(lenb(SUBSTITUTE($Z13,V$1&" (5)",""))<lenb($Z13),5, IF(lenb(SUBSTITUTE($Z13,V$1&" (6)",""))<lenb($Z13),6, IF(lenb(SUBSTITUTE($Z13,V$1&" (7)",""))<lenb($Z13),1, IF(lenb(SUBSTITUTE($Z13,V$1&" (8)",""))<lenb($Z13),8, IF(lenb(SUBSTITUTE($Z13,V$1&" (9)",""))<lenb($Z13),9, IF(lenb(SUBSTITUTE($Z13,V$1&" (10)",""))<lenb($Z13),10, IF(lenb(SUBSTITUTE($Z13,V$1&" (26)",""))<lenb($Z13),26, IF(lenb(SUBSTITUTE($Z13,V$1,""))<lenb($Z13),"ERROR", IF($Z13=$Y$1,"-",0))))))))))))) -> - | W13: =IF(lenb(SUBSTITUTE($Z13,W$1&" (1)",""))<lenb($Z13),1,IF(lenb(SUBSTITUTE($Z13,W$1&" (2)",""))<lenb($Z13),2,IF(lenb(SUBSTITUTE($Z13,W$1&" (3)",""))<lenb($Z13),3,IF(lenb(SUBSTITUTE($Z13,W$1&" (4)",""))<lenb($Z13),4,IF(lenb(SUBSTITUTE($Z13,W$1&" (5)",""))<lenb($Z13),5,IF(lenb(SUBSTITUTE($Z13,W$1&" (6)",""))<lenb($Z13),6,IF(lenb(SUBSTITUTE($Z13,W$1&" (7)",""))<lenb($Z13),1,IF(lenb(SUBSTITUTE($Z13,W$1&" (8)",""))<lenb($Z13),8,IF(lenb(SUBSTITUTE($Z13,W$1&" (9)",""))<lenb($Z13),9,IF(lenb(SUBSTITUTE($Z13,W$1&" (10)",""))<lenb($Z13),10,IF(lenb(SUBSTITUTE($Z13,W$1,""))<lenb($Z13),"ERROR",IF($Z13=$Y$1,"-",0)))))))))))) -> - | X13: =IF(lenb(SUBSTITUTE($Z13,X$1&" (1)",""))<lenb($Z13),1,IF(lenb(SUBSTITUTE($Z13,X$1&" (2)",""))<lenb($Z13),2,IF(lenb(SUBSTITUTE($Z13,X$1&" (3)",""))<lenb($Z13),3,IF(lenb(SUBSTITUTE($Z13,X$1&" (4)",""))<lenb($Z13),4,IF(lenb(SUBSTITUTE($Z13,X$1&" (5)",""))<lenb($Z13),5,IF(lenb(SUBSTITUTE($Z13,X$1&" (6)",""))<lenb($Z13),6,IF(lenb(SUBSTITUTE($Z13,X$1&" (7)",""))<lenb($Z13),1,IF(lenb(SUBSTITUTE($Z13,X$1&" (8)",""))<lenb($Z13),8,IF(lenb(SUBSTITUTE($Z13,X$1&" (9)",""))<lenb($Z13),9,IF(lenb(SUBSTITUTE($Z13,X$1&" (10)",""))<lenb($Z13),10,IF(lenb(SUBSTITUTE($Z13,X$1,""))<lenb($Z13),"ERROR",IF($Z13=$Y$1,"-",0)))))))))))) -> - | Y13: =IF(Z13=Y$1,1,"-") -> 1 | Z13: No links | AA13: =ifs(U13="","",U13="-",0,U13="Erro",0,U13<>"",LEN(U13)-LEN(SUBSTITUTE(U13,CHAR(10),""))+1) -> 0 | AB13: =COUNTIFS(Links!B:B,"FSE",Links!C:C,A13,Links!AD:AD,1) -> 0 | AC13: - | AD13: No | AE13: - | AF13: ---- | AG13: ---- | AH13: ---- | AI13: =IF(AH13="----",IF(AG13="----",IF(AF13="----","----",AF13),AF13&CHAR(10)&AG13),AF13&CHAR(10)&AG13&CHAR(10)&AH13) -> ---- | AJ13: =IFERROR( IF(AND(K13="Yes",AD13="No"),"Paper has link but no statement", IF(AND(K13="No",AD13="No"),"Paper has no link and no statement", IF(AND(K13="Yes",AD13="Yes"),"Paper has link and statement", IF(AND(K13="No",AD13="Yes"),"Paper has no link but has statement","")))),"") -> Paper has no link and no statement | AK13: 26-29/08/2024 | AL13: Research Papers | AM13: ="[FP"&TEXT(A13,"0000")&"]" -> [FP0791]
... A446: 352 | B446: Dimensions of software configuration: on the configuration context in modern software development | C446: 2020 | D446: No | E446: - | F446: - | G446: - | H446: - | I446: - | J446: - | K446: Yes | L446: Yes | M446: No | N446: No | O446: No | P446: No | Q446: No | R446: Yes | S446: - | T446: https://github.com/AI-4-SE/Dimensions-of-Software-Configuration | U446: https://github.com/AI-4-SE/Dimensions-of-Software-Configuration | V446: =IF(lenb(SUBSTITUTE($Z446,V$1&" (1)",""))<lenb($Z446),1, IF(lenb(SUBSTITUTE($Z446,V$1&" (2)",""))<lenb($Z446),2, IF(lenb(SUBSTITUTE($Z446,V$1&" (3)",""))<lenb($Z446),3, IF(lenb(SUBSTITUTE($Z446,V$1&" (4)",""))<lenb($Z446),4, IF(lenb(SUBSTITUTE($Z446,V$1&" (5)",""))<lenb($Z446),5, IF(lenb(SUBSTITUTE($Z446,V$1&" (6)",""))<lenb($Z446),6, IF(lenb(SUBSTITUTE($Z446,V$1&" (7)",""))<lenb($Z446),1, IF(lenb(SUBSTITUTE($Z446,V$1&" (8)",""))<lenb($Z446),8, IF(lenb(SUBSTITUTE($Z446,V$1&" (9)",""))<lenb($Z446),9, IF(lenb(SUBSTITUTE($Z446,V$1&" (10)",""))<lenb($Z446),10, IF(lenb(SUBSTITUTE($Z446,V$1&" (26)",""))<lenb($Z446),26, IF(lenb(SUBSTITUTE($Z446,V$1,""))<lenb($Z446),"ERROR", IF($Z446=$Y$1,"-",0))))))))))))) -> 1 | W446: =IF(lenb(SUBSTITUTE($Z446,W$1&" (1)",""))<lenb($Z446),1,IF(lenb(SUBSTITUTE($Z446,W$1&" (2)",""))<lenb($Z446),2,IF(lenb(SUBSTITUTE($Z446,W$1&" (3)",""))<lenb($Z446),3,IF(lenb(SUBSTITUTE($Z446,W$1&" (4)",""))<lenb($Z446),4,IF(lenb(SUBSTITUTE($Z446,W$1&" (5)",""))<lenb($Z446),5,IF(lenb(SUBSTITUTE($Z446,W$1&" (6)",""))<lenb($Z446),6,IF(lenb(SUBSTITUTE($Z446,W$1&" (7)",""))<lenb($Z446),1,IF(lenb(SUBSTITUTE($Z446,W$1&" (8)",""))<lenb($Z446),8,IF(lenb(SUBSTITUTE($Z446,W$1&" (9)",""))<lenb($Z446),9,IF(lenb(SUBSTITUTE($Z446,W$1&" (10)",""))<lenb($Z446),10,IF(lenb(SUBSTITUTE($Z446,W$1,""))<lenb($Z446),"ERROR",IF($Z446=$Y$1,"-",0)))))))))))) -> 0 | X446: =IF(lenb(SUBSTITUTE($Z446,X$1&" (1)",""))<lenb($Z446),1,IF(lenb(SUBSTITUTE($Z446,X$1&" (2)",""))<lenb($Z446),2,IF(lenb(SUBSTITUTE($Z446,X$1&" (3)",""))<lenb($Z446),3,IF(lenb(SUBSTITUTE($Z446,X$1&" (4)",""))<lenb($Z446),4,IF(lenb(SUBSTITUTE($Z446,X$1&" (5)",""))<lenb($Z446),5,IF(lenb(SUBSTITUTE($Z446,X$1&" (6)",""))<lenb($Z446),6,IF(lenb(SUBSTITUTE($Z446,X$1&" (7)",""))<lenb($Z446),1,IF(lenb(SUBSTITUTE($Z446,X$1&" (8)",""))<lenb($Z446),8,IF(lenb(SUBSTITUTE($Z446,X$1&" (9)",""))<lenb($Z446),9,IF(lenb(SUBSTITUTE($Z446,X$1&" (10)",""))<lenb($Z446),10,IF(lenb(SUBSTITUTE($Z446,X$1,""))<lenb($Z446),"ERROR",IF($Z446=$Y$1,"-",0)))))))))))) -> 0 | Y446: =IF(Z446=Y$1,1,"-") -> - | Z446: Publicly Available (1) | AA446: =ifs(U446="","",U446="-",0,U446="Erro",0,U446<>"",LEN(U446)-LEN(SUBSTITUTE(U446,CHAR(10),""))+1) -> 1 | AB446: =COUNTIFS(Links!B:B,"FSE",Links!C:C,A446,Links!AD:AD,1) -> 0 | AC446: No | AD446: No | AE446: - | AF446: ---- | AG446: ---- | AH446: ---- | AI446: =IF(AH446="----",IF(AG446="----",IF(AF446="----","----",AF446),AF446&CHAR(10)&AG446),AF446&CHAR(10)&AG446&CHAR(10)&AH446) -> ---- | AJ446: =IFERROR( IF(AND(K446="Yes",AD446="No"),"Paper has link but no statement", IF(AND(K446="No",AD446="No"),"Paper has no link and no statement", IF(AND(K446="Yes",AD446="Yes"),"Paper has link and statement", IF(AND(K446="No",AD446="Yes"),"Paper has no link but has statement","")))),"") -> Paper has link but no statement | AK446: 26-29/08/2024 | AL446: Research Papers | AM446: ="[FP"&TEXT(A446,"0000")&"]" -> [FP0352]
A447: 353 | B447: Global cost/quality management across multiple applications | C447: 2020 | D447: No | E447: - | F447: - | G447: - | H447: - | I447: - | J447: - | K447: Yes | L447: No | M447: No | N447: No | O447: Yes | P447: No | Q447: No | R447: No | T447: https://github.com/niuye8911/rapid_m | U447: https://github.com/niuye8911/rapid_m | V447: =IF(lenb(SUBSTITUTE($Z447,V$1&" (1)",""))<lenb($Z447),1, IF(lenb(SUBSTITUTE($Z447,V$1&" (2)",""))<lenb($Z447),2, IF(lenb(SUBSTITUTE($Z447,V$1&" (3)",""))<lenb($Z447),3, IF(lenb(SUBSTITUTE($Z447,V$1&" (4)",""))<lenb($Z447),4, IF(lenb(SUBSTITUTE($Z447,V$1&" (5)",""))<lenb($Z447),5, IF(lenb(SUBSTITUTE($Z447,V$1&" (6)",""))<lenb($Z447),6, IF(lenb(SUBSTITUTE($Z447,V$1&" (7)",""))<lenb($Z447),1, IF(lenb(SUBSTITUTE($Z447,V$1&" (8)",""))<lenb($Z447),8, IF(lenb(SUBSTITUTE($Z447,V$1&" (9)",""))<lenb($Z447),9, IF(lenb(SUBSTITUTE($Z447,V$1&" (10)",""))<lenb($Z447),10, IF(lenb(SUBSTITUTE($Z447,V$1&" (26)",""))<lenb($Z447),26, IF(lenb(SUBSTITUTE($Z447,V$1,""))<lenb($Z447),"ERROR", IF($Z447=$Y$1,"-",0))))))))))))) -> 1 | W447: =IF(lenb(SUBSTITUTE($Z447,W$1&" (1)",""))<lenb($Z447),1,IF(lenb(SUBSTITUTE($Z447,W$1&" (2)",""))<lenb($Z447),2,IF(lenb(SUBSTITUTE($Z447,W$1&" (3)",""))<lenb($Z447),3,IF(lenb(SUBSTITUTE($Z447,W$1&" (4)",""))<lenb($Z447),4,IF(lenb(SUBSTITUTE($Z447,W$1&" (5)",""))<lenb($Z447),5,IF(lenb(SUBSTITUTE($Z447,W$1&" (6)",""))<lenb($Z447),6,IF(lenb(SUBSTITUTE($Z447,W$1&" (7)",""))<lenb($Z447),1,IF(lenb(SUBSTITUTE($Z447,W$1&" (8)",""))<lenb($Z447),8,IF(lenb(SUBSTITUTE($Z447,W$1&" (9)",""))<lenb($Z447),9,IF(lenb(SUBSTITUTE($Z447,W$1&" (10)",""))<lenb($Z447),10,IF(lenb(SUBSTITUTE($Z447,W$1,""))<lenb($Z447),"ERROR",IF($Z447=$Y$1,"-",0)))))))))))) -> 0 | X447: =IF(lenb(SUBSTITUTE($Z447,X$1&" (1)",""))<lenb($Z447),1,IF(lenb(SUBSTITUTE($Z447,X$1&" (2)",""))<lenb($Z447),2,IF(lenb(SUBSTITUTE($Z447,X$1&" (3)",""))<lenb($Z447),3,IF(lenb(SUBSTITUTE($Z447,X$1&" (4)",""))<lenb($Z447),4,IF(lenb(SUBSTITUTE($Z447,X$1&" (5)",""))<lenb($Z447),5,IF(lenb(SUBSTITUTE($Z447,X$1&" (6)",""))<lenb($Z447),6,IF(lenb(SUBSTITUTE($Z447,X$1&" (7)",""))<lenb($Z447),1,IF(lenb(SUBSTITUTE($Z447,X$1&" (8)",""))<lenb($Z447),8,IF(lenb(SUBSTITUTE($Z447,X$1&" (9)",""))<lenb($Z447),9,IF(lenb(SUBSTITUTE($Z447,X$1&" (10)",""))<lenb($Z447),10,IF(lenb(SUBSTITUTE($Z447,X$1,""))<lenb($Z447),"ERROR",IF($Z447=$Y$1,"-",0)))))))))))) -> 0 | Y447: =IF(Z447=Y$1,1,"-") -> - | Z447: Publicly Available (1) | AA447: =ifs(U447="","",U447="-",0,U447="Erro",0,U447<>"",LEN(U447)-LEN(SUBSTITUTE(U447,CHAR(10),""))+1) -> 1 | AB447: =COUNTIFS(Links!B:B,"FSE",Links!C:C,A447,Links!AD:AD,1) -> 0 | AC447: No | AD447: No | AE447: - | AF447: ---- | AG447: ---- | AH447: ---- | AI447: =IF(AH447="----",IF(AG447="----",IF(AF447="----","----",AF447),AF447&CHAR(10)&AG447),AF447&CHAR(10)&AG447&CHAR(10)&AH447) -> ---- | AJ447: =IFERROR( IF(AND(K447="Yes",AD447="No"),"Paper has link but no statement", IF(AND(K447="No",AD447="No"),"Paper has no link and no statement", IF(AND(K447="Yes",AD447="Yes"),"Paper has link and statement", IF(AND(K447="No",AD447="Yes"),"Paper has no link but has statement","")))),"") -> Paper has link but no statement | AK447: 26-29/08/2024 | AL447: Research Papers | AM447: ="[FP"&TEXT(A447,"0000")&"]" -> [FP0353]
A448: 354 | B448: Understanding and discovering software configuration dependencies in cloud and datacenter systems | C448: 2020 | D448: Yes | E448: Yes | F448: Yes | G448: Yes | H448: No | I448: No | J448: - | K448: Yes | L448: No | M448: No | N448: Yes | O448: Yes | P448: No | Q448: No | R448: No | S448: 1 INTRODUCTION ... 1.2 Contributions ... We have made the datasets and cDep publicly available at: https://github.com/xlab-uiuc/cdep-fse | T448: https://github.com/xlab-uiuc/cdep-fse | U448: https://github.com/xlab-uiuc/cdep-fse | V448: =IF(lenb(SUBSTITUTE($Z448,V$1&" (1)",""))<lenb($Z448),1, IF(lenb(SUBSTITUTE($Z448,V$1&" (2)",""))<lenb($Z448),2, IF(lenb(SUBSTITUTE($Z448,V$1&" (3)",""))<lenb($Z448),3, IF(lenb(SUBSTITUTE($Z448,V$1&" (4)",""))<lenb($Z448),4, IF(lenb(SUBSTITUTE($Z448,V$1&" (5)",""))<lenb($Z448),5, IF(lenb(SUBSTITUTE($Z448,V$1&" (6)",""))<lenb($Z448),6, IF(lenb(SUBSTITUTE($Z448,V$1&" (7)",""))<lenb($Z448),1, IF(lenb(SUBSTITUTE($Z448,V$1&" (8)",""))<lenb($Z448),8, IF(lenb(SUBSTITUTE($Z448,V$1&" (9)",""))<lenb($Z448),9, IF(lenb(SUBSTITUTE($Z448,V$1&" (10)",""))<lenb($Z448),10, IF(lenb(SUBSTITUTE($Z448,V$1&" (26)",""))<lenb($Z448),26, IF(lenb(SUBSTITUTE($Z448,V$1,""))<lenb($Z448),"ERROR", IF($Z448=$Y$1,"-",0))))))))))))) -> 1 | W448: =IF(lenb(SUBSTITUTE($Z448,W$1&" (1)",""))<lenb($Z448),1,IF(lenb(SUBSTITUTE($Z448,W$1&" (2)",""))<lenb($Z448),2,IF(lenb(SUBSTITUTE($Z448,W$1&" (3)",""))<lenb($Z448),3,IF(lenb(SUBSTITUTE($Z448,W$1&" (4)",""))<lenb($Z448),4,IF(lenb(SUBSTITUTE($Z448,W$1&" (5)",""))<lenb($Z448),5,IF(lenb(SUBSTITUTE($Z448,W$1&" (6)",""))<lenb($Z448),6,IF(lenb(SUBSTITUTE($Z448,W$1&" (7)",""))<lenb($Z448),1,IF(lenb(SUBSTITUTE($Z448,W$1&" (8)",""))<lenb($Z448),8,IF(lenb(SUBSTITUTE($Z448,W$1&" (9)",""))<lenb($Z448),9,IF(lenb(SUBSTITUTE($Z448,W$1&" (10)",""))<lenb($Z448),10,IF(lenb(SUBSTITUTE($Z448,W$1,""))<lenb($Z448),"ERROR",IF($Z448=$Y$1,"-",0)))))))))))) -> 0 | X448: =IF(lenb(SUBSTITUTE($Z448,X$1&" (1)",""))<lenb($Z448),1,IF(lenb(SUBSTITUTE($Z448,X$1&" (2)",""))<lenb($Z448),2,IF(lenb(SUBSTITUTE($Z448,X$1&" (3)",""))<lenb($Z448),3,IF(lenb(SUBSTITUTE($Z448,X$1&" (4)",""))<lenb($Z448),4,IF(lenb(SUBSTITUTE($Z448,X$1&" (5)",""))<lenb($Z448),5,IF(lenb(SUBSTITUTE($Z448,X$1&" (6)",""))<lenb($Z448),6,IF(lenb(SUBSTITUTE($Z448,X$1&" (7)",""))<lenb($Z448),1,IF(lenb(SUBSTITUTE($Z448,X$1&" (8)",""))<lenb($Z448),8,IF(lenb(SUBSTITUTE($Z448,X$1&" (9)",""))<lenb($Z448),9,IF(lenb(SUBSTITUTE($Z448,X$1&" (10)",""))<lenb($Z448),10,IF(lenb(SUBSTITUTE($Z448,X$1,""))<lenb($Z448),"ERROR",IF($Z448=$Y$1,"-",0)))))))))))) -> 0 | Y448: =IF(Z448=Y$1,1,"-") -> - | Z448: Publicly Available (1) | AA448: =ifs(U448="","",U448="-",0,U448="Erro",0,U448<>"",LEN(U448)-LEN(SUBSTITUTE(U448,CHAR(10),""))+1) -> 1 | AB448: =COUNTIFS(Links!B:B,"FSE",Links!C:C,A448,Links!AD:AD,1) -> 0 | AC448: No | AD448: No | AE448: - | AF448: ---- | AG448: ---- | AH448: ---- | AI448: =IF(AH448="----",IF(AG448="----",IF(AF448="----","----",AF448),AF448&CHAR(10)&AG448),AF448&CHAR(10)&AG448&CHAR(10)&AH448) -> ---- | AJ448: =IFERROR( IF(AND(K448="Yes",AD448="No"),"Paper has link but no statement", IF(AND(K448="No",AD448="No"),"Paper has no link and no statement", IF(AND(K448="Yes",AD448="Yes"),"Paper has link and statement", IF(AND(K448="No",AD448="Yes"),"Paper has no link but has statement","")))),"") -> Paper has link but no statement | AK448: 26-29/08/2024 | AL448: Research Papers | AM448: ="[FP"&TEXT(A448,"0000")&"]" -> [FP0354]
A449: 355 | B449: Docable: evaluating the executability of software tutorials | C449: 2020 | D449: Yes | E449: No | F449: Yes | G449: No | H449: No | I449: No | J449: - | K449: Yes | L449: No | M449: No | N449: No | O449: No | P449: No | Q449: No | R449: Yes | S449: 4 HUMAN-ANNOTATION-BASED EXECUTION RESULTS ... 4.1 Annotations ... The docable tool, stepfiles, and tutorials are available at: https://github.com/docable/docable. | T449: https://github.com/docable/docable | U449: https://github.com/docable/docable | V449: =IF(lenb(SUBSTITUTE($Z449,V$1&" (1)",""))<lenb($Z449),1, IF(lenb(SUBSTITUTE($Z449,V$1&" (2)",""))<lenb($Z449),2, IF(lenb(SUBSTITUTE($Z449,V$1&" (3)",""))<lenb($Z449),3, IF(lenb(SUBSTITUTE($Z449,V$1&" (4)",""))<lenb($Z449),4, IF(lenb(SUBSTITUTE($Z449,V$1&" (5)",""))<lenb($Z449),5, IF(lenb(SUBSTITUTE($Z449,V$1&" (6)",""))<lenb($Z449),6, IF(lenb(SUBSTITUTE($Z449,V$1&" (7)",""))<lenb($Z449),1, IF(lenb(SUBSTITUTE($Z449,V$1&" (8)",""))<lenb($Z449),8, IF(lenb(SUBSTITUTE($Z449,V$1&" (9)",""))<lenb($Z449),9, IF(lenb(SUBSTITUTE($Z449,V$1&" (10)",""))<lenb($Z449),10, IF(lenb(SUBSTITUTE($Z449,V$1&" (26)",""))<lenb($Z449),26, IF(lenb(SUBSTITUTE($Z449,V$1,""))<lenb($Z449),"ERROR", IF($Z449=$Y$1,"-",0))))))))))))) -> 1 | W449: =IF(lenb(SUBSTITUTE($Z449,W$1&" (1)",""))<lenb($Z449),1,IF(lenb(SUBSTITUTE($Z449,W$1&" (2)",""))<lenb($Z449),2,IF(lenb(SUBSTITUTE($Z449,W$1&" (3)",""))<lenb($Z449),3,IF(lenb(SUBSTITUTE($Z449,W$1&" (4)",""))<lenb($Z449),4,IF(lenb(SUBSTITUTE($Z449,W$1&" (5)",""))<lenb($Z449),5,IF(lenb(SUBSTITUTE($Z449,W$1&" (6)",""))<lenb($Z449),6,IF(lenb(SUBSTITUTE($Z449,W$1&" (7)",""))<lenb($Z449),1,IF(lenb(SUBSTITUTE($Z449,W$1&" (8)",""))<lenb($Z449),8,IF(lenb(SUBSTITUTE($Z449,W$1&" (9)",""))<lenb($Z449),9,IF(lenb(SUBSTITUTE($Z449,W$1&" (10)",""))<lenb($Z449),10,IF(lenb(SUBSTITUTE($Z449,W$1,""))<lenb($Z449),"ERROR",IF($Z449=$Y$1,"-",0)))))))))))) -> 0 | X449: =IF(lenb(SUBSTITUTE($Z449,X$1&" (1)",""))<lenb($Z449),1,IF(lenb(SUBSTITUTE($Z449,X$1&" (2)",""))<lenb($Z449),2,IF(lenb(SUBSTITUTE($Z449,X$1&" (3)",""))<lenb($Z449),3,IF(lenb(SUBSTITUTE($Z449,X$1&" (4)",""))<lenb($Z449),4,IF(lenb(SUBSTITUTE($Z449,X$1&" (5)",""))<lenb($Z449),5,IF(lenb(SUBSTITUTE($Z449,X$1&" (6)",""))<lenb($Z449),6,IF(lenb(SUBSTITUTE($Z449,X$1&" (7)",""))<lenb($Z449),1,IF(lenb(SUBSTITUTE($Z449,X$1&" (8)",""))<lenb($Z449),8,IF(lenb(SUBSTITUTE($Z449,X$1&" (9)",""))<lenb($Z449),9,IF(lenb(SUBSTITUTE($Z449,X$1&" (10)",""))<lenb($Z449),10,IF(lenb(SUBSTITUTE($Z449,X$1,""))<lenb($Z449),"ERROR",IF($Z449=$Y$1,"-",0)))))))))))) -> 0 | Y449: =IF(Z449=Y$1,1,"-") -> - | Z449: Publicly Available (1) | AA449: =ifs(U449="","",U449="-",0,U449="Erro",0,U449<>"",LEN(U449)-LEN(SUBSTITUTE(U449,CHAR(10),""))+1) -> 1 | AB449: =COUNTIFS(Links!B:B,"FSE",Links!C:C,A449,Links!AD:AD,1) -> 0 | AC449: No | AD449: No | AE449: - | AF449: ---- | AG449: ---- | AH449: ---- | AI449: =IF(AH449="----",IF(AG449="----",IF(AF449="----","----",AF449),AF449&CHAR(10)&AG449),AF449&CHAR(10)&AG449&CHAR(10)&AH449) -> ---- | AJ449: =IFERROR( IF(AND(K449="Yes",AD449="No"),"Paper has link but no statement", IF(AND(K449="No",AD449="No"),"Paper has no link and no statement", IF(AND(K449="Yes",AD449="Yes"),"Paper has link and statement", IF(AND(K449="No",AD449="Yes"),"Paper has no link but has statement","")))),"") -> Paper has link but no statement | AK449: 26-29/08/2024 | AL449: Research Papers | AM449: ="[FP"&TEXT(A449,"0000")&"]" -> [FP0355]
A450: 356 | B450: RulePad: interactive authoring of checkable design rules | C450: 2020 | D450: No | E450: - | F450: - | G450: - | H450: - | I450: - | J450: - | K450: Yes | L450: Yes | M450: No | N450: No | O450: No | P450: No | Q450: No | R450: Yes | S450: 6 EVALUATION ... 1The tool and the study materials are available at https://github.com/devuxd/RulePad. 6.3 Results ... 6.2 Tasks ... We adapted the source code used in the study from a simple Java project using the model-view-controller architecture3 | T450: https://github.com/devuxd/RulePad | U450: https://github.com/devuxd/RulePad | V450: =IF(lenb(SUBSTITUTE($Z450,V$1&" (1)",""))<lenb($Z450),1, IF(lenb(SUBSTITUTE($Z450,V$1&" (2)",""))<lenb($Z450),2, IF(lenb(SUBSTITUTE($Z450,V$1&" (3)",""))<lenb($Z450),3, IF(lenb(SUBSTITUTE($Z450,V$1&" (4)",""))<lenb($Z450),4, IF(lenb(SUBSTITUTE($Z450,V$1&" (5)",""))<lenb($Z450),5, IF(lenb(SUBSTITUTE($Z450,V$1&" (6)",""))<lenb($Z450),6, IF(lenb(SUBSTITUTE($Z450,V$1&" (7)",""))<lenb($Z450),1, IF(lenb(SUBSTITUTE($Z450,V$1&" (8)",""))<lenb($Z450),8, IF(lenb(SUBSTITUTE($Z450,V$1&" (9)",""))<lenb($Z450),9, IF(lenb(SUBSTITUTE($Z450,V$1&" (10)",""))<lenb($Z450),10, IF(lenb(SUBSTITUTE($Z450,V$1&" (26)",""))<lenb($Z450),26, IF(lenb(SUBSTITUTE($Z450,V$1,""))<lenb($Z450),"ERROR", IF($Z450=$Y$1,"-",0))))))))))))) -> 1 | W450: =IF(lenb(SUBSTITUTE($Z450,W$1&" (1)",""))<lenb($Z450),1,IF(lenb(SUBSTITUTE($Z450,W$1&" (2)",""))<lenb($Z450),2,IF(lenb(SUBSTITUTE($Z450,W$1&" (3)",""))<lenb($Z450),3,IF(lenb(SUBSTITUTE($Z450,W$1&" (4)",""))<lenb($Z450),4,IF(lenb(SUBSTITUTE($Z450,W$1&" (5)",""))<lenb($Z450),5,IF(lenb(SUBSTITUTE($Z450,W$1&" (6)",""))<lenb($Z450),6,IF(lenb(SUBSTITUTE($Z450,W$1&" (7)",""))<lenb($Z450),1,IF(lenb(SUBSTITUTE($Z450,W$1&" (8)",""))<lenb($Z450),8,IF(lenb(SUBSTITUTE($Z450,W$1&" (9)",""))<lenb($Z450),9,IF(lenb(SUBSTITUTE($Z450,W$1&" (10)",""))<lenb($Z450),10,IF(lenb(SUBSTITUTE($Z450,W$1,""))<lenb($Z450),"ERROR",IF($Z450=$Y$1,"-",0)))))))))))) -> 0 | X450: =IF(lenb(SUBSTITUTE($Z450,X$1&" (1)",""))<lenb($Z450),1,IF(lenb(SUBSTITUTE($Z450,X$1&" (2)",""))<lenb($Z450),2,IF(lenb(SUBSTITUTE($Z450,X$1&" (3)",""))<lenb($Z450),3,IF(lenb(SUBSTITUTE($Z450,X$1&" (4)",""))<lenb($Z450),4,IF(lenb(SUBSTITUTE($Z450,X$1&" (5)",""))<lenb($Z450),5,IF(lenb(SUBSTITUTE($Z450,X$1&" (6)",""))<lenb($Z450),6,IF(lenb(SUBSTITUTE($Z450,X$1&" (7)",""))<lenb($Z450),1,IF(lenb(SUBSTITUTE($Z450,X$1&" (8)",""))<lenb($Z450),8,IF(lenb(SUBSTITUTE($Z450,X$1&" (9)",""))<lenb($Z450),9,IF(lenb(SUBSTITUTE($Z450,X$1&" (10)",""))<lenb($Z450),10,IF(lenb(SUBSTITUTE($Z450,X$1,""))<lenb($Z450),"ERROR",IF($Z450=$Y$1,"-",0)))))))))))) -> 0 | Y450: =IF(Z450=Y$1,1,"-") -> - | Z450: Publicly Available (1) | AA450: =ifs(U450="","",U450="-",0,U450="Erro",0,U450<>"",LEN(U450)-LEN(SUBSTITUTE(U450,CHAR(10),""))+1) -> 1 | AB450: =COUNTIFS(Links!B:B,"FSE",Links!C:C,A450,Links!AD:AD,1) -> 0 | AC450: No | AD450: No | AE450: - | AF450: ---- | AG450: ---- | AH450: ---- | AI450: =IF(AH450="----",IF(AG450="----",IF(AF450="----","----",AF450),AF450&CHAR(10)&AG450),AF450&CHAR(10)&AG450&CHAR(10)&AH450) -> ---- | AJ450: =IFERROR( IF(AND(K450="Yes",AD450="No"),"Paper has link but no statement", IF(AND(K450="No",AD450="No"),"Paper has no link and no statement", IF(AND(K450="Yes",AD450="Yes"),"Paper has link and statement", IF(AND(K450="No",AD450="Yes"),"Paper has no link but has statement","")))),"") -> Paper has link but no statement | AK450: 26-29/08/2024 | AL450: Research Papers | AM450: ="[FP"&TEXT(A450,"0000")&"]" -> [FP0356]
A451: 357 | B451: A first look at good first issues on GitHub | C451: 2020 | D451: No | E451: - | F451: - | G451: - | H451: - | I451: - | J451: - | K451: Yes | L451: No | M451: No | N451: No | O451: Yes | P451: No | Q451: No | R451: No | S451: 10 CONCLUSION ... To facilitate replications or other types of future work, we pro- vide the data, scripts, and detailed coding guidelines used in this study online: https://github.com/SunflowerPKU/FSE20Dataset. | T451: https://github.com/SunflowerPKU/FSE20Dataset | U451: https://github.com/SunflowerPKU/FSE20Dataset | V451: =IF(lenb(SUBSTITUTE($Z451,V$1&" (1)",""))<lenb($Z451),1, IF(lenb(SUBSTITUTE($Z451,V$1&" (2)",""))<lenb($Z451),2, IF(lenb(SUBSTITUTE($Z451,V$1&" (3)",""))<lenb($Z451),3, IF(lenb(SUBSTITUTE($Z451,V$1&" (4)",""))<lenb($Z451),4, IF(lenb(SUBSTITUTE($Z451,V$1&" (5)",""))<lenb($Z451),5, IF(lenb(SUBSTITUTE($Z451,V$1&" (6)",""))<lenb($Z451),6, IF(lenb(SUBSTITUTE($Z451,V$1&" (7)",""))<lenb($Z451),1, IF(lenb(SUBSTITUTE($Z451,V$1&" (8)",""))<lenb($Z451),8, IF(lenb(SUBSTITUTE($Z451,V$1&" (9)",""))<lenb($Z451),9, IF(lenb(SUBSTITUTE($Z451,V$1&" (10)",""))<lenb($Z451),10, IF(lenb(SUBSTITUTE($Z451,V$1&" (26)",""))<lenb($Z451),26, IF(lenb(SUBSTITUTE($Z451,V$1,""))<lenb($Z451),"ERROR", IF($Z451=$Y$1,"-",0))))))))))))) -> 1 | W451: =IF(lenb(SUBSTITUTE($Z451,W$1&" (1)",""))<lenb($Z451),1,IF(lenb(SUBSTITUTE($Z451,W$1&" (2)",""))<lenb($Z451),2,IF(lenb(SUBSTITUTE($Z451,W$1&" (3)",""))<lenb($Z451),3,IF(lenb(SUBSTITUTE($Z451,W$1&" (4)",""))<lenb($Z451),4,IF(lenb(SUBSTITUTE($Z451,W$1&" (5)",""))<lenb($Z451),5,IF(lenb(SUBSTITUTE($Z451,W$1&" (6)",""))<lenb($Z451),6,IF(lenb(SUBSTITUTE($Z451,W$1&" (7)",""))<lenb($Z451),1,IF(lenb(SUBSTITUTE($Z451,W$1&" (8)",""))<lenb($Z451),8,IF(lenb(SUBSTITUTE($Z451,W$1&" (9)",""))<lenb($Z451),9,IF(lenb(SUBSTITUTE($Z451,W$1&" (10)",""))<lenb($Z451),10,IF(lenb(SUBSTITUTE($Z451,W$1,""))<lenb($Z451),"ERROR",IF($Z451=$Y$1,"-",0)))))))))))) -> 0 | X451: =IF(lenb(SUBSTITUTE($Z451,X$1&" (1)",""))<lenb($Z451),1,IF(lenb(SUBSTITUTE($Z451,X$1&" (2)",""))<lenb($Z451),2,IF(lenb(SUBSTITUTE($Z451,X$1&" (3)",""))<lenb($Z451),3,IF(lenb(SUBSTITUTE($Z451,X$1&" (4)",""))<lenb($Z451),4,IF(lenb(SUBSTITUTE($Z451,X$1&" (5)",""))<lenb($Z451),5,IF(lenb(SUBSTITUTE($Z451,X$1&" (6)",""))<lenb($Z451),6,IF(lenb(SUBSTITUTE($Z451,X$1&" (7)",""))<lenb($Z451),1,IF(lenb(SUBSTITUTE($Z451,X$1&" (8)",""))<lenb($Z451),8,IF(lenb(SUBSTITUTE($Z451,X$1&" (9)",""))<lenb($Z451),9,IF(lenb(SUBSTITUTE($Z451,X$1&" (10)",""))<lenb($Z451),10,IF(lenb(SUBSTITUTE($Z451,X$1,""))<lenb($Z451),"ERROR",IF($Z451=$Y$1,"-",0)))))))))))) -> 0 | Y451: =IF(Z451=Y$1,1,"-") -> - | Z451: Publicly Available (1) | AA451: =ifs(U451="","",U451="-",0,U451="Erro",0,U451<>"",LEN(U451)-LEN(SUBSTITUTE(U451,CHAR(10),""))+1) -> 1 | AB451: =COUNTIFS(Links!B:B,"FSE",Links!C:C,A451,Links!AD:AD,1) -> 0 | AC451: No | AD451: No | AE451: - | AF451: ---- | AG451: ---- | AH451: ---- | AI451: =IF(AH451="----",IF(AG451="----",IF(AF451="----","----",AF451),AF451&CHAR(10)&AG451),AF451&CHAR(10)&AG451&CHAR(10)&AH451) -> ---- | AJ451: =IFERROR( IF(AND(K451="Yes",AD451="No"),"Paper has link but no statement", IF(AND(K451="No",AD451="No"),"Paper has no link and no statement", IF(AND(K451="Yes",AD451="Yes"),"Paper has link and statement", IF(AND(K451="No",AD451="Yes"),"Paper has no link but has statement","")))),"") -> Paper has link but no statement | AK451: 26-29/08/2024 | AL451: Research Papers | AM451: ="[FP"&TEXT(A451,"0000")&"]" -> [FP0357]
A452: 358 | B452: A randomized controlled trial on the effects of embedded computer language switching | C452: 2020 | D452: Yes | E452: Yes | F452: Yes | G452: Yes | H452: No | I452: No | J452: - | K452: Yes | L452: No | M452: Yes | N452: No | O452: No | P452: No | Q452: No | R452: Yes | S452: 5 QUANTITATIVE RESULTS This section presents the results of the experiment. The script to analyze the data can be found in the accompanying replication packet artifact [32]. | T452: https://doi.org/10.5281/zenodo.3911750 | U452: https://doi.org/10.5281/zenodo.3911750 | V452: =IF(lenb(SUBSTITUTE($Z452,V$1&" (1)",""))<lenb($Z452),1, IF(lenb(SUBSTITUTE($Z452,V$1&" (2)",""))<lenb($Z452),2, IF(lenb(SUBSTITUTE($Z452,V$1&" (3)",""))<lenb($Z452),3, IF(lenb(SUBSTITUTE($Z452,V$1&" (4)",""))<lenb($Z452),4, IF(lenb(SUBSTITUTE($Z452,V$1&" (5)",""))<lenb($Z452),5, IF(lenb(SUBSTITUTE($Z452,V$1&" (6)",""))<lenb($Z452),6, IF(lenb(SUBSTITUTE($Z452,V$1&" (7)",""))<lenb($Z452),1, IF(lenb(SUBSTITUTE($Z452,V$1&" (8)",""))<lenb($Z452),8, IF(lenb(SUBSTITUTE($Z452,V$1&" (9)",""))<lenb($Z452),9, IF(lenb(SUBSTITUTE($Z452,V$1&" (10)",""))<lenb($Z452),10, IF(lenb(SUBSTITUTE($Z452,V$1&" (26)",""))<lenb($Z452),26, IF(lenb(SUBSTITUTE($Z452,V$1,""))<lenb($Z452),"ERROR", IF($Z452=$Y$1,"-",0))))))))))))) -> 1 | W452: =IF(lenb(SUBSTITUTE($Z452,W$1&" (1)",""))<lenb($Z452),1,IF(lenb(SUBSTITUTE($Z452,W$1&" (2)",""))<lenb($Z452),2,IF(lenb(SUBSTITUTE($Z452,W$1&" (3)",""))<lenb($Z452),3,IF(lenb(SUBSTITUTE($Z452,W$1&" (4)",""))<lenb($Z452),4,IF(lenb(SUBSTITUTE($Z452,W$1&" (5)",""))<lenb($Z452),5,IF(lenb(SUBSTITUTE($Z452,W$1&" (6)",""))<lenb($Z452),6,IF(lenb(SUBSTITUTE($Z452,W$1&" (7)",""))<lenb($Z452),1,IF(lenb(SUBSTITUTE($Z452,W$1&" (8)",""))<lenb($Z452),8,IF(lenb(SUBSTITUTE($Z452,W$1&" (9)",""))<lenb($Z452),9,IF(lenb(SUBSTITUTE($Z452,W$1&" (10)",""))<lenb($Z452),10,IF(lenb(SUBSTITUTE($Z452,W$1,""))<lenb($Z452),"ERROR",IF($Z452=$Y$1,"-",0)))))))))))) -> 0 | X452: =IF(lenb(SUBSTITUTE($Z452,X$1&" (1)",""))<lenb($Z452),1,IF(lenb(SUBSTITUTE($Z452,X$1&" (2)",""))<lenb($Z452),2,IF(lenb(SUBSTITUTE($Z452,X$1&" (3)",""))<lenb($Z452),3,IF(lenb(SUBSTITUTE($Z452,X$1&" (4)",""))<lenb($Z452),4,IF(lenb(SUBSTITUTE($Z452,X$1&" (5)",""))<lenb($Z452),5,IF(lenb(SUBSTITUTE($Z452,X$1&" (6)",""))<lenb($Z452),6,IF(lenb(SUBSTITUTE($Z452,X$1&" (7)",""))<lenb($Z452),1,IF(lenb(SUBSTITUTE($Z452,X$1&" (8)",""))<lenb($Z452),8,IF(lenb(SUBSTITUTE($Z452,X$1&" (9)",""))<lenb($Z452),9,IF(lenb(SUBSTITUTE($Z452,X$1&" (10)",""))<lenb($Z452),10,IF(lenb(SUBSTITUTE($Z452,X$1,""))<lenb($Z452),"ERROR",IF($Z452=$Y$1,"-",0)))))))))))) -> 0 | Y452: =IF(Z452=Y$1,1,"-") -> - | Z452: Publicly Available (1) | AA452: =ifs(U452="","",U452="-",0,U452="Erro",0,U452<>"",LEN(U452)-LEN(SUBSTITUTE(U452,CHAR(10),""))+1) -> 1 | AB452: =COUNTIFS(Links!B:B,"FSE",Links!C:C,A452,Links!AD:AD,1) -> 0 | AC452: Yes | AD452: No | AE452: - | AF452: ---- | AG452: ---- | AH452: ---- | AI452: =IF(AH452="----",IF(AG452="----",IF(AF452="----","----",AF452),AF452&CHAR(10)&AG452),AF452&CHAR(10)&AG452&CHAR(10)&AH452) -> ---- | AJ452: =IFERROR( IF(AND(K452="Yes",AD452="No"),"Paper has link but no statement", IF(AND(K452="No",AD452="No"),"Paper has no link and no statement", IF(AND(K452="Yes",AD452="Yes"),"Paper has link and statement", IF(AND(K452="No",AD452="Yes"),"Paper has no link but has statement","")))),"") -> Paper has link but no statement | AK452: 26-29/08/2024 | AL452: Research Papers | AM452: ="[FP"&TEXT(A452,"0000")&"]" -> [FP0358]
A453: 359 | B453: A theory of the engagement in open source projects via summer of code programs | C453: 2020 | D453: No | E453: - | F453: - | G453: - | H453: - | I453: - | J453: - | K453: Yes | L453: Yes | M453: No | N453: No | O453: No | P453: No | Q453: No | R453: Yes | S453: 3 RESEARCH DESIGN ... 3.3 Phase III: Perceptions about the Theory ... Data collection. In a questionnaire7, we asked students whether they had heard of GSoC or similar programs. For the students who had heard of such a program, we asked them to describe it and tell us whether they had considered joining it. Next, we asked students to read an explanation of GSoC (from the program website).8 After that, we asked them to list, in order of importance, what SoC students gain by participating in GSoC. Then, we instructed the students to watch a 7.5-minute explana- tory video9 that the authors prepared to summarize the theory. We decided to use an explanatory video instead of text to facilitate the students’ participation. Afterward, the students answered a final questionnaire,10 | T453: https://figshare.com/s/f5a9f70a82d600b4c949 https://pt.surveymonkey.com/r/HX9H7FX https://figshare.com/s/88704bc89fac722ac073 https://pt.surveymonkey.com/r/HN82XYJ | U453: https://figshare.com/s/f5a9f70a82d600b4c949 https://pt.surveymonkey.com/r/HX9H7FX https://figshare.com/s/88704bc89fac722ac073 https://pt.surveymonkey.com/r/HN82XYJ | V453: =IF(lenb(SUBSTITUTE($Z453,V$1&" (1)",""))<lenb($Z453),1, IF(lenb(SUBSTITUTE($Z453,V$1&" (2)",""))<lenb($Z453),2, IF(lenb(SUBSTITUTE($Z453,V$1&" (3)",""))<lenb($Z453),3, IF(lenb(SUBSTITUTE($Z453,V$1&" (4)",""))<lenb($Z453),4, IF(lenb(SUBSTITUTE($Z453,V$1&" (5)",""))<lenb($Z453),5, IF(lenb(SUBSTITUTE($Z453,V$1&" (6)",""))<lenb($Z453),6, IF(lenb(SUBSTITUTE($Z453,V$1&" (7)",""))<lenb($Z453),1, IF(lenb(SUBSTITUTE($Z453,V$1&" (8)",""))<lenb($Z453),8, IF(lenb(SUBSTITUTE($Z453,V$1&" (9)",""))<lenb($Z453),9, IF(lenb(SUBSTITUTE($Z453,V$1&" (10)",""))<lenb($Z453),10, IF(lenb(SUBSTITUTE($Z453,V$1&" (26)",""))<lenb($Z453),26, IF(lenb(SUBSTITUTE($Z453,V$1,""))<lenb($Z453),"ERROR", IF($Z453=$Y$1,"-",0))))))))))))) -> 2 | W453: =IF(lenb(SUBSTITUTE($Z453,W$1&" (1)",""))<lenb($Z453),1,IF(lenb(SUBSTITUTE($Z453,W$1&" (2)",""))<lenb($Z453),2,IF(lenb(SUBSTITUTE($Z453,W$1&" (3)",""))<lenb($Z453),3,IF(lenb(SUBSTITUTE($Z453,W$1&" (4)",""))<lenb($Z453),4,IF(lenb(SUBSTITUTE($Z453,W$1&" (5)",""))<lenb($Z453),5,IF(lenb(SUBSTITUTE($Z453,W$1&" (6)",""))<lenb($Z453),6,IF(lenb(SUBSTITUTE($Z453,W$1&" (7)",""))<lenb($Z453),1,IF(lenb(SUBSTITUTE($Z453,W$1&" (8)",""))<lenb($Z453),8,IF(lenb(SUBSTITUTE($Z453,W$1&" (9)",""))<lenb($Z453),9,IF(lenb(SUBSTITUTE($Z453,W$1&" (10)",""))<lenb($Z453),10,IF(lenb(SUBSTITUTE($Z453,W$1,""))<lenb($Z453),"ERROR",IF($Z453=$Y$1,"-",0)))))))))))) -> 2 | X453: =IF(lenb(SUBSTITUTE($Z453,X$1&" (1)",""))<lenb($Z453),1,IF(lenb(SUBSTITUTE($Z453,X$1&" (2)",""))<lenb($Z453),2,IF(lenb(SUBSTITUTE($Z453,X$1&" (3)",""))<lenb($Z453),3,IF(lenb(SUBSTITUTE($Z453,X$1&" (4)",""))<lenb($Z453),4,IF(lenb(SUBSTITUTE($Z453,X$1&" (5)",""))<lenb($Z453),5,IF(lenb(SUBSTITUTE($Z453,X$1&" (6)",""))<lenb($Z453),6,IF(lenb(SUBSTITUTE($Z453,X$1&" (7)",""))<lenb($Z453),1,IF(lenb(SUBSTITUTE($Z453,X$1&" (8)",""))<lenb($Z453),8,IF(lenb(SUBSTITUTE($Z453,X$1&" (9)",""))<lenb($Z453),9,IF(lenb(SUBSTITUTE($Z453,X$1&" (10)",""))<lenb($Z453),10,IF(lenb(SUBSTITUTE($Z453,X$1,""))<lenb($Z453),"ERROR",IF($Z453=$Y$1,"-",0)))))))))))) -> 0 | Y453: =IF(Z453=Y$1,1,"-") -> - | Z453: Publicly Available (2) Not Available (2) | AA453: =ifs(U453="","",U453="-",0,U453="Erro",0,U453<>"",LEN(U453)-LEN(SUBSTITUTE(U453,CHAR(10),""))+1) -> 4 | AB453: =COUNTIFS(Links!B:B,"FSE",Links!C:C,A453,Links!AD:AD,1) -> 0 | AC453: Yes | AD453: No | AE453: - | AF453: ---- | AG453: ---- | AH453: ---- | AI453: =IF(AH453="----",IF(AG453="----",IF(AF453="----","----",AF453),AF453&CHAR(10)&AG453),AF453&CHAR(10)&AG453&CHAR(10)&AH453) -> ---- | AJ453: =IFERROR( IF(AND(K453="Yes",AD453="No"),"Paper has link but no statement", IF(AND(K453="No",AD453="No"),"Paper has no link and no statement", IF(AND(K453="Yes",AD453="Yes"),"Paper has link and statement", IF(AND(K453="No",AD453="Yes"),"Paper has no link but has statement","")))),"") -> Paper has link but no statement | AK453: 26-29/08/2024 | AL453: Research Papers | AM453: ="[FP"&TEXT(A453,"0000")&"]" -> [FP0359]
A454: 360 | B454: An empirical analysis of the costs of clone- and platform-oriented software reuse | C454: 2020 | D454: Yes | E454: Yes | F454: No | G454: No | H454: No | I454: No | J454: - | K454: Yes | L454: Yes | M454: No | N454: Yes | O454: No | P454: No | Q454: No | R454: No | S454: A replication package with our interview guide and the data we analyzed as an open-source dataset.1 | T454: https://doi.org/10.5281/zenodo.3993789 | U454: https://doi.org/10.5281/zenodo.3993789 | V454: =IF(lenb(SUBSTITUTE($Z454,V$1&" (1)",""))<lenb($Z454),1, IF(lenb(SUBSTITUTE($Z454,V$1&" (2)",""))<lenb($Z454),2, IF(lenb(SUBSTITUTE($Z454,V$1&" (3)",""))<lenb($Z454),3, IF(lenb(SUBSTITUTE($Z454,V$1&" (4)",""))<lenb($Z454),4, IF(lenb(SUBSTITUTE($Z454,V$1&" (5)",""))<lenb($Z454),5, IF(lenb(SUBSTITUTE($Z454,V$1&" (6)",""))<lenb($Z454),6, IF(lenb(SUBSTITUTE($Z454,V$1&" (7)",""))<lenb($Z454),1, IF(lenb(SUBSTITUTE($Z454,V$1&" (8)",""))<lenb($Z454),8, IF(lenb(SUBSTITUTE($Z454,V$1&" (9)",""))<lenb($Z454),9, IF(lenb(SUBSTITUTE($Z454,V$1&" (10)",""))<lenb($Z454),10, IF(lenb(SUBSTITUTE($Z454,V$1&" (26)",""))<lenb($Z454),26, IF(lenb(SUBSTITUTE($Z454,V$1,""))<lenb($Z454),"ERROR", IF($Z454=$Y$1,"-",0))))))))))))) -> 1 | W454: =IF(lenb(SUBSTITUTE($Z454,W$1&" (1)",""))<lenb($Z454),1,IF(lenb(SUBSTITUTE($Z454,W$1&" (2)",""))<lenb($Z454),2,IF(lenb(SUBSTITUTE($Z454,W$1&" (3)",""))<lenb($Z454),3,IF(lenb(SUBSTITUTE($Z454,W$1&" (4)",""))<lenb($Z454),4,IF(lenb(SUBSTITUTE($Z454,W$1&" (5)",""))<lenb($Z454),5,IF(lenb(SUBSTITUTE($Z454,W$1&" (6)",""))<lenb($Z454),6,IF(lenb(SUBSTITUTE($Z454,W$1&" (7)",""))<lenb($Z454),1,IF(lenb(SUBSTITUTE($Z454,W$1&" (8)",""))<lenb($Z454),8,IF(lenb(SUBSTITUTE($Z454,W$1&" (9)",""))<lenb($Z454),9,IF(lenb(SUBSTITUTE($Z454,W$1&" (10)",""))<lenb($Z454),10,IF(lenb(SUBSTITUTE($Z454,W$1,""))<lenb($Z454),"ERROR",IF($Z454=$Y$1,"-",0)))))))))))) -> 0 | X454: =IF(lenb(SUBSTITUTE($Z454,X$1&" (1)",""))<lenb($Z454),1,IF(lenb(SUBSTITUTE($Z454,X$1&" (2)",""))<lenb($Z454),2,IF(lenb(SUBSTITUTE($Z454,X$1&" (3)",""))<lenb($Z454),3,IF(lenb(SUBSTITUTE($Z454,X$1&" (4)",""))<lenb($Z454),4,IF(lenb(SUBSTITUTE($Z454,X$1&" (5)",""))<lenb($Z454),5,IF(lenb(SUBSTITUTE($Z454,X$1&" (6)",""))<lenb($Z454),6,IF(lenb(SUBSTITUTE($Z454,X$1&" (7)",""))<lenb($Z454),1,IF(lenb(SUBSTITUTE($Z454,X$1&" (8)",""))<lenb($Z454),8,IF(lenb(SUBSTITUTE($Z454,X$1&" (9)",""))<lenb($Z454),9,IF(lenb(SUBSTITUTE($Z454,X$1&" (10)",""))<lenb($Z454),10,IF(lenb(SUBSTITUTE($Z454,X$1,""))<lenb($Z454),"ERROR",IF($Z454=$Y$1,"-",0)))))))))))) -> 0 | Y454: =IF(Z454=Y$1,1,"-") -> - | Z454: Publicly Available (1) | AA454: =ifs(U454="","",U454="-",0,U454="Erro",0,U454<>"",LEN(U454)-LEN(SUBSTITUTE(U454,CHAR(10),""))+1) -> 1 | AB454: =COUNTIFS(Links!B:B,"FSE",Links!C:C,A454,Links!AD:AD,1) -> 0 | AC454: Yes | AD454: Yes | AE454: Due to confidentially reasons, we cannot provide all of our data, for example, on the interview results and the transcripts. Still, we described our methodology in detail and provide a dataset with all artifacts that allow other researchers to replicate our study. | AF454: Barriers (Confidentiality and privacy) | AG454: ---- | AH454: ---- | AI454: =IF(AH454="----",IF(AG454="----",IF(AF454="----","----",AF454),AF454&CHAR(10)&AG454),AF454&CHAR(10)&AG454&CHAR(10)&AH454) -> Barriers (Confidentiality and privacy) | AJ454: =IFERROR( IF(AND(K454="Yes",AD454="No"),"Paper has link but no statement", IF(AND(K454="No",AD454="No"),"Paper has no link and no statement", IF(AND(K454="Yes",AD454="Yes"),"Paper has link and statement", IF(AND(K454="No",AD454="Yes"),"Paper has no link but has statement","")))),"") -> Paper has link and statement | AK454: 26-29/08/2024 | AL454: Research Papers | AM454: ="[FP"&TEXT(A454,"0000")&"]" -> [FP0360]
A455: 361 | B455: An empirical study of bots in software development: characteristics and challenges from a practitioner’s perspective | C455: 2020 | D455: Yes | E455: Yes | F455: Yes | G455: No | H455: No | I455: No | J455: - | K455: Yes | L455: No | M455: Yes | N455: No | O455: No | P455: No | Q455: No | R455: Yes | S455: 3 STUDY METHODOLOGY ... Interview guide, survey materials, and analysis scripts can be found in the replication package of the study [9]. | T455: https://doi.org/10.5281/zenodo.4022892 | U455: https://doi.org/10.5281/zenodo.4022892 | V455: =IF(lenb(SUBSTITUTE($Z455,V$1&" (1)",""))<lenb($Z455),1, IF(lenb(SUBSTITUTE($Z455,V$1&" (2)",""))<lenb($Z455),2, IF(lenb(SUBSTITUTE($Z455,V$1&" (3)",""))<lenb($Z455),3, IF(lenb(SUBSTITUTE($Z455,V$1&" (4)",""))<lenb($Z455),4, IF(lenb(SUBSTITUTE($Z455,V$1&" (5)",""))<lenb($Z455),5, IF(lenb(SUBSTITUTE($Z455,V$1&" (6)",""))<lenb($Z455),6, IF(lenb(SUBSTITUTE($Z455,V$1&" (7)",""))<lenb($Z455),1, IF(lenb(SUBSTITUTE($Z455,V$1&" (8)",""))<lenb($Z455),8, IF(lenb(SUBSTITUTE($Z455,V$1&" (9)",""))<lenb($Z455),9, IF(lenb(SUBSTITUTE($Z455,V$1&" (10)",""))<lenb($Z455),10, IF(lenb(SUBSTITUTE($Z455,V$1&" (26)",""))<lenb($Z455),26, IF(lenb(SUBSTITUTE($Z455,V$1,""))<lenb($Z455),"ERROR", IF($Z455=$Y$1,"-",0))))))))))))) -> 1 | W455: =IF(lenb(SUBSTITUTE($Z455,W$1&" (1)",""))<lenb($Z455),1,IF(lenb(SUBSTITUTE($Z455,W$1&" (2)",""))<lenb($Z455),2,IF(lenb(SUBSTITUTE($Z455,W$1&" (3)",""))<lenb($Z455),3,IF(lenb(SUBSTITUTE($Z455,W$1&" (4)",""))<lenb($Z455),4,IF(lenb(SUBSTITUTE($Z455,W$1&" (5)",""))<lenb($Z455),5,IF(lenb(SUBSTITUTE($Z455,W$1&" (6)",""))<lenb($Z455),6,IF(lenb(SUBSTITUTE($Z455,W$1&" (7)",""))<lenb($Z455),1,IF(lenb(SUBSTITUTE($Z455,W$1&" (8)",""))<lenb($Z455),8,IF(lenb(SUBSTITUTE($Z455,W$1&" (9)",""))<lenb($Z455),9,IF(lenb(SUBSTITUTE($Z455,W$1&" (10)",""))<lenb($Z455),10,IF(lenb(SUBSTITUTE($Z455,W$1,""))<lenb($Z455),"ERROR",IF($Z455=$Y$1,"-",0)))))))))))) -> 0 | X455: =IF(lenb(SUBSTITUTE($Z455,X$1&" (1)",""))<lenb($Z455),1,IF(lenb(SUBSTITUTE($Z455,X$1&" (2)",""))<lenb($Z455),2,IF(lenb(SUBSTITUTE($Z455,X$1&" (3)",""))<lenb($Z455),3,IF(lenb(SUBSTITUTE($Z455,X$1&" (4)",""))<lenb($Z455),4,IF(lenb(SUBSTITUTE($Z455,X$1&" (5)",""))<lenb($Z455),5,IF(lenb(SUBSTITUTE($Z455,X$1&" (6)",""))<lenb($Z455),6,IF(lenb(SUBSTITUTE($Z455,X$1&" (7)",""))<lenb($Z455),1,IF(lenb(SUBSTITUTE($Z455,X$1&" (8)",""))<lenb($Z455),8,IF(lenb(SUBSTITUTE($Z455,X$1&" (9)",""))<lenb($Z455),9,IF(lenb(SUBSTITUTE($Z455,X$1&" (10)",""))<lenb($Z455),10,IF(lenb(SUBSTITUTE($Z455,X$1,""))<lenb($Z455),"ERROR",IF($Z455=$Y$1,"-",0)))))))))))) -> 0 | Y455: =IF(Z455=Y$1,1,"-") -> - | Z455: Publicly Available (1) | AA455: =ifs(U455="","",U455="-",0,U455="Erro",0,U455<>"",LEN(U455)-LEN(SUBSTITUTE(U455,CHAR(10),""))+1) -> 1 | AB455: =COUNTIFS(Links!B:B,"FSE",Links!C:C,A455,Links!AD:AD,1) -> 0 | AC455: Yes | AD455: Yes | AE455: The replication package does not contain interview transcripts to preserve participant privacy. | AF455: Barriers (Confidentiality and privacy) | AG455: ---- | AH455: ---- | AI455: =IF(AH455="----",IF(AG455="----",IF(AF455="----","----",AF455),AF455&CHAR(10)&AG455),AF455&CHAR(10)&AG455&CHAR(10)&AH455) -> Barriers (Confidentiality and privacy) | AJ455: =IFERROR( IF(AND(K455="Yes",AD455="No"),"Paper has link but no statement", IF(AND(K455="No",AD455="No"),"Paper has no link and no statement", IF(AND(K455="Yes",AD455="Yes"),"Paper has link and statement", IF(AND(K455="No",AD455="Yes"),"Paper has no link but has statement","")))),"") -> Paper has link and statement | AK455: 26-29/08/2024 | AL455: Research Papers | AM455: ="[FP"&TEXT(A455,"0000")&"]" -> [FP0361]
A456: 362 | B456: Biases and differences in code review using medical imaging and eye-tracking: genders, humans, and machines | C456: 2020 | D456: No | E456: - | F456: - | G456: - | H456: - | I456: - | J456: - | K456: Yes | L456: No | M456: No | N456: No | O456: No | P456: No | Q456: No | R456: Yes | S456: 3 EXPERIMENTAL METHODOLOGY ... All of our de-identified data are available at https://web.eecs. umich.edu/~weimerw/fmri.html. | T456: https://web.eecs.umich.edu/~weimerw/fmri.html | U456: https://web.eecs.umich.edu/~weimerw/fmri.html | V456: =IF(lenb(SUBSTITUTE($Z456,V$1&" (1)",""))<lenb($Z456),1, IF(lenb(SUBSTITUTE($Z456,V$1&" (2)",""))<lenb($Z456),2, IF(lenb(SUBSTITUTE($Z456,V$1&" (3)",""))<lenb($Z456),3, IF(lenb(SUBSTITUTE($Z456,V$1&" (4)",""))<lenb($Z456),4, IF(lenb(SUBSTITUTE($Z456,V$1&" (5)",""))<lenb($Z456),5, IF(lenb(SUBSTITUTE($Z456,V$1&" (6)",""))<lenb($Z456),6, IF(lenb(SUBSTITUTE($Z456,V$1&" (7)",""))<lenb($Z456),1, IF(lenb(SUBSTITUTE($Z456,V$1&" (8)",""))<lenb($Z456),8, IF(lenb(SUBSTITUTE($Z456,V$1&" (9)",""))<lenb($Z456),9, IF(lenb(SUBSTITUTE($Z456,V$1&" (10)",""))<lenb($Z456),10, IF(lenb(SUBSTITUTE($Z456,V$1&" (26)",""))<lenb($Z456),26, IF(lenb(SUBSTITUTE($Z456,V$1,""))<lenb($Z456),"ERROR", IF($Z456=$Y$1,"-",0))))))))))))) -> 1 | W456: =IF(lenb(SUBSTITUTE($Z456,W$1&" (1)",""))<lenb($Z456),1,IF(lenb(SUBSTITUTE($Z456,W$1&" (2)",""))<lenb($Z456),2,IF(lenb(SUBSTITUTE($Z456,W$1&" (3)",""))<lenb($Z456),3,IF(lenb(SUBSTITUTE($Z456,W$1&" (4)",""))<lenb($Z456),4,IF(lenb(SUBSTITUTE($Z456,W$1&" (5)",""))<lenb($Z456),5,IF(lenb(SUBSTITUTE($Z456,W$1&" (6)",""))<lenb($Z456),6,IF(lenb(SUBSTITUTE($Z456,W$1&" (7)",""))<lenb($Z456),1,IF(lenb(SUBSTITUTE($Z456,W$1&" (8)",""))<lenb($Z456),8,IF(lenb(SUBSTITUTE($Z456,W$1&" (9)",""))<lenb($Z456),9,IF(lenb(SUBSTITUTE($Z456,W$1&" (10)",""))<lenb($Z456),10,IF(lenb(SUBSTITUTE($Z456,W$1,""))<lenb($Z456),"ERROR",IF($Z456=$Y$1,"-",0)))))))))))) -> 0 | X456: =IF(lenb(SUBSTITUTE($Z456,X$1&" (1)",""))<lenb($Z456),1,IF(lenb(SUBSTITUTE($Z456,X$1&" (2)",""))<lenb($Z456),2,IF(lenb(SUBSTITUTE($Z456,X$1&" (3)",""))<lenb($Z456),3,IF(lenb(SUBSTITUTE($Z456,X$1&" (4)",""))<lenb($Z456),4,IF(lenb(SUBSTITUTE($Z456,X$1&" (5)",""))<lenb($Z456),5,IF(lenb(SUBSTITUTE($Z456,X$1&" (6)",""))<lenb($Z456),6,IF(lenb(SUBSTITUTE($Z456,X$1&" (7)",""))<lenb($Z456),1,IF(lenb(SUBSTITUTE($Z456,X$1&" (8)",""))<lenb($Z456),8,IF(lenb(SUBSTITUTE($Z456,X$1&" (9)",""))<lenb($Z456),9,IF(lenb(SUBSTITUTE($Z456,X$1&" (10)",""))<lenb($Z456),10,IF(lenb(SUBSTITUTE($Z456,X$1,""))<lenb($Z456),"ERROR",IF($Z456=$Y$1,"-",0)))))))))))) -> 0 | Y456: =IF(Z456=Y$1,1,"-") -> - | Z456: Publicly Available (1) | AA456: =ifs(U456="","",U456="-",0,U456="Erro",0,U456<>"",LEN(U456)-LEN(SUBSTITUTE(U456,CHAR(10),""))+1) -> 1 | AB456: =COUNTIFS(Links!B:B,"FSE",Links!C:C,A456,Links!AD:AD,1) -> 1 | AC456: No | AD456: No | AE456: - | AF456: ---- | AG456: ---- | AH456: ---- | AI456: =IF(AH456="----",IF(AG456="----",IF(AF456="----","----",AF456),AF456&CHAR(10)&AG456),AF456&CHAR(10)&AG456&CHAR(10)&AH456) -> ---- | AJ456: =IFERROR( IF(AND(K456="Yes",AD456="No"),"Paper has link but no statement", IF(AND(K456="No",AD456="No"),"Paper has no link and no statement", IF(AND(K456="Yes",AD456="Yes"),"Paper has link and statement", IF(AND(K456="No",AD456="Yes"),"Paper has no link but has statement","")))),"") -> Paper has link but no statement | AK456: 26-29/08/2024 | AL456: Research Papers | AM456: ="[FP"&TEXT(A456,"0000")&"]" -> [FP0362]
A457: 363 | B457: Community expectations for research artifacts and evaluation processes | C457: 2020 | D457: Yes | E457: Yes | F457: Yes | G457: Yes | H457: No | I457: No | J457: - | K457: Yes | L457: Yes | M457: Yes | N457: Yes | O457: No | P457: No | Q457: No | R457: Yes | S457: 2 BACKGROUND AND RELATED WORK ... As this community within the software engineering field was primarily focussing on the use and reuse of datasets it was reliant on the availability of datasets. While artifact evaluation was piloted later in 2011, in 2005 Tim Menzies and Jelber Sayyad started the now discontinued PROMISE repository1 to share research artifacts. 3 EXPECTATIONS IN THE ACM GUIDELINES AND CALLS FOR ARTIFACTS ... 2The corpus of CfAs can be found on our web site https://bhermann.github.io/artifact- survey/ and in our artifact [12]. | T457: https://bhermann.github.io/artifact-survey/ - https://bhermann.github.io/artifact-survey/questionnaire/ https://doi.org/10.5281/zenodo.3951724 | U457: https://bhermann.github.io/artifact-survey/ https://doi.org/10.5281/zenodo.3951724 | V457: =IF(lenb(SUBSTITUTE($Z457,V$1&" (1)",""))<lenb($Z457),1, IF(lenb(SUBSTITUTE($Z457,V$1&" (2)",""))<lenb($Z457),2, IF(lenb(SUBSTITUTE($Z457,V$1&" (3)",""))<lenb($Z457),3, IF(lenb(SUBSTITUTE($Z457,V$1&" (4)",""))<lenb($Z457),4, IF(lenb(SUBSTITUTE($Z457,V$1&" (5)",""))<lenb($Z457),5, IF(lenb(SUBSTITUTE($Z457,V$1&" (6)",""))<lenb($Z457),6, IF(lenb(SUBSTITUTE($Z457,V$1&" (7)",""))<lenb($Z457),1, IF(lenb(SUBSTITUTE($Z457,V$1&" (8)",""))<lenb($Z457),8, IF(lenb(SUBSTITUTE($Z457,V$1&" (9)",""))<lenb($Z457),9, IF(lenb(SUBSTITUTE($Z457,V$1&" (10)",""))<lenb($Z457),10, IF(lenb(SUBSTITUTE($Z457,V$1&" (26)",""))<lenb($Z457),26, IF(lenb(SUBSTITUTE($Z457,V$1,""))<lenb($Z457),"ERROR", IF($Z457=$Y$1,"-",0))))))))))))) -> 2 | W457: =IF(lenb(SUBSTITUTE($Z457,W$1&" (1)",""))<lenb($Z457),1,IF(lenb(SUBSTITUTE($Z457,W$1&" (2)",""))<lenb($Z457),2,IF(lenb(SUBSTITUTE($Z457,W$1&" (3)",""))<lenb($Z457),3,IF(lenb(SUBSTITUTE($Z457,W$1&" (4)",""))<lenb($Z457),4,IF(lenb(SUBSTITUTE($Z457,W$1&" (5)",""))<lenb($Z457),5,IF(lenb(SUBSTITUTE($Z457,W$1&" (6)",""))<lenb($Z457),6,IF(lenb(SUBSTITUTE($Z457,W$1&" (7)",""))<lenb($Z457),1,IF(lenb(SUBSTITUTE($Z457,W$1&" (8)",""))<lenb($Z457),8,IF(lenb(SUBSTITUTE($Z457,W$1&" (9)",""))<lenb($Z457),9,IF(lenb(SUBSTITUTE($Z457,W$1&" (10)",""))<lenb($Z457),10,IF(lenb(SUBSTITUTE($Z457,W$1,""))<lenb($Z457),"ERROR",IF($Z457=$Y$1,"-",0)))))))))))) -> 0 | X457: =IF(lenb(SUBSTITUTE($Z457,X$1&" (1)",""))<lenb($Z457),1,IF(lenb(SUBSTITUTE($Z457,X$1&" (2)",""))<lenb($Z457),2,IF(lenb(SUBSTITUTE($Z457,X$1&" (3)",""))<lenb($Z457),3,IF(lenb(SUBSTITUTE($Z457,X$1&" (4)",""))<lenb($Z457),4,IF(lenb(SUBSTITUTE($Z457,X$1&" (5)",""))<lenb($Z457),5,IF(lenb(SUBSTITUTE($Z457,X$1&" (6)",""))<lenb($Z457),6,IF(lenb(SUBSTITUTE($Z457,X$1&" (7)",""))<lenb($Z457),1,IF(lenb(SUBSTITUTE($Z457,X$1&" (8)",""))<lenb($Z457),8,IF(lenb(SUBSTITUTE($Z457,X$1&" (9)",""))<lenb($Z457),9,IF(lenb(SUBSTITUTE($Z457,X$1&" (10)",""))<lenb($Z457),10,IF(lenb(SUBSTITUTE($Z457,X$1,""))<lenb($Z457),"ERROR",IF($Z457=$Y$1,"-",0)))))))))))) -> 0 | Y457: =IF(Z457=Y$1,1,"-") -> - | Z457: Publicly Available (2) | AA457: =ifs(U457="","",U457="-",0,U457="Erro",0,U457<>"",LEN(U457)-LEN(SUBSTITUTE(U457,CHAR(10),""))+1) -> 2 | AB457: =COUNTIFS(Links!B:B,"FSE",Links!C:C,A457,Links!AD:AD,1) -> 0 | AC457: Yes | AD457: No | AE457: - | AF457: ---- | AG457: ---- | AH457: ---- | AI457: =IF(AH457="----",IF(AG457="----",IF(AF457="----","----",AF457),AF457&CHAR(10)&AG457),AF457&CHAR(10)&AG457&CHAR(10)&AH457) -> ---- | AJ457: =IFERROR( IF(AND(K457="Yes",AD457="No"),"Paper has link but no statement", IF(AND(K457="No",AD457="No"),"Paper has no link and no statement", IF(AND(K457="Yes",AD457="Yes"),"Paper has link and statement", IF(AND(K457="No",AD457="Yes"),"Paper has no link but has statement","")))),"") -> Paper has link but no statement | AK457: 26-29/08/2024 | AL457: Research Papers | AM457: ="[FP"&TEXT(A457,"0000")&"]" -> [FP0363]
A458: 364 | B458: Does stress impact technical interview performance? | C458: 2020 | D458: No | E458: - | F458: - | G458: - | H458: - | I458: - | J458: - | K458: Yes | L458: Yes | M458: No | N458: No | O458: No | P458: No | Q458: No | R458: Yes | S458: 2.3 Procedure ... 2.3.4 Eyetracking Data. For each participant and task, we collected screen recordings in video format (at 30 frames per second) and a time-indexed data file containing all eye movements and measure- ments recorded by the eye-tracking instrument.2 | T458: https://go.ncsu.edu/technical_interviews (real link: https://drive.google.com/drive/folders/1HeZY-bg6fLhgPF4xL2EQvl9FQZLIkWau ) | U458: https://go.ncsu.edu/technical_interviews | V458: =IF(lenb(SUBSTITUTE($Z458,V$1&" (1)",""))<lenb($Z458),1, IF(lenb(SUBSTITUTE($Z458,V$1&" (2)",""))<lenb($Z458),2, IF(lenb(SUBSTITUTE($Z458,V$1&" (3)",""))<lenb($Z458),3, IF(lenb(SUBSTITUTE($Z458,V$1&" (4)",""))<lenb($Z458),4, IF(lenb(SUBSTITUTE($Z458,V$1&" (5)",""))<lenb($Z458),5, IF(lenb(SUBSTITUTE($Z458,V$1&" (6)",""))<lenb($Z458),6, IF(lenb(SUBSTITUTE($Z458,V$1&" (7)",""))<lenb($Z458),1, IF(lenb(SUBSTITUTE($Z458,V$1&" (8)",""))<lenb($Z458),8, IF(lenb(SUBSTITUTE($Z458,V$1&" (9)",""))<lenb($Z458),9, IF(lenb(SUBSTITUTE($Z458,V$1&" (10)",""))<lenb($Z458),10, IF(lenb(SUBSTITUTE($Z458,V$1&" (26)",""))<lenb($Z458),26, IF(lenb(SUBSTITUTE($Z458,V$1,""))<lenb($Z458),"ERROR", IF($Z458=$Y$1,"-",0))))))))))))) -> 0 | W458: =IF(lenb(SUBSTITUTE($Z458,W$1&" (1)",""))<lenb($Z458),1,IF(lenb(SUBSTITUTE($Z458,W$1&" (2)",""))<lenb($Z458),2,IF(lenb(SUBSTITUTE($Z458,W$1&" (3)",""))<lenb($Z458),3,IF(lenb(SUBSTITUTE($Z458,W$1&" (4)",""))<lenb($Z458),4,IF(lenb(SUBSTITUTE($Z458,W$1&" (5)",""))<lenb($Z458),5,IF(lenb(SUBSTITUTE($Z458,W$1&" (6)",""))<lenb($Z458),6,IF(lenb(SUBSTITUTE($Z458,W$1&" (7)",""))<lenb($Z458),1,IF(lenb(SUBSTITUTE($Z458,W$1&" (8)",""))<lenb($Z458),8,IF(lenb(SUBSTITUTE($Z458,W$1&" (9)",""))<lenb($Z458),9,IF(lenb(SUBSTITUTE($Z458,W$1&" (10)",""))<lenb($Z458),10,IF(lenb(SUBSTITUTE($Z458,W$1,""))<lenb($Z458),"ERROR",IF($Z458=$Y$1,"-",0)))))))))))) -> 1 | X458: =IF(lenb(SUBSTITUTE($Z458,X$1&" (1)",""))<lenb($Z458),1,IF(lenb(SUBSTITUTE($Z458,X$1&" (2)",""))<lenb($Z458),2,IF(lenb(SUBSTITUTE($Z458,X$1&" (3)",""))<lenb($Z458),3,IF(lenb(SUBSTITUTE($Z458,X$1&" (4)",""))<lenb($Z458),4,IF(lenb(SUBSTITUTE($Z458,X$1&" (5)",""))<lenb($Z458),5,IF(lenb(SUBSTITUTE($Z458,X$1&" (6)",""))<lenb($Z458),6,IF(lenb(SUBSTITUTE($Z458,X$1&" (7)",""))<lenb($Z458),1,IF(lenb(SUBSTITUTE($Z458,X$1&" (8)",""))<lenb($Z458),8,IF(lenb(SUBSTITUTE($Z458,X$1&" (9)",""))<lenb($Z458),9,IF(lenb(SUBSTITUTE($Z458,X$1&" (10)",""))<lenb($Z458),10,IF(lenb(SUBSTITUTE($Z458,X$1,""))<lenb($Z458),"ERROR",IF($Z458=$Y$1,"-",0)))))))))))) -> 0 | Y458: =IF(Z458=Y$1,1,"-") -> - | Z458: Not Available (1) | AA458: =ifs(U458="","",U458="-",0,U458="Erro",0,U458<>"",LEN(U458)-LEN(SUBSTITUTE(U458,CHAR(10),""))+1) -> 1 | AB458: =COUNTIFS(Links!B:B,"FSE",Links!C:C,A458,Links!AD:AD,1) -> 0 | AC458: No | AD458: No | AE458: - | AF458: ---- | AG458: ---- | AH458: ---- | AI458: =IF(AH458="----",IF(AG458="----",IF(AF458="----","----",AF458),AF458&CHAR(10)&AG458),AF458&CHAR(10)&AG458&CHAR(10)&AH458) -> ---- | AJ458: =IFERROR( IF(AND(K458="Yes",AD458="No"),"Paper has link but no statement", IF(AND(K458="No",AD458="No"),"Paper has no link and no statement", IF(AND(K458="Yes",AD458="Yes"),"Paper has link and statement", IF(AND(K458="No",AD458="Yes"),"Paper has no link but has statement","")))),"") -> Paper has link but no statement | AK458: 26-29/08/2024 | AL458: Research Papers | AM458: ="[FP"&TEXT(A458,"0000")&"]" -> [FP0364]
A459: 365 | B459: Exploring the evolution of software practices | C459: 2020 | D459: No | E459: - | F459: - | G459: - | H459: - | I459: - | J459: - | K459: No | L459: - | M459: - | N459: - | O459: - | P459: - | Q459: - | R459: - | S459: ---- | T459: - | U459: - | V459: =IF(lenb(SUBSTITUTE($Z459,V$1&" (1)",""))<lenb($Z459),1, IF(lenb(SUBSTITUTE($Z459,V$1&" (2)",""))<lenb($Z459),2, IF(lenb(SUBSTITUTE($Z459,V$1&" (3)",""))<lenb($Z459),3, IF(lenb(SUBSTITUTE($Z459,V$1&" (4)",""))<lenb($Z459),4, IF(lenb(SUBSTITUTE($Z459,V$1&" (5)",""))<lenb($Z459),5, IF(lenb(SUBSTITUTE($Z459,V$1&" (6)",""))<lenb($Z459),6, IF(lenb(SUBSTITUTE($Z459,V$1&" (7)",""))<lenb($Z459),1, IF(lenb(SUBSTITUTE($Z459,V$1&" (8)",""))<lenb($Z459),8, IF(lenb(SUBSTITUTE($Z459,V$1&" (9)",""))<lenb($Z459),9, IF(lenb(SUBSTITUTE($Z459,V$1&" (10)",""))<lenb($Z459),10, IF(lenb(SUBSTITUTE($Z459,V$1&" (26)",""))<lenb($Z459),26, IF(lenb(SUBSTITUTE($Z459,V$1,""))<lenb($Z459),"ERROR", IF($Z459=$Y$1,"-",0))))))))))))) -> - | W459: =IF(lenb(SUBSTITUTE($Z459,W$1&" (1)",""))<lenb($Z459),1,IF(lenb(SUBSTITUTE($Z459,W$1&" (2)",""))<lenb($Z459),2,IF(lenb(SUBSTITUTE($Z459,W$1&" (3)",""))<lenb($Z459),3,IF(lenb(SUBSTITUTE($Z459,W$1&" (4)",""))<lenb($Z459),4,IF(lenb(SUBSTITUTE($Z459,W$1&" (5)",""))<lenb($Z459),5,IF(lenb(SUBSTITUTE($Z459,W$1&" (6)",""))<lenb($Z459),6,IF(lenb(SUBSTITUTE($Z459,W$1&" (7)",""))<lenb($Z459),1,IF(lenb(SUBSTITUTE($Z459,W$1&" (8)",""))<lenb($Z459),8,IF(lenb(SUBSTITUTE($Z459,W$1&" (9)",""))<lenb($Z459),9,IF(lenb(SUBSTITUTE($Z459,W$1&" (10)",""))<lenb($Z459),10,IF(lenb(SUBSTITUTE($Z459,W$1,""))<lenb($Z459),"ERROR",IF($Z459=$Y$1,"-",0)))))))))))) -> - | X459: =IF(lenb(SUBSTITUTE($Z459,X$1&" (1)",""))<lenb($Z459),1,IF(lenb(SUBSTITUTE($Z459,X$1&" (2)",""))<lenb($Z459),2,IF(lenb(SUBSTITUTE($Z459,X$1&" (3)",""))<lenb($Z459),3,IF(lenb(SUBSTITUTE($Z459,X$1&" (4)",""))<lenb($Z459),4,IF(lenb(SUBSTITUTE($Z459,X$1&" (5)",""))<lenb($Z459),5,IF(lenb(SUBSTITUTE($Z459,X$1&" (6)",""))<lenb($Z459),6,IF(lenb(SUBSTITUTE($Z459,X$1&" (7)",""))<lenb($Z459),1,IF(lenb(SUBSTITUTE($Z459,X$1&" (8)",""))<lenb($Z459),8,IF(lenb(SUBSTITUTE($Z459,X$1&" (9)",""))<lenb($Z459),9,IF(lenb(SUBSTITUTE($Z459,X$1&" (10)",""))<lenb($Z459),10,IF(lenb(SUBSTITUTE($Z459,X$1,""))<lenb($Z459),"ERROR",IF($Z459=$Y$1,"-",0)))))))))))) -> - | Y459: =IF(Z459=Y$1,1,"-") -> 1 | Z459: No links | AA459: =ifs(U459="","",U459="-",0,U459="Erro",0,U459<>"",LEN(U459)-LEN(SUBSTITUTE(U459,CHAR(10),""))+1) -> 0 | AB459: =COUNTIFS(Links!B:B,"FSE",Links!C:C,A459,Links!AD:AD,1) -> 0 | AC459: - | AD459: No | AE459: - | AF459: ---- | AG459: ---- | AH459: ---- | AI459: =IF(AH459="----",IF(AG459="----",IF(AF459="----","----",AF459),AF459&CHAR(10)&AG459),AF459&CHAR(10)&AG459&CHAR(10)&AH459) -> ---- | AJ459: =IFERROR( IF(AND(K459="Yes",AD459="No"),"Paper has link but no statement", IF(AND(K459="No",AD459="No"),"Paper has no link and no statement", IF(AND(K459="Yes",AD459="Yes"),"Paper has link and statement", IF(AND(K459="No",AD459="Yes"),"Paper has no link but has statement","")))),"") -> Paper has no link and no statement | AK459: 26-29/08/2024 | AL459: Research Papers | AM459: ="[FP"&TEXT(A459,"0000")&"]" -> [FP0365]
... A841: 127 | B841: Distinguishing Look-Alike Innocent and Vulnerable Code by Subtle Semantic Representation Learning and Explanation | C841: 2023 | D841: No | E841: - | F841: - | G841: - | H841: - | I841: - | J841: - | K841: Yes | L841: No | M841: Yes | N841: No | O841: No | P841: No | Q841: Yes | R841: No | S841: Section: Data Availability | T841: https://github.com/jacknichao/SVulD | U841: https://github.com/jacknichao/SVulD | V841: =IF(lenb(SUBSTITUTE($Z841,V$1&" (1)",""))<lenb($Z841),1, IF(lenb(SUBSTITUTE($Z841,V$1&" (2)",""))<lenb($Z841),2, IF(lenb(SUBSTITUTE($Z841,V$1&" (3)",""))<lenb($Z841),3, IF(lenb(SUBSTITUTE($Z841,V$1&" (4)",""))<lenb($Z841),4, IF(lenb(SUBSTITUTE($Z841,V$1&" (5)",""))<lenb($Z841),5, IF(lenb(SUBSTITUTE($Z841,V$1&" (6)",""))<lenb($Z841),6, IF(lenb(SUBSTITUTE($Z841,V$1&" (7)",""))<lenb($Z841),1, IF(lenb(SUBSTITUTE($Z841,V$1&" (8)",""))<lenb($Z841),8, IF(lenb(SUBSTITUTE($Z841,V$1&" (9)",""))<lenb($Z841),9, IF(lenb(SUBSTITUTE($Z841,V$1&" (10)",""))<lenb($Z841),10, IF(lenb(SUBSTITUTE($Z841,V$1&" (26)",""))<lenb($Z841),26, IF(lenb(SUBSTITUTE($Z841,V$1,""))<lenb($Z841),"ERROR", IF($Z841=$Y$1,"-",0))))))))))))) -> 1 | W841: =IF(lenb(SUBSTITUTE($Z841,W$1&" (1)",""))<lenb($Z841),1,IF(lenb(SUBSTITUTE($Z841,W$1&" (2)",""))<lenb($Z841),2,IF(lenb(SUBSTITUTE($Z841,W$1&" (3)",""))<lenb($Z841),3,IF(lenb(SUBSTITUTE($Z841,W$1&" (4)",""))<lenb($Z841),4,IF(lenb(SUBSTITUTE($Z841,W$1&" (5)",""))<lenb($Z841),5,IF(lenb(SUBSTITUTE($Z841,W$1&" (6)",""))<lenb($Z841),6,IF(lenb(SUBSTITUTE($Z841,W$1&" (7)",""))<lenb($Z841),1,IF(lenb(SUBSTITUTE($Z841,W$1&" (8)",""))<lenb($Z841),8,IF(lenb(SUBSTITUTE($Z841,W$1&" (9)",""))<lenb($Z841),9,IF(lenb(SUBSTITUTE($Z841,W$1&" (10)",""))<lenb($Z841),10,IF(lenb(SUBSTITUTE($Z841,W$1,""))<lenb($Z841),"ERROR",IF($Z841=$Y$1,"-",0)))))))))))) -> 0 | X841: =IF(lenb(SUBSTITUTE($Z841,X$1&" (1)",""))<lenb($Z841),1,IF(lenb(SUBSTITUTE($Z841,X$1&" (2)",""))<lenb($Z841),2,IF(lenb(SUBSTITUTE($Z841,X$1&" (3)",""))<lenb($Z841),3,IF(lenb(SUBSTITUTE($Z841,X$1&" (4)",""))<lenb($Z841),4,IF(lenb(SUBSTITUTE($Z841,X$1&" (5)",""))<lenb($Z841),5,IF(lenb(SUBSTITUTE($Z841,X$1&" (6)",""))<lenb($Z841),6,IF(lenb(SUBSTITUTE($Z841,X$1&" (7)",""))<lenb($Z841),1,IF(lenb(SUBSTITUTE($Z841,X$1&" (8)",""))<lenb($Z841),8,IF(lenb(SUBSTITUTE($Z841,X$1&" (9)",""))<lenb($Z841),9,IF(lenb(SUBSTITUTE($Z841,X$1&" (10)",""))<lenb($Z841),10,IF(lenb(SUBSTITUTE($Z841,X$1,""))<lenb($Z841),"ERROR",IF($Z841=$Y$1,"-",0)))))))))))) -> 0 | Y841: =IF(Z841=Y$1,1,"-") -> - | Z841: Publicly Available (1) | AA841: =ifs(U841="","",U841="-",0,U841="Erro",0,U841<>"",LEN(U841)-LEN(SUBSTITUTE(U841,CHAR(10),""))+1) -> 1 | AB841: =COUNTIFS(Links!B:B,"FSE",Links!C:C,A841,Links!AD:AD,1) -> 0 | AC841: No | AD841: No | AE841: - | AF841: ---- | AG841: ---- | AH841: ---- | AI841: =IF(AH841="----",IF(AG841="----",IF(AF841="----","----",AF841),AF841&CHAR(10)&AG841),AF841&CHAR(10)&AG841&CHAR(10)&AH841) -> ---- | AJ841: =IFERROR( IF(AND(K841="Yes",AD841="No"),"Paper has link but no statement", IF(AND(K841="No",AD841="No"),"Paper has no link and no statement", IF(AND(K841="Yes",AD841="Yes"),"Paper has link and statement", IF(AND(K841="No",AD841="Yes"),"Paper has no link but has statement","")))),"") -> Paper has link but no statement | AK841: 26-29/08/2024 | AL841: Research Papers | AM841: ="[FP"&TEXT(A841,"0000")&"]" -> [FP0127]

Sheet PapersOverview
A1: *Total= ICSE+FSE | B1: # of papers | F1: # of paper wit at least one link | J1: % of artifact sharing | N1: # of badged of papers | R1: % of badged papers | V1: # of papers with not available links | Z1: % of papers with not available links
A2: Year | B2: ICSE | C2: FSE | D2: Total* | F2: ICSE | G2: FSE | H2: Total* | J2: ICSE | K2: FSE | L2: Total* | N2: ICSE | O2: FSE | P2: Total* | R2: ICSE | S2: FSE | T2: Total* | V2: ICSE | W2: FSE | X2: Total* | Z2: ICSE | AA2: FSE | AB2: Total*
A3: 2014 | B3: =COUNTIF(ICSE!C:C,A3) -> 98 | C3: =COUNTIF(FSE!C:C,A3) -> 61 | D3: =SUM(B3,C3) -> 159 | F3: =COUNTIFS(ICSE!C:C,A3,ICSE!K:K,"Yes") -> 62 | G3: =COUNTIFS(FSE!C:C,A3,FSE!K:K,"Yes") -> 35 | H3: =SUM(F3,G3) -> 97 | J3: =TEXT((F3/$B3)*100,"#0.0") -> 63.3 | K3: =TEXT((G3/$C3)*100,"#0.0") -> 57.4 | L3: =TEXT((H3/$D3)*100,"#0.0") -> 61.0 | N3: =COUNTIFS(ICSE!C:C,A3,ICSE!D:D,"Yes") -> 1 | O3: =COUNTIFS(FSE!C:C,A3,FSE!D:D,"Yes") -> 15 | P3: =SUM(N3,O3) -> 16 | R3: =TEXT((N3/$B3)*100,"#0.0") -> 1.0 | S3: =TEXT((O3/$C3)*100,"#0.0") -> 24.6 | T3: =TEXT((P3/$D3)*100,"#0.0") -> 10.1 | V3: =COUNTIFS(ICSE!$C:$C,$A3,ICSE!$W:$W,">0") -> 35 | W3: =COUNTIFS(FSE!$C:$C,$A3,FSE!$W:$W,">0") -> 16 | X3: =SUM(V3,W3) -> 51 | Z3: =TEXT((V3/$F3)*100,"#0.0") -> 56.5 | AA3: =TEXT((W3/$G3)*100,"#0.0") -> 45.7 | AB3: =TEXT((X3/$H3)*100,"#0.0") -> 52.6
A4: 2015 | B4: =COUNTIF(ICSE!C:C,A4) -> 84 | C4: =COUNTIF(FSE!C:C,A4) -> 74 | D4: =SUM(B4,C4) -> 158 | F4: =COUNTIFS(ICSE!C:C,A4,ICSE!K:K,"Yes") -> 49 | G4: =COUNTIFS(FSE!C:C,A4,FSE!K:K,"Yes") -> 48 | H4: =SUM(F4,G4) -> 97 | J4: =TEXT((F4/$B4)*100,"#0.0") -> 58.3 | K4: =TEXT((G4/$C4)*100,"#0.0") -> 64.9 | L4: =TEXT((H4/$D4)*100,"#0.0") -> 61.4 | N4: =COUNTIFS(ICSE!C:C,A4,ICSE!D:D,"Yes") -> 0 | O4: =COUNTIFS(FSE!C:C,A4,FSE!D:D,"Yes") -> 17 | P4: =SUM(N4,O4) -> 17 | R4: =TEXT((N4/$B4)*100,"#0.0") -> 0.0 | S4: =TEXT((O4/$C4)*100,"#0.0") -> 23.0 | T4: =TEXT((P4/$D4)*100,"#0.0") -> 10.8 | V4: =COUNTIFS(ICSE!$C:$C,$A4,ICSE!$W:$W,">0") -> 23 | W4: =COUNTIFS(FSE!$C:$C,$A4,FSE!$W:$W,">0") -> 21 | X4: =SUM(V4,W4) -> 44 | Z4: =TEXT((V4/$F4)*100,"#0.0") -> 46.9 | AA4: =TEXT((W4/$G4)*100,"#0.0") -> 43.8 | AB4: =TEXT((X4/$H4)*100,"#0.0") -> 45.4
A5: 2016 | B5: =COUNTIF(ICSE!C:C,A5) -> 101 | C5: =COUNTIF(FSE!C:C,A5) -> 74 | D5: =SUM(B5,C5) -> 175 | F5: =COUNTIFS(ICSE!C:C,A5,ICSE!K:K,"Yes") -> 70 | G5: =COUNTIFS(FSE!C:C,A5,FSE!K:K,"Yes") -> 54 | H5: =SUM(F5,G5) -> 124 | J5: =TEXT((F5/$B5)*100,"#0.0") -> 69.3 | K5: =TEXT((G5/$C5)*100,"#0.0") -> 73.0 | L5: =TEXT((H5/$D5)*100,"#0.0") -> 70.9 | N5: =COUNTIFS(ICSE!C:C,A5,ICSE!D:D,"Yes") -> 0 | O5: =COUNTIFS(FSE!C:C,A5,FSE!D:D,"Yes") -> 17 | P5: =SUM(N5,O5) -> 17 | R5: =TEXT((N5/$B5)*100,"#0.0") -> 0.0 | S5: =TEXT((O5/$C5)*100,"#0.0") -> 23.0 | T5: =TEXT((P5/$D5)*100,"#0.0") -> 9.7 | V5: =COUNTIFS(ICSE!$C:$C,$A5,ICSE!$W:$W,">0") -> 37 | W5: =COUNTIFS(FSE!$C:$C,$A5,FSE!$W:$W,">0") -> 21 | X5: =SUM(V5,W5) -> 58 | Z5: =TEXT((V5/$F5)*100,"#0.0") -> 52.9 | AA5: =TEXT((W5/$G5)*100,"#0.0") -> 38.9 | AB5: =TEXT((X5/$H5)*100,"#0.0") -> 46.8
A6: 2017 | B6: =COUNTIF(ICSE!C:C,A6) -> 68 | C6: =COUNTIF(FSE!C:C,A6) -> 72 | D6: =SUM(B6,C6) -> 140 | F6: =COUNTIFS(ICSE!C:C,A6,ICSE!K:K,"Yes") -> 56 | G6: =COUNTIFS(FSE!C:C,A6,FSE!K:K,"Yes") -> 53 | H6: =SUM(F6,G6) -> 109 | J6: =TEXT((F6/$B6)*100,"#0.0") -> 82.4 | K6: =TEXT((G6/$C6)*100,"#0.0") -> 73.6 | L6: =TEXT((H6/$D6)*100,"#0.0") -> 77.9 | N6: =COUNTIFS(ICSE!C:C,A6,ICSE!D:D,"Yes") -> 0 | O6: =COUNTIFS(FSE!C:C,A6,FSE!D:D,"Yes") -> 11 | P6: =SUM(N6,O6) -> 11 | R6: =TEXT((N6/$B6)*100,"#0.0") -> 0.0 | S6: =TEXT((O6/$C6)*100,"#0.0") -> 15.3 | T6: =TEXT((P6/$D6)*100,"#0.0") -> 7.9 | V6: =COUNTIFS(ICSE!$C:$C,$A6,ICSE!$W:$W,">0") -> 20 | W6: =COUNTIFS(FSE!$C:$C,$A6,FSE!$W:$W,">0") -> 14 | X6: =SUM(V6,W6) -> 34 | Z6: =TEXT((V6/$F6)*100,"#0.0") -> 35.7 | AA6: =TEXT((W6/$G6)*100,"#0.0") -> 26.4 | AB6: =TEXT((X6/$H6)*100,"#0.0") -> 31.2
A7: 2018 | B7: =COUNTIF(ICSE!C:C,A7) -> 105 | C7: =COUNTIF(FSE!C:C,A7) -> 61 | D7: =SUM(B7,C7) -> 166 | F7: =COUNTIFS(ICSE!C:C,A7,ICSE!K:K,"Yes") -> 83 | G7: =COUNTIFS(FSE!C:C,A7,FSE!K:K,"Yes") -> 51 | H7: =SUM(F7,G7) -> 134 | J7: =TEXT((F7/$B7)*100,"#0.0") -> 79.0 | K7: =TEXT((G7/$C7)*100,"#0.0") -> 83.6 | L7: =TEXT((H7/$D7)*100,"#0.0") -> 80.7 | N7: =COUNTIFS(ICSE!C:C,A7,ICSE!D:D,"Yes") -> 2 | O7: =COUNTIFS(FSE!C:C,A7,FSE!D:D,"Yes") -> 20 | P7: =SUM(N7,O7) -> 22 | R7: =TEXT((N7/$B7)*100,"#0.0") -> 1.9 | S7: =TEXT((O7/$C7)*100,"#0.0") -> 32.8 | T7: =TEXT((P7/$D7)*100,"#0.0") -> 13.3 | V7: =COUNTIFS(ICSE!$C:$C,$A7,ICSE!$W:$W,">0") -> 17 | W7: =COUNTIFS(FSE!$C:$C,$A7,FSE!$W:$W,">0") -> 5 | X7: =SUM(V7,W7) -> 22 | Z7: =TEXT((V7/$F7)*100,"#0.0") -> 20.5 | AA7: =TEXT((W7/$G7)*100,"#0.0") -> 9.8 | AB7: =TEXT((X7/$H7)*100,"#0.0") -> 16.4
A8: 2019 | B8: =COUNTIF(ICSE!C:C,A8) -> 109 | C8: =COUNTIF(FSE!C:C,A8) -> 74 | D8: =SUM(B8,C8) -> 183 | F8: =COUNTIFS(ICSE!C:C,A8,ICSE!K:K,"Yes") -> 79 | G8: =COUNTIFS(FSE!C:C,A8,FSE!K:K,"Yes") -> 62 | H8: =SUM(F8,G8) -> 141 | J8: =TEXT((F8/$B8)*100,"#0.0") -> 72.5 | K8: =TEXT((G8/$C8)*100,"#0.0") -> 83.8 | L8: =TEXT((H8/$D8)*100,"#0.0") -> 77.0 | N8: =COUNTIFS(ICSE!C:C,A8,ICSE!D:D,"Yes") -> 45 | O8: =COUNTIFS(FSE!C:C,A8,FSE!D:D,"Yes") -> 21 | P8: =SUM(N8,O8) -> 66 | R8: =TEXT((N8/$B8)*100,"#0.0") -> 41.3 | S8: =TEXT((O8/$C8)*100,"#0.0") -> 28.4 | T8: =TEXT((P8/$D8)*100,"#0.0") -> 36.1 | V8: =COUNTIFS(ICSE!$C:$C,$A8,ICSE!$W:$W,">0") -> 6 | W8: =COUNTIFS(FSE!$C:$C,$A8,FSE!$W:$W,">0") -> 9 | X8: =SUM(V8,W8) -> 15 | Z8: =TEXT((V8/$F8)*100,"#0.0") -> 7.6 | AA8: =TEXT((W8/$G8)*100,"#0.0") -> 14.5 | AB8: =TEXT((X8/$H8)*100,"#0.0") -> 10.6
A9: 2020 | B9: =COUNTIF(ICSE!C:C,A9) -> 129 | C9: =COUNTIF(FSE!C:C,A9) -> 101 | D9: =SUM(B9,C9) -> 230 | F9: =COUNTIFS(ICSE!C:C,A9,ICSE!K:K,"Yes") -> 106 | G9: =COUNTIFS(FSE!C:C,A9,FSE!K:K,"Yes") -> 91 | H9: =SUM(F9,G9) -> 197 | J9: =TEXT((F9/$B9)*100,"#0.0") -> 82.2 | K9: =TEXT((G9/$C9)*100,"#0.0") -> 90.1 | L9: =TEXT((H9/$D9)*100,"#0.0") -> 85.7 | N9: =COUNTIFS(ICSE!C:C,A9,ICSE!D:D,"Yes") -> 54 | O9: =COUNTIFS(FSE!C:C,A9,FSE!D:D,"Yes") -> 54 | P9: =SUM(N9,O9) -> 108 | R9: =TEXT((N9/$B9)*100,"#0.0") -> 41.9 | S9: =TEXT((O9/$C9)*100,"#0.0") -> 53.5 | T9: =TEXT((P9/$D9)*100,"#0.0") -> 47.0 | V9: =COUNTIFS(ICSE!$C:$C,$A9,ICSE!$W:$W,">0") -> 7 | W9: =COUNTIFS(FSE!$C:$C,$A9,FSE!$W:$W,">0") -> 5 | X9: =SUM(V9,W9) -> 12 | Z9: =TEXT((V9/$F9)*100,"#0.0") -> 6.6 | AA9: =TEXT((W9/$G9)*100,"#0.0") -> 5.5 | AB9: =TEXT((X9/$H9)*100,"#0.0") -> 6.1
A10: 2021 | B10: =COUNTIF(ICSE!C:C,A10) -> 138 | C10: =COUNTIF(FSE!C:C,A10) -> 97 | D10: =SUM(B10,C10) -> 235 | F10: =COUNTIFS(ICSE!C:C,A10,ICSE!K:K,"Yes") -> 120 | G10: =COUNTIFS(FSE!C:C,A10,FSE!K:K,"Yes") -> 85 | H10: =SUM(F10,G10) -> 205 | J10: =TEXT((F10/$B10)*100,"#0.0") -> 87.0 | K10: =TEXT((G10/$C10)*100,"#0.0") -> 87.6 | L10: =TEXT((H10/$D10)*100,"#0.0") -> 87.2 | N10: =COUNTIFS(ICSE!C:C,A10,ICSE!D:D,"Yes") -> 50 | O10: =COUNTIFS(FSE!C:C,A10,FSE!D:D,"Yes") -> 50 | P10: =SUM(N10,O10) -> 100 | R10: =TEXT((N10/$B10)*100,"#0.0") -> 36.2 | S10: =TEXT((O10/$C10)*100,"#0.0") -> 51.5 | T10: =TEXT((P10/$D10)*100,"#0.0") -> 42.6 | V10: =COUNTIFS(ICSE!$C:$C,$A10,ICSE!$W:$W,">0") -> 6 | W10: =COUNTIFS(FSE!$C:$C,$A10,FSE!$W:$W,">0") -> 2 | X10: =SUM(V10,W10) -> 8 | Z10: =TEXT((V10/$F10)*100,"#0.0") -> 5.0 | AA10: =TEXT((W10/$G10)*100,"#0.0") -> 2.4 | AB10: =TEXT((X10/$H10)*100,"#0.0") -> 3.9
A11: 2022 | B11: =COUNTIF(ICSE!C:C,A11) -> 197 | C11: =COUNTIF(FSE!C:C,A11) -> 99 | D11: =SUM(B11,C11) -> 296 | F11: =COUNTIFS(ICSE!C:C,A11,ICSE!K:K,"Yes") -> 176 | G11: =COUNTIFS(FSE!C:C,A11,FSE!K:K,"Yes") -> 91 | H11: =SUM(F11,G11) -> 267 | J11: =TEXT((F11/$B11)*100,"#0.0") -> 89.3 | K11: =TEXT((G11/$C11)*100,"#0.0") -> 91.9 | L11: =TEXT((H11/$D11)*100,"#0.0") -> 90.2 | N11: =COUNTIFS(ICSE!C:C,A11,ICSE!D:D,"Yes") -> 63 | O11: =COUNTIFS(FSE!C:C,A11,FSE!D:D,"Yes") -> 41 | P11: =SUM(N11,O11) -> 104 | R11: =TEXT((N11/$B11)*100,"#0.0") -> 32.0 | S11: =TEXT((O11/$C11)*100,"#0.0") -> 41.4 | T11: =TEXT((P11/$D11)*100,"#0.0") -> 35.1 | V11: =COUNTIFS(ICSE!$C:$C,$A11,ICSE!$W:$W,">0") -> 5 | W11: =COUNTIFS(FSE!$C:$C,$A11,FSE!$W:$W,">0") -> 1 | X11: =SUM(V11,W11) -> 6 | Z11: =TEXT((V11/$F11)*100,"#0.0") -> 2.8 | AA11: =TEXT((W11/$G11)*100,"#0.0") -> 1.1 | AB11: =TEXT((X11/$H11)*100,"#0.0") -> 2.2
A12: 2023 | B12: =COUNTIF(ICSE!C:C,A12) -> 207 | C12: =COUNTIF(FSE!C:C,A12) -> 127 | D12: =SUM(B12,C12) -> 334 | F12: =COUNTIFS(ICSE!C:C,A12,ICSE!K:K,"Yes") -> 200 | G12: =COUNTIFS(FSE!C:C,A12,FSE!K:K,"Yes") -> 125 | H12: =SUM(F12,G12) -> 325 | J12: =TEXT((F12/$B12)*100,"#0.0") -> 96.6 | K12: =TEXT((G12/$C12)*100,"#0.0") -> 98.4 | L12: =TEXT((H12/$D12)*100,"#0.0") -> 97.3 | N12: =COUNTIFS(ICSE!C:C,A12,ICSE!D:D,"Yes") -> 82 | O12: =COUNTIFS(FSE!C:C,A12,FSE!D:D,"Yes") -> 62 | P12: =SUM(N12,O12) -> 144 | R12: =TEXT((N12/$B12)*100,"#0.0") -> 39.6 | S12: =TEXT((O12/$C12)*100,"#0.0") -> 48.8 | T12: =TEXT((P12/$D12)*100,"#0.0") -> 43.1 | V12: =COUNTIFS(ICSE!$C:$C,$A12,ICSE!$W:$W,">0") -> 9 | W12: =COUNTIFS(FSE!$C:$C,$A12,FSE!$W:$W,">0") -> 4 | X12: =SUM(V12,W12) -> 13 | Z12: =TEXT((V12/$F12)*100,"#0.0") -> 4.5 | AA12: =TEXT((W12/$G12)*100,"#0.0") -> 3.2 | AB12: =TEXT((X12/$H12)*100,"#0.0") -> 4.0
A14: Total | B14: =SUM(B3:B12) -> 1236 | C14: =SUM(C3:C12) -> 840 | D14: =SUM(B14,C14) -> 2076 | F14: =SUM(F3:F12) -> 1001 | G14: =SUM(G3:G12) -> 695 | H14: =SUM(F14,G14) -> 1696 | N14: =SUM(N3:N12) -> 297 | O14: =SUM(O3:O12) -> 308 | P14: =SUM(N14,O14) -> 605 | V14: =SUM(V3:V12) -> 165 | W14: =SUM(W3:W12) -> 98 | X14: =SUM(V14,W14) -> 263
A16: Papers in years with AE track | B16: =sum(B8:B12) -> 780 | C16: =SUM(C3:C12) -> 840 | D16: =SUM(B16,C16) -> 1620 | F16: =sum(F8:F12) -> 681 | G16: =SUM(G3:G12) -> 695 | H16: =SUM(F16,G16) -> 1376 | N16: =sum(N8:N12) -> 294 | O16: =SUM(O3:O12) -> 308 | P16: =SUM(N16,O16) -> 602 | V16: =sum(V8:V12) -> 33 | W16: =SUM(W3:W12) -> 98 | X16: =SUM(V16,W16) -> 131
B17: 2019-2023 | C17: 2014-2023 | F17: 2019-2023 | G17: 2014-2023 | N17: 2019-2023 | O17: 2014-2023 | V17: 2019-2023 | W17: 2014-2023

Sheet Links
A1: Links | B1: =COUNTIF(C:C,">0") -> 2171 | D1: Here we considered where the artifact is stored | E1: ="ICSE: "&COUNTIF(B:B,"ICSE")&" links" -> ICSE: 1227 links | F1: ="FSE: "&COUNTIF(B:B,"FSE")&" links" -> FSE: 944 links | H1: =SUM(H3:H2173) -> 328 | I1: =SUM(I3:I2173) -> 93 | J1: =SUM(J3:J2173) -> 27 | K1: =SUM(K3:K2173) -> 5 | L1: =SUM(L3:L2173) -> 1 | M1: =SUM(M3:M2173) -> 7 | N1: =SUM(N3:N2173) -> 6 | O1: =SUM(O3:O2173) -> 1 | ... AY1: =SUM(AY3:AY2173) -> 107 | BA1: =COUNTIF(BA3:BA2173,BA2) -> 468 | BB1: =COUNTIF(BB3:BB2173,BB2) -> 1034 | BC1: =COUNTIF(BC3:BC2173,BC2) -> 172 | BD1: =COUNTIF(BD3:BD2173,BD2) -> 309 | BE1: =COUNTIF(BE3:BE2173,BE2) -> 188
A2: Year | B2: Conference | C2: Paper ID | D2: Link | E2: Status per paper | F2: Status per link | G2: =COUNTIF(G3:G2213,"ERROR") -> 0 | H2: Zenodo | I2: Figshare | J2: arXiv | K2: OSF | L2: archive.org | M2: acm. | N2: SoftwareHeritage | O2: mendeley | P2: GitHub | Q2: GitLab | R2: Bitbucket | S2: Docker. | T2: /Pypi | U2: Crates.io | V2: Drive. | W2: Dropbox | X2: googlecode | Y2: cloud.google | Z2: docs.google | AA2: sites.google | AB2: Youtube | AC2: kaggle | AD2: University | AE2: Microsoft. | AF2: ibm | AG2: researchgate | AH2: Other | AI2: Unique identifier | AJ2: Short link | AK2: bit.ly | AL2: goo.gl | AM2: tinyurl | AN2: tiny.cc | AO2: https://t.ly | AP2: shorturl.at | AQ2: cutt.ly | AR2: youtu.be | AS2: real link | AT2: University domain | AU2: .edu | AV2: Github | AW2: Anonymous. | AX2: doi | AY2: persistent identifier | BA2: Archival | BB2: Code | BC2: General-purpose | BD2: Institutional | BE2: Others | BF2: Category
A3: {=XLOOKUP(C3,ICSE!A:A,ICSE!C:C,,2,1)} -> 2022 | B3: ICSE | C3: 2 | D3: https://github.com/acieroid/wassail/tree/icse2022 | E3: {=XLOOKUP(C3,ICSE!A:A,ICSE!Z:Z,,0,1)} -> Publicly available (2) | F3: Publicly available | G3: {=IF(B3="ICSE",IF(COUNTIFS(B:B,B3,C:C,C3)=XLOOKUP(C3,ICSE!A:A,ICSE!AA:AA,"ERROR",0,1),"OK","ERROR"),IF(B3="FSE",IF(COUNTIFS(B:B,B3,C:C,C3)=XLOOKUP(C3,FSE!A:A,FSE!AA:AA,"ERROR",0,1),"OK","ERROR")))} -> OK | H3: =countif($D3,"*"&H$2&"*") -> 0 | I3: =countif($D3,"*"&I$2&"*") -> 0 | J3: =countif($D3,"*"&J$2&"*") -> 0 | K3: =countif($D3,"*"&K$2&"*") -> 0 | L3: =countif($D3,"*"&L$2&"*") -> 0 | M3: =countif($D3,"*"&M$2&"*") -> 0 | N3: =countif($D3,"*"&N$2&"*") -> 0 | O3: =countif($D3,"*"&O$2&"*") -> 0 | P3: =IF(OR(AV3=1,AW3=1),1,0) -> 1 | Q3: =countif($D3,"*"&Q$2&"*") -> 0 | R3: =countif($D3,"*"&R$2&"*") -> 0 | S3: =countif($D3,"*"&S$2&"*") -> 0 | T3: =countif($D3,"*"&T$2&"*") -> 0 | U3: =countif($D3,"*"&U$2&"*") -> 0 | V3: =countif($D3,"*"&V$2&"*") -> 0 | W3: =countif($D3,"*"&W$2&"*") -> 0 | X3: =countif($D3,"*"&X$2&"*") -> 0 | ... AC3: =countif($D3,"*"&AC$2&"*") -> 0 | AD3: =IF(OR(AT3=1,AU3=1),1,0) -> 0 | AE3: =countif($D3,"*"&AE$2&"*") -> 0 | AF3: =countif($D3,"*"&AF$2&"*") -> 0 | AG3: =countif($D3,"*"&AG$2&"*") -> 0 | AH3: =IF(D3<>"",IF(SUM(H3:AG3,T3)=0,1,0),0) -> 0 | AI3: =IF(OR(AX3=1,AY3=1),1,0) -> 0 | AJ3: =SUM(AK3:AR3) -> 0 | AK3: =countif($D3,"*"&AK$2&"*") -> 0 | AL3: =countif($D3,"*"&AL$2&"*") -> 0 | AM3: =countif($D3,"*"&AM$2&"*") -> 0 | AN3: =countif($D3,"*"&AN$2&"*") -> 0 | AO3: =countif($D3,"*"&AO$2&"*") -> 0 | AP3: =countif($D3,"*"&AP$2&"*") -> 0 | AQ3: =countif($D3,"*"&AQ$2&"*") -> 0 | AR3: =countif($D3,"*"&AR$2&"*") -> 0 | AS3: =countif($D3,"*"&AS$2&"*") -> 0 | AT3: 0 | AU3: =countif($D3,"*"&AU$2&"*") -> 0 | AV3: =countif($D3,"*"&AV$2&"*") -> 1 | AW3: =countif($D3,"*"&AW$2&"*") -> 0 | AX3: =countif($D3,"*"&AX$2&"*") -> 0 | AY3: 0 | BA3: =IF(SUM(H3,I3,J3,K3,L3,M3,N3,O3)>0,BA$2,"") | BB3: =IF(SUM(P3,Q3,R3,S3,T3,U3)<>0,BB$2,"") -> Code | BC3: =IF(SUM(V3:AC3)<>0,BC$2,"") | BD3: =IF(SUM(AE3,AF3,AD3)<>0,BD$2,"") | BE3: =IF(SUM(AH3,AG3)<>0,BE$2,"") | BF3: =CONCATENATE(BA3:BE3) -> Code
A4: {=XLOOKUP(C4,ICSE!A:A,ICSE!C:C,,2,1)} -> 2022 | B4: ICSE | C4: 2 | D4: https://zenodo.org/record/5821007 | E4: {=XLOOKUP(C4,ICSE!A:A,ICSE!Z:Z,,0,1)} -> Publicly available (2) | F4: Publicly available | G4: {=IF(B4="ICSE",IF(COUNTIFS(B:B,B4,C:C,C4)=XLOOKUP(C4,ICSE!A:A,ICSE!AA:AA,"ERROR",0,1),"OK","ERROR"),IF(B4="FSE",IF(COUNTIFS(B:B,B4,C:C,C4)=XLOOKUP(C4,FSE!A:A,FSE!AA:AA,"ERROR",0,1),"OK","ERROR")))} -> OK | H4: =countif($D4,"*"&H$2&"*") -> 1 | I4: =countif($D4,"*"&I$2&"*") -> 0 | J4: =countif($D4,"*"&J$2&"*") -> 0 | K4: =countif($D4,"*"&K$2&"*") -> 0 | L4: =countif($D4,"*"&L$2&"*") -> 0 | M4: =countif($D4,"*"&M$2&"*") -> 0 | N4: =countif($D4,"*"&N$2&"*") -> 0 | O4: =countif($D4,"*"&O$2&"*") -> 0 | P4: =IF(OR(AV4=1,AW4=1),1,0) -> 0 | Q4: =countif($D4,"*"&Q$2&"*") -> 0 | R4: =countif($D4,"*"&R$2&"*") -> 0 | S4: =countif($D4,"*"&S$2&"*") -> 0 | T4: =countif($D4,"*"&T$2&"*") -> 0 | U4: =countif($D4,"*"&U$2&"*") -> 0 | V4: =countif($D4,"*"&V$2&"*") -> 0 | W4: =countif($D4,"*"&W$2&"*") -> 0 | X4: =countif($D4,"*"&X$2&"*") -> 0 | ... AC4: =countif($D4,"*"&AC$2&"*") -> 0 | AD4: =IF(OR(AT4=1,AU4=1),1,0) -> 0 | AE4: =countif($D4,"*"&AE$2&"*") -> 0 | AF4: =countif($D4,"*"&AF$2&"*") -> 0 | AG4: =countif($D4,"*"&AG$2&"*") -> 0 | AH4: =IF(D4<>"",IF(SUM(H4:AG4,T4)=0,1,0),0) -> 0 | AI4: =IF(OR(AX4=1,AY4=1),1,0) -> 1 | AJ4: =SUM(AK4:AR4) -> 0 | AK4: =countif($D4,"*"&AK$2&"*") -> 0 | AL4: =countif($D4,"*"&AL$2&"*") -> 0 | AM4: =countif($D4,"*"&AM$2&"*") -> 0 | AN4: =countif($D4,"*"&AN$2&"*") -> 0 | AO4: =countif($D4,"*"&AO$2&"*") -> 0 | AP4: =countif($D4,"*"&AP$2&"*") -> 0 | AQ4: =countif($D4,"*"&AQ$2&"*") -> 0 | AR4: =countif($D4,"*"&AR$2&"*") -> 0 | AS4: =countif($D4,"*"&AS$2&"*") -> 0 | AT4: 0 | AU4: =countif($D4,"*"&AU$2&"*") -> 0 | AV4: =countif($D4,"*"&AV$2&"*") -> 0 | AW4: =countif($D4,"*"&AW$2&"*") -> 0 | AX4: =countif($D4,"*"&AX$2&"*") -> 0 | AY4: 1 | BA4: =IF(SUM(H4,I4,J4,K4,L4,M4,N4,O4)>0,BA$2,"") -> Archival | BB4: =IF(SUM(P4,Q4,R4,S4,T4,U4)<>0,BB$2,"") | BC4: =IF(SUM(V4:AC4)<>0,BC$2,"") | BD4: =IF(SUM(AE4,AF4,AD4)<>0,BD$2,"") | BE4: =IF(SUM(AH4,AG4)<>0,BE$2,"") | BF4: =CONCATENATE(BA4:BE4) -> Archival
